Workbook
Name AccountNames: [1]Lists!$B$3:$B$2001
Name CDMQRCentralBPAClarityUploadQuarterlies_1: #REF!
Name CDMQRCentralBPAClarityUploadQuarterlies_1: #REF!
Name CDMQRCentralBPAClarityUploadQuarterlies_1: #REF!
Name CDMQRCentralBPAClarityUploadQuarterlies_1: #REF!
Name CDMQRCentralBPAClarityUploadQuarterlies_1: #REF!
Name CDMQRCentralBPAClarityUploadQuarterlies_1: #REF!
Name CDMQRCentralBPAClarityUploadQuarterlies_1: #REF!
Name CDMQRCentralBPAClarityUploadQuarterlies_1: #REF!
Name CDMQRCentralBPAClarityUploadQuarterlies_1: #REF!
Name CDMQRCentralBPAClarityUploadQuarterlies_1: #REF!
Name CDMQRClarityuploadfileQ316.xlsx_1: #REF!
Name CDMQRClarityuploadfileQ316.xlsx_1: #REF!
Name CDMQRClarityuploadfileQ316.xlsx_1: #REF!
Name CDMQRClarityuploadfileQ316.xlsx_1: #REF!
Name CDMQRClarityuploadfileQ316.xlsx_1: #REF!
Name CDMQRClarityuploadfileQ316.xlsx_1: #REF!
Name CDMQRClarityuploadfileQ316.xlsx_1: #REF!
Name CDMQRClarityuploadfileQ316.xlsx_1: #REF!
Name CDMQRClarityuploadfileQ316.xlsx_1: #REF!
Name CDMQRClarityuploadfileQ316.xlsx_2: #REF!
Name CDMQRClarityuploadfileQ316.xlsx_2: #REF!
Name CDMQRClarityuploadfileQ316.xlsx_2: #REF!
Name CDMQRClarityuploadfileQ316.xlsx_2: #REF!
Name CDMQRClarityuploadfileQ316.xlsx_2: #REF!
Name CDMQRClarityuploadfileQ316.xlsx_2: #REF!
Name CDMQRClarityuploadfileQ316.xlsx_2: #REF!
Name CDMQRClarityuploadfileQ316.xlsx_3: #REF!
Name CDMQRClarityuploadfileQ316.xlsx_3: #REF!
Name CDMQRClarityuploadfileQ316.xlsx_3: #REF!
Name CDMQRClarityuploadfileQ316.xlsx_3: #REF!
Name CDMQRClarityuploadfileQ316.xlsx_3: #REF!
Name CDMQRClarityuploadfileQ316.xlsx_3: #REF!
Name CDMQRClarityuploadfileQ316.xlsx_4: #REF!
Name CDMQRClarityuploadfileQ316.xlsx_4: #REF!
Name CDMQRClarityuploadfileQ316.xlsx_4: #REF!
Name CDMQRClarityuploadfileQ316.xlsx_4: #REF!
Name CDMQRClarityuploadfileQ316.xlsx_4: #REF!
Name CDMQRClarityuploadfileQ316.xlsx_4: #REF!
Name CQtr: #REF!
Name CQtr: #REF!
Name CQtr: #REF!
Name Entity: [1]Lists!$F$3:$F$501
Name OLE_LINK1: 'L&A by product'!#REF!
Name OLE_LINK1: 'L&A by stage'!$A$2
Name OLE_LINK1: 'Margins and balances'!$A$2
Name PPPPPPPQtr: #REF!
Name PPPPPPPQtr: #REF!
Name PPPPPPPQtr: #REF!
Name PPPPPPPQtr: #REF!
Name PPPPPPPQtr: #REF!
Name PPPPPPQtr: #REF!
Name PPPPPPQtr: #REF!
Name PPPPPPQtr: #REF!
Name PPPPPPQtr: #REF!
Name PPPPPPQtr: #REF!
Name PPPPPQtr: #REF!
Name PPPPPQtr: #REF!
Name PPPPPQtr: #REF!
Name PPPPPQtr: #REF!

Sheet YTD Consolidation check 
B1: =CQtr&" YTD" -> #REF! | C1: Group | G1: BUK | J1: CIB | M1: CCP | P1: BI | S1: HO | W1: Cast to Group | Z1: Cast to Core | AC1: CIB+CCP=BI | AF1: Cast to Core
C2: =CQtr&" YTD" -> #REF! | D2: =PPPPQtr&" YTD" -> #REF! | G2: =CQtr&" YTD" -> #REF! | H2: =PPPPQtr&" YTD" -> #REF! | J2: =CQtr&" YTD" -> #REF! | K2: =PPPPQtr&" YTD" -> #REF! | M2: =CQtr&" YTD" -> #REF! | N2: =PPPPQtr&" YTD" -> #REF! | P2: =CQtr&" YTD" -> #REF! | Q2: =PPPPQtr&" YTD" -> #REF! | S2: =CQtr&" YTD" -> #REF! | T2: =PPPPQtr&" YTD" -> #REF! | W2: =CQtr&" YTD" -> #REF! | Y2: =PPPPQtr&" YTD" -> #REF! | AC2: =CQtr&" YTD" -> #REF! | AE2: =PPPPQtr&" YTD" -> #REF!
B3: Total income | C3: ='Group PH'!C4 -> 6283 | D3: ='Group PH'!D4 -> 5252 | G3: ='Barclays UK YTD'!C7 -> 7353 | H3: ='Barclays UK YTD'!D7 -> 7383 | J3: ='Barclays International YTD'!C62 -> 10231 | K3: ='Barclays International YTD'!D62 -> 9765 | M3: ='Barclays International YTD'!C102 -> 4444 | N3: ='Barclays International YTD'!D102 -> 4261 | P3: ='Barclays International YTD'!C8 -> 14675 | Q3: ='Barclays International YTD'!D8 -> 14026 | S3: ='Head Office YTD'!C7 -> -396 | T3: ='Head Office YTD'!D7 -> -273 | W3: =ROUND(G3,0)+ROUND(S3,0)+ROUND(P3,0)-ROUND(C3,0) -> 15349 | Y3: =ROUND(H3,0)+ROUND(T3,0)+ROUND(Q3,0)-ROUND(D3,0) -> 15884 | Z3: =ROUND(H3,0)+ROUND(T3,0)+ROUND(Q3,0)-ROUND(#REF!,0) -> #REF! | AC3: =P3-J3-M3 -> -8.1854523e-12 | AE3: =Q3-K3-N3 -> 0 | AF3: =ROUND(N3,0)+ROUND(Z3,0)+ROUND(W3,0)-ROUND(#REF!,0) -> #REF!
B4: Credit impairment charges and other provisions | C4: ='Group PH'!C5 -> -2115 | D4: ='Group PH'!D5 -> -448 | G4: ='Barclays UK YTD'!C8 -> -712 | H4: ='Barclays UK YTD'!D8 -> -826 | J4: ='Barclays International YTD'!C63 -> -157 | K4: ='Barclays International YTD'!D63 -> 150 | M4: ='Barclays International YTD'!C103 -> -1016 | N4: ='Barclays International YTD'!D103 -> -808 | P4: ='Barclays International YTD'!C9 -> -1173 | Q4: ='Barclays International YTD'!D9 -> -658 | S4: ='Head Office YTD'!C8 -> -27 | T4: ='Head Office YTD'!D8 -> 16 | W4: =ROUND(G4,0)+ROUND(S4,0)+ROUND(P4,0)-ROUND(C4,0) -> 203 | Y4: =ROUND(H4,0)+ROUND(T4,0)+ROUND(Q4,0)-ROUND(D4,0) -> -1020 | Z4: =ROUND(H4,0)+ROUND(T4,0)+ROUND(Q4,0)-ROUND(#REF!,0) -> #REF! | AC4: =P4-J4-M4 -> 0 | AE4: =Q4-K4-N4 -> 0 | AF4: =ROUND(N4,0)+ROUND(Z4,0)+ROUND(W4,0)-ROUND(#REF!,0) -> #REF!
B5: Net operating income | C5: ='Group PH'!C6 -> 4168 | D5: ='Group PH'!D6 -> 4804 | G5: ='Barclays UK YTD'!C9 -> 6641 | H5: ='Barclays UK YTD'!D9 -> 6557 | J5: ='Barclays International YTD'!C64 -> 10074 | K5: ='Barclays International YTD'!D64 -> 9915 | M5: ='Barclays International YTD'!C104 -> 3428 | N5: ='Barclays International YTD'!D104 -> 3453 | P5: ='Barclays International YTD'!C10 -> 13502 | Q5: ='Barclays International YTD'!D10 -> 13368 | S5: ='Head Office YTD'!C9 -> -423 | T5: ='Head Office YTD'!D9 -> -257 | W5: =ROUND(G5,0)+ROUND(S5,0)+ROUND(P5,0)-ROUND(C5,0) -> 15552 | Y5: =ROUND(H5,0)+ROUND(T5,0)+ROUND(Q5,0)-ROUND(D5,0) -> 14864 | Z5: =ROUND(H5,0)+ROUND(T5,0)+ROUND(Q5,0)-ROUND(#REF!,0) -> #REF! | AC5: =P5-J5-M5 -> 0 | AE5: =Q5-K5-N5 -> 0 | AF5: =ROUND(N5,0)+ROUND(Z5,0)+ROUND(W5,0)-ROUND(#REF!,0) -> #REF!
B6: Operating expenses | C6: ='Group PH'!C7 -> -3253 | D6: ='Group PH'!D7 -> -3257 | G6: ='Barclays UK YTD'!C10 -> -3995.6945 | H6: ='Barclays UK YTD'!D10 -> -4075 | J6: ='Barclays International YTD'!C65 -> -6882 | K6: ='Barclays International YTD'!D65 -> -7093 | M6: ='Barclays International YTD'!C105 -> -2281 | N6: ='Barclays International YTD'!D105 -> -2231 | P6: ='Barclays International YTD'!C11 -> -9162.8284 | Q6: ='Barclays International YTD'!D11 -> -9324 | S6: ='Head Office YTD'!C10 -> -200 | T6: ='Head Office YTD'!D10 -> -228 | W6: =ROUND(G6,0)+ROUND(S6,0)+ROUND(P6,0)-ROUND(C6,0) -> -10106 | Y6: =ROUND(H6,0)+ROUND(T6,0)+ROUND(Q6,0)-ROUND(D6,0) -> -10370 | Z6: =ROUND(H6,0)+ROUND(T6,0)+ROUND(Q6,0)-ROUND(#REF!,0) -> #REF! | AC6: =P6-J6-M6 -> 0.17155109 | AE6: =Q6-K6-N6 -> 0 | AF6: =ROUND(N6,0)+ROUND(Z6,0)+ROUND(W6,0)-ROUND(#REF!,0) -> #REF! | AH6: Bank levy
B7: Bank Levy | C7: ='Group PH'!#REF! -> #REF! | D7: ='Group PH'!#REF! -> #REF! | G7: ='Barclays UK YTD'!C11 -> -41 | H7: ='Barclays UK YTD'!D11 -> -46 | J7: ='Barclays International YTD'!C66 -> -156 | K7: ='Barclays International YTD'!D66 -> -188 | M7: ='Barclays International YTD'!C106 -> -18.4 | N7: ='Barclays International YTD'!D106 -> -22 | P7: ='Barclays International YTD'!C12 -> -174.4 | Q7: ='Barclays International YTD'!D12 -> -210 | S7: ='Head Office YTD'!C11 -> -11 | T7: ='Head Office YTD'!D11 -> -13 | W7: =ROUND(G7,0)+ROUND(S7,0)+ROUND(P7,0)-ROUND(C7,0) -> #REF! | Y7: =ROUND(H7,0)+ROUND(T7,0)+ROUND(Q7,0)-ROUND(D7,0) -> #REF! | AC7: =P7-J7-M7 -> 3.1974423e-14 | AE7: =Q7-K7-N7 -> 0
B8: Litigation and conduct | C8: ='Group PH'!C8 -> -10.340854 | D8: ='Group PH'!D8 -> -61 | G8: ='Barclays UK YTD'!C13 -> -1582.3055 | H8: ='Barclays UK YTD'!D13 -> -483 | J8: ='Barclays International YTD'!C68 -> -109.36277 | K8: ='Barclays International YTD'!D68 -> -68 | M8: ='Barclays International YTD'!C108 -> -7.4087847 | N8: ='Barclays International YTD'!D108 -> -59 | P8: ='Barclays International YTD'!C14 -> -115.77155 | Q8: ='Barclays International YTD'!D14 -> -127 | S8: ='Head Office YTD'!C14 -> -151.39434 | T8: ='Head Office YTD'!D14 -> -1597 | W8: =ROUND(G8,0)+ROUND(S8,0)+ROUND(P8,0)-ROUND(C8,0) -> -1839 | Y8: =ROUND(H8,0)+ROUND(T8,0)+ROUND(Q8,0)-ROUND(D8,0) -> -2146 | Z8: =ROUND(H8,0)+ROUND(T8,0)+ROUND(Q8,0)-ROUND(#REF!,0) -> #REF! | AC8: =ROUND(P8,0)-ROUND(J8,0)-ROUND(M8,0) -> 0 | AE8: =Q8-K8-N8 -> 0 | AF8: =ROUND(N8,0)+ROUND(Z8,0)+ROUND(W8,0)-ROUND(#REF!,0) -> #REF!
B9: Total operating expenses | C9: ='Group PH'!C9 -> -3263 | D9: ='Group PH'!D9 -> -3318 | G9: ='Barclays UK YTD'!C14 -> -5619 | H9: ='Barclays UK YTD'!D14 -> -4604 | J9: ='Barclays International YTD'!C69 -> -7147 | K9: ='Barclays International YTD'!D69 -> -7349 | M9: ='Barclays International YTD'!C109 -> -2306 | N9: ='Barclays International YTD'!D109 -> -2312 | P9: ='Barclays International YTD'!C15 -> -9453 | Q9: ='Barclays International YTD'!D15 -> -9661 | S9: ='Head Office YTD'!C15 -> -362 | T9: ='Head Office YTD'!D15 -> -1978 | W9: =ROUND(G9,0)+ROUND(S9,0)+ROUND(P9,0)-ROUND(C9,0) -> -12171 | Y9: =ROUND(H9,0)+ROUND(T9,0)+ROUND(Q9,0)-ROUND(D9,0) -> -12925 | Z9: =ROUND(H9,0)+ROUND(T9,0)+ROUND(Q9,0)-ROUND(#REF!,0) -> #REF! | AC9: =P9-J9-M9 -> 0 | AE9: =Q9-K9-N9 -> 0 | AF9: =ROUND(N9,0)+ROUND(Z9,0)+ROUND(W9,0)-ROUND(#REF!,0) -> #REF!
B10: Other net (expenses)/income | C10: ='Group PH'!C10 -> 8 | D10: ='Group PH'!D10 -> -3 | G10: ='Barclays UK YTD'!C15 -> - | H10: ='Barclays UK YTD'!D15 -> 3 | J10: ='Barclays International YTD'!C70 -> 28 | K10: ='Barclays International YTD'!D70 -> 27 | M10: ='Barclays International YTD'!C110 -> 41 | N10: ='Barclays International YTD'!D110 -> 41 | P10: ='Barclays International YTD'!C16 -> 69 | Q10: ='Barclays International YTD'!D16 -> 68 | S10: ='Head Office YTD'!C16 -> 2 | T10: ='Head Office YTD'!D16 -> -2 | W10: =ROUND(G10,0)+ROUND(S10,0)+ROUND(P10,0)-ROUND(C10,0) -> #VALUE! | Y10: =ROUND(H10,0)+ROUND(T10,0)+ROUND(Q10,0)-ROUND(D10,0) -> 72 | Z10: =ROUND(H10,0)+ROUND(T10,0)+ROUND(Q10,0)-ROUND(#REF!,0) -> #REF! | AC10: =P10-J10-M10 -> 0 | AE10: =Q10-K10-N10 -> 0 | AF10: =ROUND(N10,0)+ROUND(Z10,0)+ROUND(W10,0)-ROUND(#REF!,0) -> #REF!
B11: Profit/(loss) before tax | C11: ='Group PH'!C11 -> 913 | D11: ='Group PH'!D11 -> 1483 | G11: ='Barclays UK YTD'!C16 -> 1022 | H11: ='Barclays UK YTD'!D16 -> 1956 | J11: ='Barclays International YTD'!C71 -> 2955 | K11: ='Barclays International YTD'!D71 -> 2593 | M11: ='Barclays International YTD'!C111 -> 1163 | N11: ='Barclays International YTD'!D111 -> 1182 | P11: ='Barclays International YTD'!C17 -> 4118 | Q11: ='Barclays International YTD'!D17 -> 3775 | S11: ='Head Office YTD'!C17 -> -783 | T11: ='Head Office YTD'!D17 -> -2237 | W11: =ROUND(G11,0)+ROUND(S11,0)+ROUND(P11,0)-ROUND(C11,0) -> 3444 | Y11: =ROUND(H11,0)+ROUND(T11,0)+ROUND(Q11,0)-ROUND(D11,0) -> 2011 | Z11: =ROUND(H11,0)+ROUND(T11,0)+ROUND(Q11,0)-ROUND(#REF!,0) -> #REF! | AC11: =P11-J11-M11 -> 0 | AE11: =Q11-K11-N11 -> 0 | AF11: =ROUND(N11,0)+ROUND(Z11,0)+ROUND(W11,0)-ROUND(#REF!,0) -> #REF!
B12: Attributable profit/(loss)1 | C12: ='Group PH'!C16 -> 605 | D12: ='Group PH'!D16 -> 1038 | G12: ='Barclays UK YTD'!C17 -> 281 | H12: ='Barclays UK YTD'!D17 -> 1198 | J12: ='Barclays International YTD'!C72 -> 1980 | K12: ='Barclays International YTD'!D72 -> 1781 | M12: ='Barclays International YTD'!C112 -> 836 | N12: ='Barclays International YTD'!D112 -> 818 | P12: ='Barclays International YTD'!C18 -> 2816 | Q12: ='Barclays International YTD'!D18 -> 2599 | S12: ='Head Office YTD'!C18 -> -636 | T12: ='Head Office YTD'!D18 -> -2200 | W12: =ROUND(G12,0)+ROUND(S12,0)+ROUND(P12,0)-ROUND(C12,0) -> 1856 | Y12: =ROUND(H12,0)+ROUND(T12,0)+ROUND(Q12,0)-ROUND(D12,0) -> 559 | Z12: =ROUND(H12,0)+ROUND(T12,0)+ROUND(Q12,0)-ROUND(#REF!,0) -> #REF! | AC12: =P12-J12-M12 -> 1.0231815e-12 | AE12: =Q12-K12-N12 -> 0 | AF12: =ROUND(N12,0)+ROUND(Z12,0)+ROUND(W12,0)-ROUND(#REF!,0) -> #REF!
B14: Average tangible shareholders' equity (£bn) | C14: ='Group PH'!C20 -> 46994.626 | D14: ='Group PH'!D20 -> 45200 | G14: ='Barclays UK YTD'!C36 -> 10333.198 | H14: ='Barclays UK YTD'!D36 -> 10000 | J14: ='Barclays International YTD'!C88 -> 25886.815 | K14: ='Barclays International YTD'!D88 -> 26000 | M14: ='Barclays International YTD'!C130 -> 5281.7143 | N14: ='Barclays International YTD'!D130 -> 5000 | P14: ='Barclays International YTD'!C36 -> 31168.529 | Q14: ='Barclays International YTD'!D36 -> 31000 | S14: ='Head Office YTD'!C26 -> 5056.3352 | T14: ='Head Office YTD'!D26 -> 3100 | W14: =ROUND(G14,0)+ROUND(S14,0)+ROUND(P14,0)-ROUND(C14,0) -> -437 | Y14: =ROUND(H14,0)+ROUND(T14,0)+ROUND(Q14,0)-ROUND(D14,0) -> -1100 | Z14: =ROUND(H14,-2)+ROUND(T14,-2)+ROUND(Q14,-2)-ROUND(#REF!,-2) -> #REF! | AC14: =P14-J14-M14 -> 0 | AE14: =Q14-K14-N14 -> 0 | AF14: =ROUND(N14,-2)+ROUND(Z14,-2)+ROUND(W14,-2)-ROUND(#REF!,-2) -> #REF!
B15: Basic earnings/(loss) per share | C15: ='Group PH'!C23 -> 3.5015357 | D15: ='Group PH'!D23 -> 6.1
B17: Profit/(loss) before tax ex L&C | C17: ='Group PH'!C26 -> 923.34085 | D17: ='Group PH'!D26 -> 1544 | G17: ='Barclays UK YTD'!C42 -> 2604.3055 | H17: ='Barclays UK YTD'!D42 -> 2439 | J17: ='Barclays International YTD'!C92 -> 3064.3628 | K17: ='Barclays International YTD'!D92 -> 2661 | M17: ='Barclays International YTD'!C135 -> 1170.4088 | N17: ='Barclays International YTD'!D135 -> 1241 | P17: ='Barclays International YTD'!C42 -> 4233.7716 | Q17: ='Barclays International YTD'!D42 -> 3902 | S17: ='Head Office YTD'!C29 -> -631.60566 | T17: ='Head Office YTD'!D29 -> -640 | W17: =ROUND(G17,0)+ROUND(S17,0)+ROUND(P17,0)-ROUND(C17,0) -> 5283 | Y17: =ROUND(H17,0)+ROUND(T17,0)+ROUND(Q17,0)-ROUND(D17,0) -> 4157 | AC17: =ROUND(P17,0)-ROUND(J17,0)-ROUND(M17,0) -> 0 | AE17: =Q17-K17-N17 -> 0
B18: Attributable profit/(loss) ex L&C | C18: ='Group PH'!C27 -> 604.40094 | D18: ='Group PH'!D27 -> 1084 | G18: ='Barclays UK YTD'!C43 -> 1813.076 | H18: ='Barclays UK YTD'!D43 -> 1670 | J18: ='Barclays International YTD'!C93 -> 2063.5163 | K18: ='Barclays International YTD'!D93 -> 1843 | M18: ='Barclays International YTD'!C136 -> 841.52103 | N18: ='Barclays International YTD'!D136 -> 862 | P18: ='Barclays International YTD'!C43 -> 2906.0373 | Q18: ='Barclays International YTD'!D43 -> 2705 | S18: ='Head Office YTD'!C30 -> -524.84075 | T18: ='Head Office YTD'!D30 -> -642 | W18: =ROUND(G18,0)+ROUND(S18,0)+ROUND(P18,0)-ROUND(C18,0) -> 3590 | Y18: =ROUND(H18,0)+ROUND(T18,0)+ROUND(Q18,0)-ROUND(D18,0) -> 2649 | AC18: =ROUND(P18,0)-ROUND(J18,0)-ROUND(M18,0) -> 0 | AE18: =Q18-K18-N18 -> 0
B19: Post tax L&C impact | C19: ='CYYTD performance measures excl'!G21 -> 1733 | D19: ='PYYTD performance measures'!G21 -> 2136 | G19: ='CYYTD performance measures excl'!B21 -> 1532 | H19: ='PYYTD performance measures'!B21 -> 472 | J19: ='CYYTD performance measures excl'!C21 -> 84 | K19: ='PYYTD performance measures'!C21 -> 62 | M19: ='CYYTD performance measures excl'!D21 -> 6 | N19: ='PYYTD performance measures'!D21 -> 44 | P19: ='CYYTD performance measures excl'!E21 -> 90 | Q19: ='PYYTD performance measures'!E21 -> 106 | S19: ='CYYTD performance measures excl'!F21 -> 111 | T19: ='PYYTD performance measures'!F21 -> 1558 | W19: =ROUND(G19,0)+ROUND(S19,0)+ROUND(P19,0)-ROUND(C19,0) -> 0 | Y19: =ROUND(H19,0)+ROUND(T19,0)+ROUND(Q19,0)-ROUND(D19,0) -> 0 | AC19: =P19-J19-M19 -> 0 | AE19: =Q19-K19-N19 -> 0
B21: Total assets | C21: ='Group Qrtly'!C38 -> 1444297 | D21: ='Group Qrtly'!H38 -> 1193543 | G21: ='Barclays UK YTD'!C21 -> 257776 | H21: ='Barclays UK YTD'!D21 -> 249700 | J21: ='Barclays International YTD'!C81 -> 795600 | K21: ='Barclays International YTD'!D81 -> 790500 | M21: ='Barclays International YTD'!C116 -> 65800 | N21: ='Barclays International YTD'!D116 -> 71600 | P21: ='Barclays International YTD'!C27 -> 861400 | Q21: ='Barclays International YTD'!D27 -> 862100 | S21: ='Head Office YTD'!C21 -> 21040 | T21: ='Head Office YTD'!D21 -> 21500 | W21: =ROUND(G21,-2)+ROUND(S21,-2)+ROUND(P21,-2)-ROUND(C21,-2) -> -304100 | Y21: =ROUND(H21,-2)+ROUND(T21,-2)+ROUND(Q21,-2)-ROUND(D21,-2) -> -60200 | Z21: =ROUND(H21,-3)+ROUND(T21,-3)+ROUND(Q21,-3)-ROUND(#REF!,-3) -> #REF! | AC21: =P21-J21-M21 -> 0 | AE21: =Q21-K21-N21 -> 0 | AF21: =ROUND(N21,-3)+ROUND(Z21,-3)+ROUND(W21,-3)-ROUND(#REF!,-3) -> #REF!
B22: Risk weighted assets | C22: ='Group PH'!C37 -> 325631 | D22: ='Group PH'!D37 -> 295131.09 | G22: ='Barclays UK YTD'!C24 -> 74900.809 | H22: ='Barclays UK YTD'!D24 -> 75200 | J22: ='Barclays International YTD'!C84 -> 171452.99 | K22: ='Barclays International YTD'!D84 -> 170900 | M22: ='Barclays International YTD'!C118 -> 37690.31 | N22: ='Barclays International YTD'!D118 -> 39800 | P22: ='Barclays International YTD'!C31 -> 209243.3 | Q22: ='Barclays International YTD'!D31 -> 210741 | S22: ='Head Office YTD'!C22 -> 10986.984 | T22: ='Head Office YTD'!D22 -> 26000 | W22: =ROUND(G22,-2)+ROUND(S22,-2)+ROUND(P22,-2)-ROUND(C22,-2) -> -30500 | Y22: =ROUND(H22,-2)+ROUND(T22,-2)+ROUND(Q22,-2)-ROUND(D22,-2) -> 16800 | AC22: =P22-J22-M22 -> 100 | AE22: =Q22-K22-N22 -> 41
B23: Average UK leverage exposure | C23: ='Group PH'!#REF! -> #REF! | D23: ='Group PH'!#REF! -> #REF! | Z23: =ROUND(H23,-3)+ROUND(T23,-3)+ROUND(Q23,-3)-ROUND(#REF!,-3) -> #REF! | AF23: =ROUND(N23,-3)+ROUND(Z23,-3)+ROUND(W23,-3)-ROUND(#REF!,-3) -> #REF!
B29: Quarterly pages
B31: =CQtr&" YTD" -> #REF! | C31: Group | G31: BUK | J31: CIB | M31: CCP | P31: BI | S31: HO | W31: Cast to Group | Z31: Cast to Core | AC31: CIB+CCP=BI | AF31: Cast to Core
C32: =CQtr&" YTD" -> #REF! | D32: =PPPPQtr&" YTD" -> #REF! | G32: =CQtr&" YTD" -> #REF! | H32: =PPPPQtr&" YTD" -> #REF! | J32: =CQtr&" YTD" -> #REF! | K32: =PPPPQtr&" YTD" -> #REF! | M32: =CQtr&" YTD" -> #REF! | N32: =PPPPQtr&" YTD" -> #REF! | P32: =CQtr&" YTD" -> #REF! | Q32: =PPPPQtr&" YTD" -> #REF! | S32: =CQtr&" YTD" -> #REF! | T32: =PPPPQtr&" YTD" -> #REF! | W32: =CQtr&" YTD" -> #REF! | Y32: =PPPPQtr&" YTD" -> #REF!
B33: Total income | C33: =ROUND('Group Qrtly'!C6,0)+ROUND('Group Qrtly'!E6,0)+ROUND('Group Qrtly'!F6,0)+ROUND('Group Qrtly'!G6,0) -> 22663 | D33: =ROUND('Group Qrtly'!H6,0)+ROUND('Group Qrtly'!J6,0)+ROUND('Group Qrtly'!K6,0)+ROUND('Group Qrtly'!L6,0) -> 21030 | G33: =ROUND('Barclays UK Qrtly'!C7,0)+ROUND('Barclays UK Qrtly'!E7,0)+ROUND('Barclays UK Qrtly'!F7,0)+ROUND('Barclays UK Qrtly'!G7,0) -> 7280 | H33: =ROUND('Barclays UK Qrtly'!H7,0)+ROUND('Barclays UK Qrtly'!J7,0)+ROUND('Barclays UK Qrtly'!K7,0)+ROUND('Barclays UK Qrtly'!L7,0) -> 7372 | J33: =ROUND('Barclays International Qrtly'!C64,0)+ROUND('Barclays International Qrtly'!E64,0)+ROUND('Barclays International Qrtly'!F64,0)+ROUND('Barclays International Qrtly'!G64,0) -> 11343 | K33: =ROUND('Barclays International Qrtly'!H64,0)+ROUND('Barclays International Qrtly'!J64,0)+ROUND('Barclays International Qrtly'!K64,0)+ROUND('Barclays International Qrtly'!L64,0) -> 9471 | M33: =ROUND('Barclays International Qrtly'!C105,0)+ROUND('Barclays International Qrtly'!E105,0)+ROUND('Barclays International Qrtly'!F105,0)+ROUND('Barclays International Qrtly'!G105,0) -> 4406 | N33: =ROUND('Barclays International Qrtly'!H105,0)+ROUND('Barclays International Qrtly'!J105,0)+ROUND('Barclays International Qrtly'!K105,0)+ROUND('Barclays International Qrtly'!L105,0) -> 4317 | P33: =ROUND('Barclays International Qrtly'!C8,0)+ROUND('Barclays International Qrtly'!E8,0)+ROUND('Barclays International Qrtly'!F8,0)+ROUND('Barclays International Qrtly'!G8,0) -> 15749 | Q33: =ROUND('Barclays International Qrtly'!H8,0)+ROUND('Barclays International Qrtly'!J8,0)+ROUND('Barclays International Qrtly'!K8,0)+ROUND('Barclays International Qrtly'!L8,0) -> 13788 | S33: =ROUND('Head Office Qrtly'!C7,0)+ROUND('Head Office Qrtly'!E7,0)+ROUND('Head Office Qrtly'!F7,0)+ROUND('Head Office Qrtly'!G7,0) -> -366 | T33: =ROUND('Head Office Qrtly'!H7,0)+ROUND('Head Office Qrtly'!J7,0)+ROUND('Head Office Qrtly'!K7,0)+ROUND('Head Office Qrtly'!L7,0) -> -130 | W33: =ROUND(G33,0)+ROUND(S33,0)+ROUND(P33,0)-ROUND(C33,0) -> 0 | Y33: =ROUND(H33,0)+ROUND(T33,0)+ROUND(Q33,0)-ROUND(D33,0) -> 0 | Z33: =ROUND(H33,0)+ROUND(T33,0)+ROUND(Q33,0)-ROUND(#REF!,0) -> #REF! | AC33: =P33-J33-M33 -> 0 | AE33: =Q33-K33-N33 -> 0 | AF33: =ROUND(N33,0)+ROUND(Z33,0)+ROUND(W33,0)-ROUND(#REF!,0) -> #REF!
B34: Credit impairment charges and other provisions | C34: =ROUND('Group Qrtly'!C7,0)+ROUND('Group Qrtly'!E7,0)+ROUND('Group Qrtly'!F7,0)+ROUND('Group Qrtly'!G7,0) -> -3579 | D34: =ROUND('Group Qrtly'!H7,0)+ROUND('Group Qrtly'!J7,0)+ROUND('Group Qrtly'!K7,0)+ROUND('Group Qrtly'!L7,0) -> -1628 | G34: =ROUND('Barclays UK Qrtly'!C8,0)+ROUND('Barclays UK Qrtly'!E8,0)+ROUND('Barclays UK Qrtly'!F8,0)+ROUND('Barclays UK Qrtly'!G8,0) -> -1002 | H34: =ROUND('Barclays UK Qrtly'!H8,0)+ROUND('Barclays UK Qrtly'!J8,0)+ROUND('Barclays UK Qrtly'!K8,0)+ROUND('Barclays UK Qrtly'!L8,0) -> -816 | J34: =ROUND('Barclays International Qrtly'!C65,0)+ROUND('Barclays International Qrtly'!E65,0)+ROUND('Barclays International Qrtly'!F65,0)+ROUND('Barclays International Qrtly'!G65,0) -> -829 | K34: =ROUND('Barclays International Qrtly'!H65,0)+ROUND('Barclays International Qrtly'!J65,0)+ROUND('Barclays International Qrtly'!K65,0)+ROUND('Barclays International Qrtly'!L65,0) -> -61 | M34: =ROUND('Barclays International Qrtly'!C106,0)+ROUND('Barclays International Qrtly'!E106,0)+ROUND('Barclays International Qrtly'!F106,0)+ROUND('Barclays International Qrtly'!G106,0) -> -1708 | N34: =ROUND('Barclays International Qrtly'!H106,0)+ROUND('Barclays International Qrtly'!J106,0)+ROUND('Barclays International Qrtly'!K106,0)+ROUND('Barclays International Qrtly'!L106,0) -> -749 | P34: =ROUND('Barclays International Qrtly'!C9,0)+ROUND('Barclays International Qrtly'!E9,0)+ROUND('Barclays International Qrtly'!F9,0)+ROUND('Barclays International Qrtly'!G9,0) -> -2537 | Q34: =ROUND('Barclays International Qrtly'!H9,0)+ROUND('Barclays International Qrtly'!J9,0)+ROUND('Barclays International Qrtly'!K9,0)+ROUND('Barclays International Qrtly'!L9,0) -> -810 | S34: =ROUND('Head Office Qrtly'!C8,0)+ROUND('Head Office Qrtly'!E8,0)+ROUND('Head Office Qrtly'!F8,0)+ROUND('Head Office Qrtly'!G8,0) -> -40 | T34: =ROUND('Head Office Qrtly'!H8,0)+ROUND('Head Office Qrtly'!J8,0)+ROUND('Head Office Qrtly'!K8,0)+ROUND('Head Office Qrtly'!L8,0) -> -2 | W34: =ROUND(G34,0)+ROUND(S34,0)+ROUND(P34,0)-ROUND(C34,0) -> 0 | Y34: =ROUND(H34,0)+ROUND(T34,0)+ROUND(Q34,0)-ROUND(D34,0) -> 0 | Z34: =ROUND(H34,0)+ROUND(T34,0)+ROUND(Q34,0)-ROUND(#REF!,0) -> #REF! | AC34: =P34-J34-M34 -> 0 | AE34: =Q34-K34-N34 -> 0 | AF34: =ROUND(N34,0)+ROUND(Z34,0)+ROUND(W34,0)-ROUND(#REF!,0) -> #REF!
B35: Net operating income | C35: =ROUND('Group Qrtly'!C8,0)+ROUND('Group Qrtly'!E8,0)+ROUND('Group Qrtly'!F8,0)+ROUND('Group Qrtly'!G8,0) -> 19084 | D35: =ROUND('Group Qrtly'!H8,0)+ROUND('Group Qrtly'!J8,0)+ROUND('Group Qrtly'!K8,0)+ROUND('Group Qrtly'!L8,0) -> 19402 | G35: =ROUND('Barclays UK Qrtly'!C9,0)+ROUND('Barclays UK Qrtly'!E9,0)+ROUND('Barclays UK Qrtly'!F9,0)+ROUND('Barclays UK Qrtly'!G9,0) -> 6278 | H35: =ROUND('Barclays UK Qrtly'!H9,0)+ROUND('Barclays UK Qrtly'!J9,0)+ROUND('Barclays UK Qrtly'!K9,0)+ROUND('Barclays UK Qrtly'!L9,0) -> 6556 | J35: =ROUND('Barclays International Qrtly'!C66,0)+ROUND('Barclays International Qrtly'!E66,0)+ROUND('Barclays International Qrtly'!F66,0)+ROUND('Barclays International Qrtly'!G66,0) -> 10514 | K35: =ROUND('Barclays International Qrtly'!H66,0)+ROUND('Barclays International Qrtly'!J66,0)+ROUND('Barclays International Qrtly'!K66,0)+ROUND('Barclays International Qrtly'!L66,0) -> 9410 | M35: =ROUND('Barclays International Qrtly'!C107,0)+ROUND('Barclays International Qrtly'!E107,0)+ROUND('Barclays International Qrtly'!F107,0)+ROUND('Barclays International Qrtly'!G107,0) -> 2698 | N35: =ROUND('Barclays International Qrtly'!H107,0)+ROUND('Barclays International Qrtly'!J107,0)+ROUND('Barclays International Qrtly'!K107,0)+ROUND('Barclays International Qrtly'!L107,0) -> 3568 | P35: =ROUND('Barclays International Qrtly'!C10,0)+ROUND('Barclays International Qrtly'!E10,0)+ROUND('Barclays International Qrtly'!F10,0)+ROUND('Barclays International Qrtly'!G10,0) -> 13212 | Q35: =ROUND('Barclays International Qrtly'!H10,0)+ROUND('Barclays International Qrtly'!J10,0)+ROUND('Barclays International Qrtly'!K10,0)+ROUND('Barclays International Qrtly'!L10,0) -> 12978 | S35: =ROUND('Head Office Qrtly'!C9,0)+ROUND('Head Office Qrtly'!E9,0)+ROUND('Head Office Qrtly'!F9,0)+ROUND('Head Office Qrtly'!G9,0) -> -406 | T35: =ROUND('Head Office Qrtly'!H9,0)+ROUND('Head Office Qrtly'!J9,0)+ROUND('Head Office Qrtly'!K9,0)+ROUND('Head Office Qrtly'!L9,0) -> -132 | W35: =ROUND(G35,0)+ROUND(S35,0)+ROUND(P35,0)-ROUND(C35,0) -> 0 | Y35: =ROUND(H35,0)+ROUND(T35,0)+ROUND(Q35,0)-ROUND(D35,0) -> 0 | Z35: =ROUND(H35,0)+ROUND(T35,0)+ROUND(Q35,0)-ROUND(#REF!,0) -> #REF! | AC35: =P35-J35-M35 -> 0 | AE35: =Q35-K35-N35 -> 0 | AF35: =ROUND(N35,0)+ROUND(Z35,0)+ROUND(W35,0)-ROUND(#REF!,0) -> #REF!
B36: Operating costs | C36: =ROUND('Group Qrtly'!C9,0)+ROUND('Group Qrtly'!E9,0)+ROUND('Group Qrtly'!F9,0)+ROUND('Group Qrtly'!G9,0) -> -13355 | D36: =ROUND('Group Qrtly'!H9,0)+ROUND('Group Qrtly'!J9,0)+ROUND('Group Qrtly'!K9,0)+ROUND('Group Qrtly'!L9,0) -> -13520 | G36: =ROUND('Barclays UK Qrtly'!C10,0)+ROUND('Barclays UK Qrtly'!E10,0)+ROUND('Barclays UK Qrtly'!F10,0)+ROUND('Barclays UK Qrtly'!G10,0) -> -4020 | H36: =ROUND('Barclays UK Qrtly'!H10,0)+ROUND('Barclays UK Qrtly'!J10,0)+ROUND('Barclays UK Qrtly'!K10,0)+ROUND('Barclays UK Qrtly'!L10,0) -> -4069 | J36: =ROUND('Barclays International Qrtly'!C67,0)+ROUND('Barclays International Qrtly'!E67,0)+ROUND('Barclays International Qrtly'!F67,0)+ROUND('Barclays International Qrtly'!G67,0) -> -6953 | K36: =ROUND('Barclays International Qrtly'!H67,0)+ROUND('Barclays International Qrtly'!J67,0)+ROUND('Barclays International Qrtly'!K67,0)+ROUND('Barclays International Qrtly'!L67,0) -> -6939 | M36: =ROUND('Barclays International Qrtly'!C108,0)+ROUND('Barclays International Qrtly'!E108,0)+ROUND('Barclays International Qrtly'!F108,0)+ROUND('Barclays International Qrtly'!G108,0) -> -2223 | N36: =ROUND('Barclays International Qrtly'!H108,0)+ROUND('Barclays International Qrtly'!J108,0)+ROUND('Barclays International Qrtly'!K108,0)+ROUND('Barclays International Qrtly'!L108,0) -> -2291 | P36: =ROUND('Barclays International Qrtly'!C11,0)+ROUND('Barclays International Qrtly'!E11,0)+ROUND('Barclays International Qrtly'!F11,0)+ROUND('Barclays International Qrtly'!G11,0) -> -9176 | Q36: =ROUND('Barclays International Qrtly'!H11,0)+ROUND('Barclays International Qrtly'!J11,0)+ROUND('Barclays International Qrtly'!K11,0)+ROUND('Barclays International Qrtly'!L11,0) -> -9230 | S36: =ROUND('Head Office Qrtly'!C10,0)+ROUND('Head Office Qrtly'!E10,0)+ROUND('Head Office Qrtly'!F10,0)+ROUND('Head Office Qrtly'!G10,0) -> -159 | T36: =ROUND('Head Office Qrtly'!H10,0)+ROUND('Head Office Qrtly'!J10,0)+ROUND('Head Office Qrtly'!K10,0)+ROUND('Head Office Qrtly'!L10,0) -> -221 | W36: =ROUND(G36,0)+ROUND(S36,0)+ROUND(P36,0)-ROUND(C36,0) -> 0 | Y36: =ROUND(H36,0)+ROUND(T36,0)+ROUND(Q36,0)-ROUND(D36,0) -> 0 | Z36: =ROUND(H36,0)+ROUND(T36,0)+ROUND(Q36,0)-ROUND(#REF!,0) -> #REF! | AC36: =P36-J36-M36 -> 0 | AE36: =Q36-K36-N36 -> 0 | AF36: =ROUND(N36,0)+ROUND(Z36,0)+ROUND(W36,0)-ROUND(#REF!,0) -> #REF!
B37: Bank Levy | C37: =ROUND('Group Qrtly'!C10,0)+ROUND('Group Qrtly'!E10,0)+ROUND('Group Qrtly'!F10,0)+ROUND('Group Qrtly'!G10,0) -> -226 | D37: =ROUND('Group Qrtly'!H10,0)+ROUND('Group Qrtly'!J10,0)+ROUND('Group Qrtly'!K10,0)+ROUND('Group Qrtly'!L10,0) -> -269 | G37: =ROUND('Barclays UK Qrtly'!C11,0)+ROUND('Barclays UK Qrtly'!E11,0)+ROUND('Barclays UK Qrtly'!F11,0)+ROUND('Barclays UK Qrtly'!G11,0) -> -41 | H37: =ROUND('Barclays UK Qrtly'!H11,0)+ROUND('Barclays UK Qrtly'!J11,0)+ROUND('Barclays UK Qrtly'!K11,0)+ROUND('Barclays UK Qrtly'!L11,0) -> -46 | J37: =ROUND('Barclays International Qrtly'!C68,0)+ROUND('Barclays International Qrtly'!E68,0)+ROUND('Barclays International Qrtly'!F68,0)+ROUND('Barclays International Qrtly'!G68,0) -> -156 | K37: =ROUND('Barclays International Qrtly'!H68,0)+ROUND('Barclays International Qrtly'!J68,0)+ROUND('Barclays International Qrtly'!K68,0)+ROUND('Barclays International Qrtly'!L68,0) -> -188 | M37: =ROUND('Barclays International Qrtly'!C109,0)+ROUND('Barclays International Qrtly'!E109,0)+ROUND('Barclays International Qrtly'!F109,0)+ROUND('Barclays International Qrtly'!G109,0) -> -18 | N37: =ROUND('Barclays International Qrtly'!H109,0)+ROUND('Barclays International Qrtly'!J109,0)+ROUND('Barclays International Qrtly'!K109,0)+ROUND('Barclays International Qrtly'!L109,0) -> -22 | P37: =ROUND('Barclays International Qrtly'!C12,0)+ROUND('Barclays International Qrtly'!E12,0)+ROUND('Barclays International Qrtly'!F12,0)+ROUND('Barclays International Qrtly'!G12,0) -> -174 | Q37: =ROUND('Barclays International Qrtly'!H12,0)+ROUND('Barclays International Qrtly'!J12,0)+ROUND('Barclays International Qrtly'!K12,0)+ROUND('Barclays International Qrtly'!L12,0) -> -210 | S37: =ROUND('Head Office Qrtly'!C11,0)+ROUND('Head Office Qrtly'!E11,0)+ROUND('Head Office Qrtly'!F11,0)+ROUND('Head Office Qrtly'!G11,0) -> -11 | T37: =ROUND('Head Office Qrtly'!H11,0)+ROUND('Head Office Qrtly'!J11,0)+ROUND('Head Office Qrtly'!K11,0)+ROUND('Head Office Qrtly'!L11,0) -> -13 | W37: =ROUND(G37,0)+ROUND(S37,0)+ROUND(P37,0)-ROUND(C37,0) -> 0 | AC37: =P37-J37-M37 -> 0 | AE37: =Q37-K37-N37 -> 0
B38: Litigation and conduct | C38: =ROUND('Group Qrtly'!C13,0)+ROUND('Group Qrtly'!E13,0)+ROUND('Group Qrtly'!F13,0)+ROUND('Group Qrtly'!G13,0) -> -1798 | D38: =ROUND('Group Qrtly'!H13,0)+ROUND('Group Qrtly'!J13,0)+ROUND('Group Qrtly'!K13,0)+ROUND('Group Qrtly'!L13,0) -> -307 | G38: =ROUND('Barclays UK Qrtly'!C13,0)+ROUND('Barclays UK Qrtly'!E13,0)+ROUND('Barclays UK Qrtly'!F13,0)+ROUND('Barclays UK Qrtly'!G13,0) -> -1584 | H38: =ROUND('Barclays UK Qrtly'!H13,0)+ROUND('Barclays UK Qrtly'!J13,0)+ROUND('Barclays UK Qrtly'!K13,0)+ROUND('Barclays UK Qrtly'!L13,0) -> -75 | J38: =ROUND('Barclays International Qrtly'!C70,0)+ROUND('Barclays International Qrtly'!E70,0)+ROUND('Barclays International Qrtly'!F70,0)+ROUND('Barclays International Qrtly'!G70,0) -> -90 | K38: =ROUND('Barclays International Qrtly'!H70,0)+ROUND('Barclays International Qrtly'!J70,0)+ROUND('Barclays International Qrtly'!K70,0)+ROUND('Barclays International Qrtly'!L70,0) -> #VALUE! | M38: =ROUND('Barclays International Qrtly'!C111,0)+ROUND('Barclays International Qrtly'!E111,0)+ROUND('Barclays International Qrtly'!F111,0)+ROUND('Barclays International Qrtly'!G111,0) -> -7 | N38: =ROUND('Barclays International Qrtly'!H111,0)+ROUND('Barclays International Qrtly'!J111,0)+ROUND('Barclays International Qrtly'!K111,0)+ROUND('Barclays International Qrtly'!L111,0) -> -57 | P38: =ROUND('Barclays International Qrtly'!C14,0)+ROUND('Barclays International Qrtly'!E14,0)+ROUND('Barclays International Qrtly'!F14,0)+ROUND('Barclays International Qrtly'!G14,0) -> -97 | Q38: =ROUND('Barclays International Qrtly'!H14,0)+ROUND('Barclays International Qrtly'!J14,0)+ROUND('Barclays International Qrtly'!K14,0)+ROUND('Barclays International Qrtly'!L14,0) -> -131 | S38: =ROUND('Head Office Qrtly'!C14,0)+ROUND('Head Office Qrtly'!E14,0)+ROUND('Head Office Qrtly'!F14,0)+ROUND('Head Office Qrtly'!G14,0) -> -117 | T38: =ROUND('Head Office Qrtly'!H14,0)+ROUND('Head Office Qrtly'!J14,0)+ROUND('Head Office Qrtly'!K14,0)+ROUND('Head Office Qrtly'!L14,0) -> -101 | W38: =ROUND(G38,0)+ROUND(S38,0)+ROUND(P38,0)-ROUND(C38,0) -> 0 | Y38: =ROUND(H38,0)+ROUND(T38,0)+ROUND(Q38,0)-ROUND(D38,0) -> 0 | Z38: =ROUND(H38,0)+ROUND(T38,0)+ROUND(Q38,0)-ROUND(#REF!,0) -> #REF! | AC38: =P38-J38-M38 -> 0 | AE38: =Q38-K38-N38 -> #VALUE! | AF38: =ROUND(N38,0)+ROUND(Z38,0)+ROUND(W38,0)-ROUND(#REF!,0) -> #REF!
B39: Total operating expenses | C39: =ROUND('Group Qrtly'!C14,0)+ROUND('Group Qrtly'!E14,0)+ROUND('Group Qrtly'!F14,0)+ROUND('Group Qrtly'!G14,0) -> -15379 | D39: =ROUND('Group Qrtly'!H14,0)+ROUND('Group Qrtly'!J14,0)+ROUND('Group Qrtly'!K14,0)+ROUND('Group Qrtly'!L14,0) -> -14236 | G39: =ROUND('Barclays UK Qrtly'!C14,0)+ROUND('Barclays UK Qrtly'!E14,0)+ROUND('Barclays UK Qrtly'!F14,0)+ROUND('Barclays UK Qrtly'!G14,0) -> -5645 | H39: =ROUND('Barclays UK Qrtly'!H14,0)+ROUND('Barclays UK Qrtly'!J14,0)+ROUND('Barclays UK Qrtly'!K14,0)+ROUND('Barclays UK Qrtly'!L14,0) -> -4190 | J39: =ROUND('Barclays International Qrtly'!C71,0)+ROUND('Barclays International Qrtly'!E71,0)+ROUND('Barclays International Qrtly'!F71,0)+ROUND('Barclays International Qrtly'!G71,0) -> -7199 | K39: =ROUND('Barclays International Qrtly'!H71,0)+ROUND('Barclays International Qrtly'!J71,0)+ROUND('Barclays International Qrtly'!K71,0)+ROUND('Barclays International Qrtly'!L71,0) -> -7201 | M39: =ROUND('Barclays International Qrtly'!C112,0)+ROUND('Barclays International Qrtly'!E112,0)+ROUND('Barclays International Qrtly'!F112,0)+ROUND('Barclays International Qrtly'!G112,0) -> -2248 | N39: =ROUND('Barclays International Qrtly'!H112,0)+ROUND('Barclays International Qrtly'!J112,0)+ROUND('Barclays International Qrtly'!K112,0)+ROUND('Barclays International Qrtly'!L112,0) -> -2370 | P39: =ROUND('Barclays International Qrtly'!C15,0)+ROUND('Barclays International Qrtly'!E15,0)+ROUND('Barclays International Qrtly'!F15,0)+ROUND('Barclays International Qrtly'!G15,0) -> -9447 | Q39: =ROUND('Barclays International Qrtly'!H15,0)+ROUND('Barclays International Qrtly'!J15,0)+ROUND('Barclays International Qrtly'!K15,0)+ROUND('Barclays International Qrtly'!L15,0) -> -9571 | S39: =ROUND('Head Office Qrtly'!C15,0)+ROUND('Head Office Qrtly'!E15,0)+ROUND('Head Office Qrtly'!F15,0)+ROUND('Head Office Qrtly'!G15,0) -> -287 | T39: =ROUND('Head Office Qrtly'!H15,0)+ROUND('Head Office Qrtly'!J15,0)+ROUND('Head Office Qrtly'!K15,0)+ROUND('Head Office Qrtly'!L15,0) -> -475 | W39: =ROUND(G39,0)+ROUND(S39,0)+ROUND(P39,0)-ROUND(C39,0) -> 0 | Y39: =ROUND(H39,0)+ROUND(T39,0)+ROUND(Q39,0)-ROUND(D39,0) -> 0 | Z39: =ROUND(H39,0)+ROUND(T39,0)+ROUND(Q39,0)-ROUND(#REF!,0) -> #REF! | AC39: =P39-J39-M39 -> 0 | AE39: =Q39-K39-N39 -> 0 | AF39: =ROUND(N39,0)+ROUND(Z39,0)+ROUND(W39,0)-ROUND(#REF!,0) -> #REF!
B40: Other net (expenses)/income | C40: =ROUND('Group Qrtly'!C15,0)+ROUND('Group Qrtly'!E15,0)+ROUND('Group Qrtly'!F15,0)+ROUND('Group Qrtly'!G15,0) -> 82 | D40: =ROUND('Group Qrtly'!H15,0)+ROUND('Group Qrtly'!J15,0)+ROUND('Group Qrtly'!K15,0)+ROUND('Group Qrtly'!L15,0) -> 47 | G40: =ROUND('Barclays UK Qrtly'!C15,0)+ROUND('Barclays UK Qrtly'!E15,0)+ROUND('Barclays UK Qrtly'!F15,0)+ROUND('Barclays UK Qrtly'!G15,0) -> #VALUE! | H40: =ROUND('Barclays UK Qrtly'!H15,0)+ROUND('Barclays UK Qrtly'!J15,0)+ROUND('Barclays UK Qrtly'!K15,0)+ROUND('Barclays UK Qrtly'!L15,0) -> 5 | J40: =ROUND('Barclays International Qrtly'!C72,0)+ROUND('Barclays International Qrtly'!E72,0)+ROUND('Barclays International Qrtly'!F72,0)+ROUND('Barclays International Qrtly'!G72,0) -> 16 | K40: =ROUND('Barclays International Qrtly'!H72,0)+ROUND('Barclays International Qrtly'!J72,0)+ROUND('Barclays International Qrtly'!K72,0)+ROUND('Barclays International Qrtly'!L72,0) -> 36 | M40: =ROUND('Barclays International Qrtly'!C113,0)+ROUND('Barclays International Qrtly'!E113,0)+ROUND('Barclays International Qrtly'!F113,0)+ROUND('Barclays International Qrtly'!G113,0) -> 41 | N40: =ROUND('Barclays International Qrtly'!H113,0)+ROUND('Barclays International Qrtly'!J113,0)+ROUND('Barclays International Qrtly'!K113,0)+ROUND('Barclays International Qrtly'!L113,0) -> 37 | P40: =ROUND('Barclays International Qrtly'!C16,0)+ROUND('Barclays International Qrtly'!E16,0)+ROUND('Barclays International Qrtly'!F16,0)+ROUND('Barclays International Qrtly'!G16,0) -> 57 | Q40: =ROUND('Barclays International Qrtly'!H16,0)+ROUND('Barclays International Qrtly'!J16,0)+ROUND('Barclays International Qrtly'!K16,0)+ROUND('Barclays International Qrtly'!L16,0) -> 73 | S40: =ROUND('Head Office Qrtly'!C16,0)+ROUND('Head Office Qrtly'!E16,0)+ROUND('Head Office Qrtly'!F16,0)+ROUND('Head Office Qrtly'!G16,0) -> 26 | T40: =ROUND('Head Office Qrtly'!H16,0)+ROUND('Head Office Qrtly'!J16,0)+ROUND('Head Office Qrtly'!K16,0)+ROUND('Head Office Qrtly'!L16,0) -> -31 | W40: =ROUND(G40,0)+ROUND(S40,0)+ROUND(P40,0)-ROUND(C40,0) -> #VALUE! | Y40: =ROUND(H40,0)+ROUND(T40,0)+ROUND(Q40,0)-ROUND(D40,0) -> 0 | AC40: =P40-J40-M40 -> 0 | AE40: =Q40-K40-N40 -> 0
B41: Profit/(loss) before tax | C41: =ROUND('Group Qrtly'!C16,0)+ROUND('Group Qrtly'!E16,0)+ROUND('Group Qrtly'!F16,0)+ROUND('Group Qrtly'!G16,0) -> 3787 | D41: =ROUND('Group Qrtly'!H16,0)+ROUND('Group Qrtly'!J16,0)+ROUND('Group Qrtly'!K16,0)+ROUND('Group Qrtly'!L16,0) -> 5213 | G41: =ROUND('Barclays UK Qrtly'!C16,0)+ROUND('Barclays UK Qrtly'!E16,0)+ROUND('Barclays UK Qrtly'!F16,0)+ROUND('Barclays UK Qrtly'!G16,0) -> 632 | H41: =ROUND('Barclays UK Qrtly'!H16,0)+ROUND('Barclays UK Qrtly'!J16,0)+ROUND('Barclays UK Qrtly'!K16,0)+ROUND('Barclays UK Qrtly'!L16,0) -> 2371 | J41: =ROUND('Barclays International Qrtly'!C73,0)+ROUND('Barclays International Qrtly'!E73,0)+ROUND('Barclays International Qrtly'!F73,0)+ROUND('Barclays International Qrtly'!G73,0) -> 3331 | K41: =ROUND('Barclays International Qrtly'!H73,0)+ROUND('Barclays International Qrtly'!J73,0)+ROUND('Barclays International Qrtly'!K73,0)+ROUND('Barclays International Qrtly'!L73,0) -> 2245 | M41: =ROUND('Barclays International Qrtly'!C114,0)+ROUND('Barclays International Qrtly'!E114,0)+ROUND('Barclays International Qrtly'!F114,0)+ROUND('Barclays International Qrtly'!G114,0) -> 491 | N41: =ROUND('Barclays International Qrtly'!H114,0)+ROUND('Barclays International Qrtly'!J114,0)+ROUND('Barclays International Qrtly'!K114,0)+ROUND('Barclays International Qrtly'!L114,0) -> 1235 | P41: =ROUND('Barclays International Qrtly'!C17,0)+ROUND('Barclays International Qrtly'!E17,0)+ROUND('Barclays International Qrtly'!F17,0)+ROUND('Barclays International Qrtly'!G17,0) -> 3822 | Q41: =ROUND('Barclays International Qrtly'!H17,0)+ROUND('Barclays International Qrtly'!J17,0)+ROUND('Barclays International Qrtly'!K17,0)+ROUND('Barclays International Qrtly'!L17,0) -> 3480 | S41: =ROUND('Head Office Qrtly'!C17,0)+ROUND('Head Office Qrtly'!E17,0)+ROUND('Head Office Qrtly'!F17,0)+ROUND('Head Office Qrtly'!G17,0) -> -667 | T41: =ROUND('Head Office Qrtly'!H17,0)+ROUND('Head Office Qrtly'!J17,0)+ROUND('Head Office Qrtly'!K17,0)+ROUND('Head Office Qrtly'!L17,0) -> -638 | W41: =ROUND(G41,0)+ROUND(S41,0)+ROUND(P41,0)-ROUND(C41,0) -> 0 | Y41: =ROUND(H41,0)+ROUND(T41,0)+ROUND(Q41,0)-ROUND(D41,0) -> 0 | Z41: =ROUND(H41,-2)+ROUND(T41,-2)+ROUND(Q41,-2)-ROUND(#REF!,-2) -> #REF! | AC41: =P41-J41-M41 -> 0 | AE41: =Q41-K41-N41 -> 0 | AF41: =ROUND(N41,-2)+ROUND(Z41,-2)+ROUND(W41,-2)-ROUND(#REF!,-2) -> #REF!
B42: Attributable profit/(loss)1 | C42: =ROUND('Group Qrtly'!C21,0)+ROUND('Group Qrtly'!E21,0)+ROUND('Group Qrtly'!F21,0)+ROUND('Group Qrtly'!G21,0) -> 2028 | D42: =ROUND('Group Qrtly'!H21,0)+ROUND('Group Qrtly'!J21,0)+ROUND('Group Qrtly'!K21,0)+ROUND('Group Qrtly'!L21,0) -> 3353 | G42: =ROUND('Barclays UK Qrtly'!C17,0)+ROUND('Barclays UK Qrtly'!E17,0)+ROUND('Barclays UK Qrtly'!F17,0)+ROUND('Barclays UK Qrtly'!G17,0) -> 34 | H42: =ROUND('Barclays UK Qrtly'!H17,0)+ROUND('Barclays UK Qrtly'!J17,0)+ROUND('Barclays UK Qrtly'!K17,0)+ROUND('Barclays UK Qrtly'!L17,0) -> 1646 | J42: =ROUND('Barclays International Qrtly'!C74,0)+ROUND('Barclays International Qrtly'!E74,0)+ROUND('Barclays International Qrtly'!F74,0)+ROUND('Barclays International Qrtly'!G74,0) -> 2218 | K42: =ROUND('Barclays International Qrtly'!H74,0)+ROUND('Barclays International Qrtly'!J74,0)+ROUND('Barclays International Qrtly'!K74,0)+ROUND('Barclays International Qrtly'!L74,0) -> 1529 | M42: =ROUND('Barclays International Qrtly'!C115,0)+ROUND('Barclays International Qrtly'!E115,0)+ROUND('Barclays International Qrtly'!F115,0)+ROUND('Barclays International Qrtly'!G115,0) -> 339 | N42: =ROUND('Barclays International Qrtly'!H115,0)+ROUND('Barclays International Qrtly'!J115,0)+ROUND('Barclays International Qrtly'!K115,0)+ROUND('Barclays International Qrtly'!L115,0) -> 851 | P42: =ROUND('Barclays International Qrtly'!C18,0)+ROUND('Barclays International Qrtly'!E18,0)+ROUND('Barclays International Qrtly'!F18,0)+ROUND('Barclays International Qrtly'!G18,0) -> 2557 | Q42: =ROUND('Barclays International Qrtly'!H18,0)+ROUND('Barclays International Qrtly'!J18,0)+ROUND('Barclays International Qrtly'!K18,0)+ROUND('Barclays International Qrtly'!L18,0) -> 2380 | S42: =ROUND('Head Office Qrtly'!C18,0)+ROUND('Head Office Qrtly'!E18,0)+ROUND('Head Office Qrtly'!F18,0)+ROUND('Head Office Qrtly'!G18,0) -> -563 | T42: =ROUND('Head Office Qrtly'!H18,0)+ROUND('Head Office Qrtly'!J18,0)+ROUND('Head Office Qrtly'!K18,0)+ROUND('Head Office Qrtly'!L18,0) -> -673 | W42: =ROUND(G42,0)+ROUND(S42,0)+ROUND(P42,0)-ROUND(C42,0) -> 0 | Y42: =ROUND(H42,0)+ROUND(T42,0)+ROUND(Q42,0)-ROUND(D42,0) -> 0 | AC42: =P42-J42-M42 -> 0 | AE42: =Q42-K42-N42 -> 0
B44: Average tangible shareholders' equity (£bn) | C44: =('Group Qrtly'!C25+'Group Qrtly'!E25+'Group Qrtly'!F25+'Group Qrtly'!G25)/4 -> 46995.033 | D44: =('Group Qrtly'!H25+'Group Qrtly'!J25+'Group Qrtly'!K25+'Group Qrtly'!L25)/4 -> 44423.09 | G44: =('Barclays UK Qrtly'!C29+'Barclays UK Qrtly'!E29+'Barclays UK Qrtly'!F29+'Barclays UK Qrtly'!G29)/4 -> 10374.568 | H44: =('Barclays UK Qrtly'!H29+'Barclays UK Qrtly'!J29+'Barclays UK Qrtly'!K29+'Barclays UK Qrtly'!L29)/4 -> 10167.484 | J44: =('Barclays International Qrtly'!C90+'Barclays International Qrtly'!E90+'Barclays International Qrtly'!F90+'Barclays International Qrtly'!G90)/4 -> 26433.913 | K44: =('Barclays International Qrtly'!H90+'Barclays International Qrtly'!J90+'Barclays International Qrtly'!K90+'Barclays International Qrtly'!L90)/4 -> 25844.157 | M44: =('Barclays International Qrtly'!C125+'Barclays International Qrtly'!E125+'Barclays International Qrtly'!F125+'Barclays International Qrtly'!G125)/4 -> 5227.6167 | N44: =('Barclays International Qrtly'!H125+'Barclays International Qrtly'!J125+'Barclays International Qrtly'!K125+'Barclays International Qrtly'!L125)/4 -> 5199.484 | P44: =('Barclays International Qrtly'!C36+'Barclays International Qrtly'!E36+'Barclays International Qrtly'!F36+'Barclays International Qrtly'!G36)/4 -> 31624.77 | Q44: =('Barclays International Qrtly'!H36+'Barclays International Qrtly'!J36+'Barclays International Qrtly'!K36+'Barclays International Qrtly'!L36)/4 -> 31068.641 | S44: =('Head Office Qrtly'!C26+'Head Office Qrtly'!E26+'Head Office Qrtly'!F26+'Head Office Qrtly'!G26)/4 -> 5006.9443 | T44: =('Head Office Qrtly'!H26+'Head Office Qrtly'!J26+'Head Office Qrtly'!K26+'Head Office Qrtly'!L26)/4 -> 3157.1485 | W44: =ROUND(G44,-2)+ROUND(S44,-2)+ROUND(P44,-2)-ROUND(C44,-2) -> 0 | Y44: =ROUND(H44,-1)+ROUND(T44,-1)+ROUND(Q44,-1)-ROUND(D44,-1) -> -20 | AC44: =P44-J44-M44 -> -36.758971 | AE44: =Q44-K44-N44 -> 25
B45: Basic earnings/(loss) per share | C45: ='Group Qrtly'!C28+'Group Qrtly'!E28+'Group Qrtly'!F28+'Group Qrtly'!G28 -> 11.770129
B47: Profit/(loss) before tax ex L&C | C47: =ROUND('Group Qrtly'!C31,0)+ROUND('Group Qrtly'!E31,0)+ROUND('Group Qrtly'!F31,0)+ROUND('Group Qrtly'!G31,0) -> 5585 | D47: =ROUND('Group Qrtly'!H31,0)+ROUND('Group Qrtly'!J31,0)+ROUND('Group Qrtly'!K31,0)+ROUND('Group Qrtly'!L31,0) -> 5520 | G47: =ROUND('Barclays UK Qrtly'!C35,0)+ROUND('Barclays UK Qrtly'!E35,0)+ROUND('Barclays UK Qrtly'!F35,0)+ROUND('Barclays UK Qrtly'!G35,0) -> 2216 | H47: =ROUND('Barclays UK Qrtly'!H35,0)+ROUND('Barclays UK Qrtly'!J35,0)+ROUND('Barclays UK Qrtly'!K35,0)+ROUND('Barclays UK Qrtly'!L35,0) -> 2446 | J47: =ROUND('Barclays International Qrtly'!C94,0)+ROUND('Barclays International Qrtly'!E94,0)+ROUND('Barclays International Qrtly'!F94,0)+ROUND('Barclays International Qrtly'!G94,0) -> 3421 | K47: =ROUND('Barclays International Qrtly'!H94,0)+ROUND('Barclays International Qrtly'!J94,0)+ROUND('Barclays International Qrtly'!K94,0)+ROUND('Barclays International Qrtly'!L94,0) -> 2319 | M47: =ROUND('Barclays International Qrtly'!C130,0)+ROUND('Barclays International Qrtly'!E130,0)+ROUND('Barclays International Qrtly'!F130,0)+ROUND('Barclays International Qrtly'!G130,0) -> 498 | N47: =ROUND('Barclays International Qrtly'!H130,0)+ROUND('Barclays International Qrtly'!J130,0)+ROUND('Barclays International Qrtly'!K130,0)+ROUND('Barclays International Qrtly'!L130,0) -> 1292 | P47: =ROUND('Barclays International Qrtly'!C42,0)+ROUND('Barclays International Qrtly'!E42,0)+ROUND('Barclays International Qrtly'!F42,0)+ROUND('Barclays International Qrtly'!G42,0) -> 3919 | Q47: =ROUND('Barclays International Qrtly'!H42,0)+ROUND('Barclays International Qrtly'!J42,0)+ROUND('Barclays International Qrtly'!K42,0)+ROUND('Barclays International Qrtly'!L42,0) -> 3611 | S47: =ROUND('Head Office Qrtly'!C29,0)+ROUND('Head Office Qrtly'!E29,0)+ROUND('Head Office Qrtly'!F29,0)+ROUND('Head Office Qrtly'!G29,0) -> -550 | T47: =ROUND('Head Office Qrtly'!H29,0)+ROUND('Head Office Qrtly'!J29,0)+ROUND('Head Office Qrtly'!K29,0)+ROUND('Head Office Qrtly'!L29,0) -> -537 | W47: =ROUND(G47,0)+ROUND(S47,0)+ROUND(P47,0)-ROUND(C47,0) -> 0 | Y47: =ROUND(H47,0)+ROUND(T47,0)+ROUND(Q47,0)-ROUND(D47,0) -> 0 | AC47: =P47-J47-M47 -> 0 | AE47: =Q47-K47-N47 -> 0
B48: Attributable profit/(loss) ex L&C | C48: =ROUND('Group Qrtly'!C32,0)+ROUND('Group Qrtly'!E32,0)+ROUND('Group Qrtly'!F32,0)+ROUND('Group Qrtly'!G32,0) -> 3714 | D48: =ROUND('Group Qrtly'!H32,0)+ROUND('Group Qrtly'!J32,0)+ROUND('Group Qrtly'!K32,0)+ROUND('Group Qrtly'!L32,0) -> 3605 | G48: =ROUND('Barclays UK Qrtly'!C36,0)+ROUND('Barclays UK Qrtly'!E36,0)+ROUND('Barclays UK Qrtly'!F36,0)+ROUND('Barclays UK Qrtly'!G36,0) -> 1567 | H48: =ROUND('Barclays UK Qrtly'!H36,0)+ROUND('Barclays UK Qrtly'!J36,0)+ROUND('Barclays UK Qrtly'!K36,0)+ROUND('Barclays UK Qrtly'!L36,0) -> 1709 | J48: =ROUND('Barclays International Qrtly'!C95,0)+ROUND('Barclays International Qrtly'!E95,0)+ROUND('Barclays International Qrtly'!F95,0)+ROUND('Barclays International Qrtly'!G95,0) -> 2286 | K48: =ROUND('Barclays International Qrtly'!H95,0)+ROUND('Barclays International Qrtly'!J95,0)+ROUND('Barclays International Qrtly'!K95,0)+ROUND('Barclays International Qrtly'!L95,0) -> 1597 | M48: =ROUND('Barclays International Qrtly'!C131,0)+ROUND('Barclays International Qrtly'!E131,0)+ROUND('Barclays International Qrtly'!F131,0)+ROUND('Barclays International Qrtly'!G131,0) -> 345 | N48: =ROUND('Barclays International Qrtly'!H131,0)+ROUND('Barclays International Qrtly'!J131,0)+ROUND('Barclays International Qrtly'!K131,0)+ROUND('Barclays International Qrtly'!L131,0) -> 893 | P48: =ROUND('Barclays International Qrtly'!C43,0)+ROUND('Barclays International Qrtly'!E43,0)+ROUND('Barclays International Qrtly'!F43,0)+ROUND('Barclays International Qrtly'!G43,0) -> 2631 | Q48: =ROUND('Barclays International Qrtly'!H43,0)+ROUND('Barclays International Qrtly'!J43,0)+ROUND('Barclays International Qrtly'!K43,0)+ROUND('Barclays International Qrtly'!L43,0) -> 2490 | S48: =ROUND('Head Office Qrtly'!C30,0)+ROUND('Head Office Qrtly'!E30,0)+ROUND('Head Office Qrtly'!F30,0)+ROUND('Head Office Qrtly'!G30,0) -> -484 | T48: =ROUND('Head Office Qrtly'!H30,0)+ROUND('Head Office Qrtly'!J30,0)+ROUND('Head Office Qrtly'!K30,0)+ROUND('Head Office Qrtly'!L30,0) -> -594 | W48: =ROUND(G76,0)+ROUND(S76,0)+ROUND(P76,0)-ROUND(C76,0) -> 5283 | Y48: =ROUND(H76,0)+ROUND(T76,0)+ROUND(Q76,0)-ROUND(D76,0) -> 4157 | Z48: =ROUND(H76,-3)+ROUND(T76,-3)+ROUND(Q76,-3)-ROUND(#REF!,-3) -> #REF! | AC48: =P48-J48-M48 -> 0 | AE48: =Q48-K48-N48 -> 0 | AF48: =ROUND(N76,-3)+ROUND(Z76,-3)+ROUND(W76,-3)-ROUND(#REF!,-3) -> #REF!
B49: Post tax L&C impact | C49: =ROUND('Group performance measures excl'!B21,0)+ROUND('Group performance measures excl'!D21,0)+ROUND('Group performance measures excl'!E21,0)+ROUND('Group performance measures excl'!F21,0) -> 1686 | D49: =ROUND('Group performance measures excl'!G21,0)+ROUND('Group performance measures excl'!I21,0)+ROUND('Group performance measures excl'!J21,0)+ROUND('Group performance measures excl'!K21,0) -> 252 | G49: =ROUND('BUK performance measures excl'!B19,0)+ROUND('BUK performance measures excl'!D19,0)+ROUND('BUK performance measures excl'!E19,0)+ROUND('BUK performance measures excl'!F19,0) -> 1533 | H49: =ROUND('BUK performance measures excl'!G19,0)+ROUND('BUK performance measures excl'!I19,0)+ROUND('BUK performance measures excl'!J19,0)+ROUND('BUK performance measures excl'!K19,0) -> 63 | J49: =ROUND('BI performance measures excl'!B48,0)+ROUND('BI performance measures excl'!D48,0)+ROUND('BI performance measures excl'!E48,0)+ROUND('BI performance measures excl'!F48,0) -> 68 | K49: =ROUND('BI performance measures excl'!G48,0)+ROUND('BI performance measures excl'!I48,0)+ROUND('BI performance measures excl'!J48,0)+ROUND('BI performance measures excl'!K48,0) -> 68 | M49: =ROUND('BI performance measures excl'!B77,0)+ROUND('BI performance measures excl'!D77,0)+ROUND('BI performance measures excl'!E77,0)+ROUND('BI performance measures excl'!F77,0) -> 6 | N49: =ROUND('BI performance measures excl'!G77,0)+ROUND('BI performance measures excl'!I77,0)+ROUND('BI performance measures excl'!J77,0)+ROUND('BI performance measures excl'!K77,0) -> 42 | P49: =ROUND('BI performance measures excl'!B19,0)+ROUND('BI performance measures excl'!D19,0)+ROUND('BI performance measures excl'!E19,0)+ROUND('BI performance measures excl'!F19,0) -> 74 | Q49: =ROUND('BI performance measures excl'!G19,0)+ROUND('BI performance measures excl'!I19,0)+ROUND('BI performance measures excl'!J19,0)+ROUND('BI performance measures excl'!K19,0) -> 110 | S49: =ROUND('HO performance measures excl'!B10,0)+ROUND('HO performance measures excl'!D10,0)+ROUND('HO performance measures excl'!E10,0)+ROUND('HO performance measures excl'!F10,0) -> 79 | T49: =ROUND('HO performance measures excl'!G10,0)+ROUND('HO performance measures excl'!I10,0)+ROUND('HO performance measures excl'!J10,0)+ROUND('HO performance measures excl'!K10,0) -> 79 | W49: =ROUND(G49,0)+ROUND(S49,0)+ROUND(P49,0)-ROUND(C49,0) -> 0 | Y49: =ROUND(H49,0)+ROUND(T49,0)+ROUND(Q49,0)-ROUND(D49,0) -> 0 | AC49: =P49-J49-M49 -> 0 | AE49: =Q49-K49-N49 -> 0
Z50: =ROUND(H50,-3)+ROUND(T50,-3)+ROUND(Q50,-3)-ROUND(#REF!,-3) -> #REF! | AF50: =ROUND(N50,-3)+ROUND(Z50,-3)+ROUND(W50,-3)-ROUND(#REF!,-3) -> #REF!
B51: Total assets | C51: ='Group Qrtly'!C38 -> 1444297 | D51: ='Group Qrtly'!H38 -> 1193543 | G51: ='Barclays UK Qrtly'!C21 -> 267542 | H51: ='Barclays UK Qrtly'!H21 -> 253086 | J51: ='Barclays International Qrtly'!C83 -> 1082486 | K51: ='Barclays International Qrtly'!H83 -> 838100 | M51: ='Barclays International Qrtly'!C119 -> 70715 | N51: ='Barclays International Qrtly'!H119 -> 80900 | P51: ='Barclays International Qrtly'!C27 -> 1153201 | Q51: ='Barclays International Qrtly'!H27 -> 918950 | S51: ='Head Office Qrtly'!C21 -> 23554 | T51: ='Head Office Qrtly'!H21 -> 21407 | W51: =ROUND(G51,-2)+ROUND(S51,-2)+ROUND(P51,-2)-ROUND(C51,-2) -> 0 | Y51: =ROUND(H51,-2)+ROUND(T51,-2)+ROUND(Q51,-2)-ROUND(D51,-2) -> 0 | AC51: =P51-J51-M51 -> 0 | AE51: =Q51-K51-N51 -> -50
B52: Risk weighted assets | C52: ='Group Qrtly'!C42 -> 325631 | D52: ='Group Qrtly'!H42 -> 319670.58 | G52: ='Barclays UK Qrtly'!C24 -> 77678 | H52: ='Barclays UK Qrtly'!H24 -> 76558.949 | J52: ='Barclays International Qrtly'!C86 -> 201747 | K52: ='Barclays International Qrtly'!H86 -> 176589.56 | M52: ='Barclays International Qrtly'!C121 -> 36161 | N52: ='Barclays International Qrtly'!H121 -> 39481.377 | P52: ='Barclays International Qrtly'!C31 -> 237908 | Q52: ='Barclays International Qrtly'!H31 -> 216070.94 | S52: ='Head Office Qrtly'!C22 -> 10045 | T52: ='Head Office Qrtly'!H22 -> 27040.696 | W52: =ROUND(G52,-2)+ROUND(S52,-2)+ROUND(P52,-2)-ROUND(C52,-2) -> 0 | Y52: =ROUND(H52,-2)+ROUND(T52,-2)+ROUND(Q52,-2)-ROUND(D52,-2) -> 0 | AC52: =P52-J52-M52 -> 0 | AE52: =Q52-K52-N52 -> 0
B53: Average UK leverage exposure | C53: ='Group Qrtly'!C44 -> 1176200
B59: YTD pages = Quarterly pages
B61: =CQtr&" YTD" -> #REF! | C61: Group | G61: BUK | J61: CIB | M61: CCP | P61: BI | S61: HO
C62: =CQtr&" YTD" -> #REF! | D62: =PPPPQtr&" YTD" -> #REF! | G62: =CQtr&" YTD" -> #REF! | H62: =PPPPQtr&" YTD" -> #REF! | J62: =CQtr&" YTD" -> #REF! | K62: =PPPPQtr&" YTD" -> #REF! | M62: =CQtr&" YTD" -> #REF! | N62: =PPPPQtr&" YTD" -> #REF! | P62: =CQtr&" YTD" -> #REF! | Q62: =PPPPQtr&" YTD" -> #REF! | S62: =CQtr&" YTD" -> #REF! | T62: =PPPPQtr&" YTD" -> #REF!
B64: Total income | C64: =ROUND(C3,0)-ROUND(C33,0) -> -16380 | D64: =ROUND(D3,0)-ROUND(D33,0) -> -15778 | G64: =ROUND(G3,0)-ROUND(G33,0) -> 73 | H64: =ROUND(H3,0)-ROUND(H33,0) -> 11 | J64: =ROUND(J3,0)-ROUND(J33,0) -> -1112 | K64: =ROUND(K3,0)-ROUND(K33,0) -> 294 | M64: =ROUND(M3,0)-ROUND(M33,0) -> 38 | N64: =ROUND(N3,0)-ROUND(N33,0) -> -56 | P64: =ROUND(P3,0)-ROUND(P33,0) -> -1074 | Q64: =ROUND(Q3,0)-ROUND(Q33,0) -> 238 | S64: =ROUND(S3,0)-ROUND(S33,0) -> -30 | T64: =ROUND(T3,0)-ROUND(T33,0) -> -143
B65: Credit impairment charges and other provisions | C65: =ROUND(C4,0)-ROUND(C34,0) -> 1464 | D65: =ROUND(D4,0)-ROUND(D34,0) -> 1180 | G65: =ROUND(G4,0)-ROUND(G34,0) -> 290 | H65: =ROUND(H4,0)-ROUND(H34,0) -> -10 | J65: =ROUND(J4,0)-ROUND(J34,0) -> 672 | K65: =ROUND(K4,0)-ROUND(K34,0) -> 211 | M65: =ROUND(M4,0)-ROUND(M34,0) -> 692 | N65: =ROUND(N4,0)-ROUND(N34,0) -> -59 | P65: =ROUND(P4,0)-ROUND(P34,0) -> 1364 | Q65: =ROUND(Q4,0)-ROUND(Q34,0) -> 152 | S65: =ROUND(S4,0)-ROUND(S34,0) -> 13 | T65: =ROUND(T4,0)-ROUND(T34,0) -> 18
B66: Net operating income | C66: =ROUND(C5,0)-ROUND(C35,0) -> -14916 | D66: =ROUND(D5,0)-ROUND(D35,0) -> -14598 | G66: =ROUND(G5,0)-ROUND(G35,0) -> 363 | H66: =ROUND(H5,0)-ROUND(H35,0) -> 1 | J66: =ROUND(J5,0)-ROUND(J35,0) -> -440 | K66: =ROUND(K5,0)-ROUND(K35,0) -> 505 | M66: =ROUND(M5,0)-ROUND(M35,0) -> 730 | N66: =ROUND(N5,0)-ROUND(N35,0) -> -115 | P66: =ROUND(P5,0)-ROUND(P35,0) -> 290 | Q66: =ROUND(Q5,0)-ROUND(Q35,0) -> 390 | S66: =ROUND(S5,0)-ROUND(S35,0) -> -17 | T66: =ROUND(T5,0)-ROUND(T35,0) -> -125
B67: Operating costs | C67: =ROUND(C6,0)-ROUND(C36,0) -> 10102 | D67: =ROUND(D6,0)-ROUND(D36,0) -> 10263 | G67: =ROUND(G6,0)-ROUND(G36,0) -> 24 | H67: =ROUND(H6,0)-ROUND(H36,0) -> -6 | J67: =ROUND(J6,0)-ROUND(J36,0)-J37+J7 -> 71 | K67: =ROUND(K6,0)-ROUND(K36,0)-K37+K7 -> -154 | M67: =ROUND(M6,0)-ROUND(M36,0)-ROUND(M37,0)+ROUND(M7,0) -> -58 | N67: =ROUND(N6,0)-ROUND(N36,0)-N37+N7 -> 60 | P67: =ROUND(P6,0)-ROUND(P36,0) -> 13 | Q67: =ROUND(Q6,0)-ROUND(Q36,0) -> -94 | S67: =ROUND(S6,0)-ROUND(S36,0) -> -41 | T67: =ROUND(T6,0)-ROUND(T36,0) -> -7
B68: Litigation and conduct | C68: =ROUND(C8,0)-ROUND(C38,0) -> 1788 | D68: =ROUND(D8,0)-ROUND(D38,0) -> 246 | G68: =ROUND(G8,0)-ROUND(G38,0) -> 2 | H68: =ROUND(H8,0)-ROUND(H38,0) -> -408 | J68: =ROUND(J8,0)-ROUND(J38,0) -> -19 | K68: =ROUND(K8,0)-ROUND(K38,0) -> #VALUE! | M68: =ROUND(M8,0)-ROUND(M38,0) -> 0 | N68: =ROUND(N8,0)-ROUND(N38,0) -> -2 | P68: =ROUND(P8,0)-ROUND(P38,0) -> -19 | Q68: =ROUND(Q8,0)-ROUND(Q38,0) -> 4 | S68: =ROUND(S8,0)-ROUND(S38,0) -> -34 | T68: =ROUND(T8,0)-ROUND(T38,0) -> -1496
B69: Total operating expenses | C69: =ROUND(C9,0)-ROUND(C39,0) -> 12116 | D69: =ROUND(D9,0)-ROUND(D39,0) -> 10918 | G69: =ROUND(G9,0)-ROUND(G39,0) -> 26 | H69: =ROUND(H9,0)-ROUND(H39,0) -> -414 | J69: =ROUND(J9,0)-ROUND(J39,0) -> 52 | K69: =ROUND(K9,0)-ROUND(K39,0) -> -148 | M69: =ROUND(M9,0)-ROUND(M39,0) -> -58 | N69: =ROUND(N9,0)-ROUND(N39,0) -> 58 | P69: =ROUND(P9,0)-ROUND(P39,0) -> -6 | Q69: =ROUND(Q9,0)-ROUND(Q39,0) -> -90 | S69: =ROUND(S9,0)-ROUND(S39,0) -> -75 | T69: =ROUND(T9,0)-ROUND(T39,0) -> -1503
B70: Other net (expenses)/income | C70: =ROUND(C10,0)-ROUND(C40,0) -> -74 | D70: =ROUND(D10,0)-ROUND(D40,0) -> -50 | G70: =ROUND(G10,0)-ROUND(G40,0) -> #VALUE! | H70: =ROUND(H10,0)-ROUND(H40,0) -> -2 | J70: =ROUND(J10,0)-ROUND(J40,0) -> 12 | K70: =ROUND(K10,0)-ROUND(K40,0) -> -9 | M70: =ROUND(M10,0)-ROUND(M40,0) -> 0 | N70: =ROUND(N10,0)-ROUND(N40,0) -> 4 | P70: =ROUND(P10,0)-ROUND(P40,0) -> 12 | Q70: =ROUND(Q10,0)-ROUND(Q40,0) -> -5 | S70: =ROUND(S10,0)-ROUND(S40,0) -> -24 | T70: =ROUND(T10,0)-ROUND(T40,0) -> 29
B71: Profit/(loss) before tax | C71: =ROUND(C11,0)-ROUND(C41,0) -> -2874 | D71: =ROUND(D11,0)-ROUND(D41,0) -> -3730 | G71: =ROUND(G11,0)-ROUND(G41,0) -> 390 | H71: =ROUND(H11,0)-ROUND(H41,0) -> -415 | J71: =ROUND(J11,0)-ROUND(J41,0) -> -376 | K71: =ROUND(K11,0)-ROUND(K41,0) -> 348 | M71: =ROUND(M11,0)-ROUND(M41,0) -> 672 | N71: =ROUND(N11,0)-ROUND(N41,0) -> -53 | P71: =ROUND(P11,0)-ROUND(P41,0) -> 296 | Q71: =ROUND(Q11,0)-ROUND(Q41,0) -> 295 | S71: =ROUND(S11,0)-ROUND(S41,0) -> -116 | T71: =ROUND(T11,0)-ROUND(T41,0) -> -1599
B72: Attributable profit/(loss)1 | C72: =ROUND(C12,0)-ROUND(C42,0) -> -1423 | D72: =ROUND(D12,0)-ROUND(D42,0) -> -2315 | G72: =ROUND(G12,0)-ROUND(G42,0) -> 247 | H72: =ROUND(H12,0)-ROUND(H42,0) -> -448 | J72: =ROUND(J12,0)-ROUND(J42,0) -> -238 | K72: =ROUND(K12,0)-ROUND(K42,0) -> 252 | M72: =ROUND(M12,0)-ROUND(M42,0) -> 497 | N72: =ROUND(N12,0)-ROUND(N42,0) -> -33 | P72: =ROUND(P12,0)-ROUND(P42,0) -> 259 | Q72: =ROUND(Q12,0)-ROUND(Q42,0) -> 219 | S72: =ROUND(S12,0)-ROUND(S42,0) -> -73 | T72: =ROUND(T12,0)-ROUND(T42,0) -> -1527
B74: Basic earnings/(loss) per share
B76: Profit/(loss) before tax ex L&C | C76: =ROUND(C17,0)-ROUND(C47,0) -> -4662 | D76: =ROUND(D17,0)-ROUND(D47,0) -> -3976 | G76: =ROUND(G17,0)-ROUND(G47,0) -> 388 | H76: =ROUND(H17,0)-ROUND(H47,0) -> -7 | J76: =ROUND(J17,0)-ROUND(J47,0) -> -357 | K76: =ROUND(K17,0)-ROUND(K47,0) -> 342 | M76: =ROUND(M17,0)-ROUND(M47,0) -> 672 | N76: =ROUND(N17,0)-ROUND(N47,0) -> -51 | P76: =ROUND(P17,0)-ROUND(P47,0) -> 315 | Q76: =ROUND(Q17,0)-ROUND(Q47,0) -> 291 | S76: =ROUND(S17,0)-ROUND(S47,0) -> -82 | T76: =ROUND(T17,0)-ROUND(T47,0) -> -103
B77: Attributable profit/(loss) ex L&C | C77: =ROUND(C18,0)-ROUND(C48,0) -> -3110 | D77: =ROUND(D18,0)-ROUND(D48,0) -> -2521 | G77: =ROUND(G18,0)-ROUND(G48,0) -> 246 | H77: =ROUND(H18,0)-ROUND(H48,0) -> -39 | J77: =ROUND(J18,0)-ROUND(J48,0) -> -222 | K77: =ROUND(K18,0)-ROUND(K48,0) -> 246 | M77: =ROUND(M18,0)-ROUND(M48,0) -> 497 | N77: =ROUND(N18,0)-ROUND(N48,0) -> -31 | P77: =ROUND(P18,0)-ROUND(P48,0) -> 275 | Q77: =ROUND(Q18,0)-ROUND(Q48,0) -> 215 | S77: =ROUND(S18,0)-ROUND(S48,0) -> -41 | T77: =ROUND(T18,0)-ROUND(T48,0) -> -48
B78: Post tax L&C impact | C78: =ROUND(C19,0)-ROUND(C49,0) -> 47 | D78: =ROUND(D19,0)-ROUND(D49,0) -> 1884 | G78: =ROUND(G19,0)-ROUND(G49,0) -> -1 | H78: =ROUND(H19,0)-ROUND(H49,0) -> 409 | J78: =ROUND(J19,0)-ROUND(J49,0) -> 16 | K78: =ROUND(K19,0)-ROUND(K49,0) -> -6 | M78: =ROUND(M19,0)-ROUND(M49,0) -> 0 | N78: =ROUND(N19,0)-ROUND(N49,0) -> 2 | P78: =ROUND(P19,0)-ROUND(P49,0) -> 16 | Q78: =ROUND(Q19,0)-ROUND(Q49,0) -> -4 | S78: =ROUND(S19,0)-ROUND(S49,0) -> 32 | T78: =ROUND(T19,0)-ROUND(T49,0) -> 1479
B80: Total assets | C80: =ROUND(C21,-2)-ROUND(C51,-2) -> 0 | D80: =ROUND(D21,-2)-ROUND(D51,-2) -> 0 | G80: =ROUND(G21,-2)-ROUND(G51,-2) -> -9700 | H80: =ROUND(H21,-2)-ROUND(H51,-2) -> -3400 | J80: =ROUND(J21,-2)-ROUND(J51,-2) -> -286900 | K80: =ROUND(K21,-2)-ROUND(K51,-2) -> -47600 | M80: =ROUND(M21,-2)-ROUND(M51,-2) -> -4900 | N80: =ROUND(N21,-2)-ROUND(N51,-2) -> -9300 | P80: =ROUND(P21,-2)-ROUND(P51,-2) -> -291800 | Q80: =ROUND(Q21,-2)-ROUND(Q51,-2) -> -56900 | S80: =ROUND(S21,-2)-ROUND(S51,-2) -> -2600 | T80: =ROUND(T21,-2)-ROUND(T51,-2) -> 100
B81: Risk weighted assets | C81: =ROUND(C22,-2)-ROUND(C52,-2) -> 0 | D81: =ROUND(D22,-2)-ROUND(D52,-2) -> -24600 | G81: =ROUND(G22,-2)-ROUND(G52,-2) -> -2800 | H81: =ROUND(H22,-2)-ROUND(H52,-2) -> -1400 | J81: =ROUND(J22,-2)-ROUND(J52,-2) -> -30200 | K81: =ROUND(K22,-2)-ROUND(K52,-2) -> -5700 | M81: =ROUND(M22,-2)-ROUND(M52,-2) -> 1500 | N81: =ROUND(N22,-2)-ROUND(N52,-2) -> 300 | P81: =ROUND(P22,-2)-ROUND(P52,-2) -> -28700 | Q81: =ROUND(Q22,-2)-ROUND(Q52,-2) -> -5400 | S81: =ROUND(S22,-2)-ROUND(S52,-2) -> 1000 | T81: =ROUND(T22,-2)-ROUND(T52,-2) -> -1000
B82: Average UK leverage exposure

Sheet Group PH
B1: Barclays Group results
B2: for the three months ended | C2: 31.03.20 | D2: 31.03.19
C3: £m | D3: £m | E3: % Change
B4: Total income | C4: 6283 | D4: 5252 | E4: 19.630617
B5: Credit impairment charges | C5: -2115 | D5: -448
B6: Net operating income | C6: 4168 | D6: 4804 | E6: -13.238968
B7: Operating expenses | C7: -3253 | D7: -3257 | E7: -
B8: Litigation and conduct | C8: -10.340854 | D8: -61 | E8: 83.606557
B9: Total operating expenses | C9: -3263 | D9: -3318 | E9: 1.6576251
B10: Other net income/(expenses) | C10: 8 | D10: -3
B11: Profit before tax | C11: 913 | D11: 1483 | E11: -38.435604
B12: Tax charge | C12: -71 | D12: -248 | E12: 71.370968
B13: Profit after tax | C13: 842 | D13: 1235 | E13: -31.821862
B14: Non-controlling interests | C14: -16 | D14: -17 | E14: 5.8823529
B15: Other equity instrument holders | C15: -221 | D15: -180 | E15: -22.777778
B16: Attributable profit | C16: 605 | D16: 1038 | E16: -41.714836
B18: Performance measures
B19: Return on average tangible shareholders' equity | C19: 0.051 | D19: 0.092
B20: Average tangible shareholders' equity (£bn) | C20: 46994.626 | D20: 45200
B21: Cost: income ratio | C21: 0.52 | D21: 0.63
B22: Loan loss rate (bps) | C22: 222.58505 | D22: 54
B23: Basic earnings per share | C23: 3.5015357 | D23: 6.1
B25: Performance measures excluding litigation and conduct
B26: Profit before tax | C26: 923.34085 | D26: 1544 | E26: -40.220207
B27: Attributable profit | C27: 604.40094 | D27: 1084 | E27: -44.280443
B28: Return on average tangible shareholders' equity | C28: 0.051 | D28: 0.096
B29: Cost: income ratio | C29: 0.52 | D29: 0.62
B30: Basic earnings per share | C30: 3.4980685 | D30: 6.3
C32: As at 31.03.20 | D32: As at 31.12.19 | E32: As at 31.03.19
B33: Balance sheet and capital management | C33: £bn | D33: £bn | E33: £bn
B34: Tangible net asset value per share | C34: 284.38013 | D34: 262.31927 | E34: 266
B35: Common equity tier 1 ratio | C35: 0.131 | D35: 0.138 | E35: 0.13
B36: Common equity tier 1 capital | C36: 42484 | D36: 40813.416 | E36: 41400
B37: Risk weighted assets | C37: 325631 | D37: 295131.09 | E37: 319700
B38: Average UK leverage ratio | C38: 0.045 | D38: 0.045 | E38: 0.046
B39: UK leverage ratio | C39: 0.045 | D39: 0.051 | E39: 0.049
B41: Funding and liquidity
B42: Group liquidity pool (£bn) | C42: 237000 | D42: 211000 | E42: 232000
B43: Liquidity coverage ratio | C43: 1.55 | D43: 1.6 | E43: 1.6
B44: Loan: deposit ratio | C44: 0.79 | D44: 0.82 | E44: 0.8

Sheet Barclays UK YTD
B2: Barclays UK | C2: Year ended | D2: Year ended
C3: 31.12.19 | D3: 31.12.18
B4: Income statement information | C4: £m | D4: £m | E4: % Change | H4: % Check | L4: =CQtr&" YTD" -> #REF! | M4: =PPPPQtr&" YTD" -> #REF!
B5: Net interest income | C5: 5888 | D5: 6028 | E5: -2.322495 | H5: =IFERROR(ROUND(IF(C5>0,100*(ROUND(C5,0)-ROUND(D5,0))/ROUND(D5,0),-100*(ROUND(C5,0)-ROUND(D5,0))/ROUND(D5,0)),0)-ROUND(E5,0),0) -> 0 | J5: Casting down check | L5: Check to Appendix
B6: Net fee, commission and other income | C6: 1465 | D6: 1355 | E6: 8.1180812 | H6: =IFERROR(ROUND(IF(C6>0,100*(ROUND(C6,0)-ROUND(D6,0))/ROUND(D6,0),-100*(ROUND(C6,0)-ROUND(D6,0))/ROUND(D6,0)),0)-ROUND(E6,0),0) -> 0 | J6: =CQtr&" YTD" -> #REF! | K6: =PPPPQtr&" YTD" -> #REF!
B7: Total income | C7: 7353 | D7: 7383 | E7: - | H7: =IFERROR(ROUND(IF(C7>0,100*(ROUND(C7,0)-ROUND(D7,0))/ROUND(D7,0),-100*(ROUND(C7,0)-ROUND(D7,0))/ROUND(D7,0)),0)-ROUND(E7,0),0) -> 0 | J7: =ROUND(C5,0)+ROUND(C6,0)-ROUND(C7,0) -> 0 | K7: =ROUND(D5,0)+ROUND(D6,0)-ROUND(D7,0) -> 0 | L7: =C7-'CYYTD performance measures excl'!B10 -> 0 | M7: =D7-'PYYTD performance measures'!B10 -> 0
B8: Credit impairment charges | C8: -712 | D8: -826 | E8: 13.801453 | H8: =IFERROR(ROUND(IF(C8>0,100*(ROUND(C8,0)-ROUND(D8,0))/ROUND(D8,0),-100*(ROUND(C8,0)-ROUND(D8,0))/ROUND(D8,0)),0)-ROUND(E8,0),0) -> 0
B9: Net operating income | C9: 6641 | D9: 6557 | E9: 1.2810737 | H9: =IFERROR(ROUND(IF(C9>0,100*(ROUND(C9,0)-ROUND(D9,0))/ROUND(D9,0),-100*(ROUND(C9,0)-ROUND(D9,0))/ROUND(D9,0)),0)-ROUND(E9,0),0) -> 0
B10: Operating costs | C10: -3995.6945 | D10: -4075 | E10: 1.9386503 | H10: =IFERROR(ROUND(IF(C10>0,100*(ROUND(C10,0)-ROUND(D10,0))/ROUND(D10,0),-100*(ROUND(C10,0)-ROUND(D10,0))/ROUND(D10,0)),0)-ROUND(E10,0),0) -> 0 | J10: =ROUND(C7,0)+ROUND(C8,0)-ROUND(C9,0) -> 0 | K10: =ROUND(D7,0)+ROUND(D8,0)-ROUND(D9,0) -> 0 | L10: =ROUND(C10,0)+ROUND(C11,0)-ROUND('CYYTD performance measures excl'!B8,0) -> 0 | M10: =D10+D11-'PYYTD performance measures'!B8 -> 0
B11: UK bank levy | C11: -41 | D11: -46 | E11: 10.869565 | H11: =IFERROR(ROUND(IF(C11>0,100*(ROUND(C11,0)-ROUND(D11,0))/ROUND(D11,0),-100*(ROUND(C11,0)-ROUND(D11,0))/ROUND(D11,0)),0)-ROUND(E11,0),0) -> 0
B12: Operating expenses | C12: -4036.6945 | D12: -4121 | E12: 2.0383402 | H12: =IFERROR(ROUND(IF(C12>0,100*(ROUND(C12,0)-ROUND(D12,0))/ROUND(D12,0),-100*(ROUND(C12,0)-ROUND(D12,0))/ROUND(D12,0)),0)-ROUND(E12,0),0) -> 0 | J12: =ROUND(C10,0)+ROUND(C11,0)-ROUND(C12,0) -> 0 | K12: =ROUND(D10,0)+ROUND(D11,0)-ROUND(D12,0) -> 0 | L12: =ROUND(C12,0)-ROUND('CYYTD performance measures excl'!B8,0) -> 0 | M12: =ROUND(D12,0)-'PYYTD performance measures'!B8 -> 0
B13: Litigation and conduct | C13: -1582.3055 | D13: -483 | H13: =IFERROR(ROUND(IF(C13>0,100*(ROUND(C13,0)-ROUND(D13,0))/ROUND(D13,0),-100*(ROUND(C13,0)-ROUND(D13,0))/ROUND(D13,0)),0)-ROUND(E13,0),0) -> 0
B14: Total operating expenses | C14: -5619 | D14: -4604 | E14: -22.046047 | H14: =IFERROR(ROUND(IF(C14>0,100*(ROUND(C14,0)-ROUND(D14,0))/ROUND(D14,0),-100*(ROUND(C14,0)-ROUND(D14,0))/ROUND(D14,0)),0)-ROUND(E14,0),0) -> 0 | J14: =+ROUND(C10,0)-ROUND(C14,0)+ROUND(C13,0)+ROUND(C11,0) -> 0 | K14: =+ROUND(D10,0)-ROUND(D14,0)+ROUND(D13,0)+ROUND(D11,0) -> 0 | L14: =C14-'CYYTD performance measures excl'!B6 -> 0 | M14: =D14-'PYYTD performance measures'!B6 -> 0
B15: Other net income | C15: - | D15: 3 | H15: =IFERROR(ROUND(IF(C15>0,100*(ROUND(C15,0)-ROUND(D15,0))/ROUND(D15,0),-100*(ROUND(C15,0)-ROUND(D15,0))/ROUND(D15,0)),0)-ROUND(E15,0),0) -> 0
B16: Profit before tax | C16: 1022 | D16: 1956 | E16: -47.750511 | H16: =IFERROR(ROUND(IF(C16>0,100*(ROUND(C16,0)-ROUND(D16,0))/ROUND(D16,0),-100*(ROUND(C16,0)-ROUND(D16,0))/ROUND(D16,0)),0)-ROUND(E16,0),0) -> 0 | J16: =ROUND(C9,0)+ROUND(C10,0)+ROUND(C15,0)-ROUND(C16,0)+ROUND(C13,0)+ROUND(C11,0) -> #VALUE! | K16: =ROUND(D9,0)+ROUND(D10,0)+ROUND(D15,0)-ROUND(D16,0)+ROUND(D13,0)+ROUND(D11,0) -> 0 | L16: =C16-'CYYTD performance measures excl'!B15 -> 0 | M16: =D16-'PYYTD performance measures'!B15 -> 0
B17: Attributable profit1 | C17: 281 | D17: 1198 | E17: -76.54424 | H17: =IFERROR(ROUND(IF(C17>0,100*(ROUND(C17,0)-ROUND(D17,0))/ROUND(D17,0),-100*(ROUND(C17,0)-ROUND(D17,0))/ROUND(D17,0)),0)-ROUND(E17,0),0) -> 0 | K17: AP | L17: =C17-'CYYTD performance measures excl'!B20 -> 0 | M17: =D17-'PYYTD performance measures'!B20 -> 0
B19: Balance sheet information | C19: £bn | D19: £bn | H19: Consistency with quarterlies check | L19: =CQtr -> #REF! | M19: Q418 | N19: Q318
B20: Loans and advances to customers at amortised cost | C20: 193700 | D20: 187600 | G20: Loans and advances to customers at amortised cost | H20: =ROUND(C20,-2)-ROUND(L20,-2) -> -2000 | I20: =ROUND(D20,-2)-ROUND(M20,-2) -> 100 | L20: ='Barclays UK Qrtly'!C20 -> 195700 | M20: ='Barclays UK Qrtly'!H20 -> 187500 | N20: ='Barclays UK Qrtly'!J20 -> 187600
B21: Total assets | C21: 257776 | D21: 249700 | G21: Total assets | H21: =ROUND(C21,-2)-ROUND(L21,-2) -> -9700 | I21: =ROUND(D21,-2)-ROUND(M21,-2) -> -3400 | L21: ='Barclays UK Qrtly'!C21 -> 267542 | M21: ='Barclays UK Qrtly'!H21 -> 253086 | N21: ='Barclays UK Qrtly'!J21 -> 249669
B22: Customer deposits at amortised cost | C22: 205477.24 | D22: 197300 | G22: Customer deposits at amortised cost | H22: =ROUND(C22,-2)-ROUND(L22,-2) -> -2000 | I22: =ROUND(D22,-2)-ROUND(M22,-2) -> 0 | L22: ='Barclays UK Qrtly'!C22 -> 207489.79 | M22: ='Barclays UK Qrtly'!H22 -> 197284.41 | N22: ='Barclays UK Qrtly'!J22 -> 197279.46
B23: Loan: deposit ratio | C23: 0.96 | D23: 0.96 | G23: Loan: deposit ratio | H23: =C23-L23 -> 0 | I23: =D23-M23 -> 0 | L23: ='Barclays UK Qrtly'!C23 -> 0.96 | M23: ='Barclays UK Qrtly'!H23 -> 0.96 | N23: ='Barclays UK Qrtly'!J23 -> 0.96
B24: Risk weighted assets | C24: 74900.809 | D24: 75200 | G24: Risk weighted assets | H24: =ROUND(C24,-2)-ROUND(L24,-2) -> -2800 | I24: =ROUND(D24,-2)-ROUND(M24,-2) -> -1400 | L24: ='Barclays UK Qrtly'!C24 -> 77678 | M24: ='Barclays UK Qrtly'!H24 -> 76558.949 | N24: ='Barclays UK Qrtly'!J24 -> 75181
B25: Period end allocated tangible equity | C25: 10253.792 | D25: 10200 | G25: Period end allocated tangible equity | H25: =ROUND(C25,-2)-ROUND(L25,-2) -> -300 | I25: =ROUND(D25,-2)-ROUND(M25,-2) -> -300 | L25: ='Barclays UK Qrtly'!C25 -> 10645.223 | M25: ='Barclays UK Qrtly'!H25 -> 10466.112 | N25: ='Barclays UK Qrtly'!J25 -> 10201.511
B27: Key facts
B28: Average loan to value of mortgage portfolio2 | C28: 0.51 | D28: 0.49
B29: Average loan to value of new mortgage lending2 | C29: 0.68 | D29: 0.65
B30: Number of branches | C30: 963 | D30: 1058
B31: Mobile banking active customers | C31: 8.4 | D31: 7.3m
B32: 30 day arrears rate - Barclaycard Consumer UK | C32: 0.017 | D32: 0.018
B34: Performance measures
B35: Return on average allocated tangible equity | C35: 0.027 | D35: 0.119
B36: Average allocated tangible equity (£bn) | C36: 10333.198 | D36: 10000 | H36: ROTE check
B37: Cost: income ratio | C37: 0.76 | D37: 0.62 | H37: =ROUND(C35,3)-ROUND(((C17/C36)),3) -> 0 | I37: =ROUND(D35,-4)-ROUND(((D17/D36)/4*4),-4) -> 0
B38: Loan loss rate (bps) | C38: 35.5728 | D38: 43 | G38: ex L&C | H38: =ROUND(C44,3)-ROUND(((C43/C36)),3) -> 0 | I38: =ROUND(D44,3)-ROUND(((D43/D36)/4*4),3) -> 0
B39: Net interest margin | C39: 0.0309 | D39: 0.0323
B41: Performance measures excluding litigation and conduct3 | C41: £m | D41: £m
B42: Profit before tax | C42: 2604.3055 | D42: 2439 | E42: 6.7650677 | H42: CIR Check
B43: Attributable profit | C43: 1813.076 | D43: 1670 | E43: 8.5628743 | H43: =ROUND(-ROUND(C14,0)/ROUND(C7,0),2)-ROUND(C37,2) -> 0 | I43: =ROUND(-ROUND(D14,0)/ROUND(D7,0),2)-ROUND(D37,2) -> 0
B44: Return on average allocated tangible equity | C44: 0.175 | D44: 0.167 | H44: =-ROUND(C14,0)/ROUND(C7,0) -> 0.76417789 | I44: =-ROUND(D14,0)/ROUND(D7,0) -> 0.62359474 | L44: =C36-'CYYTD performance measures excl'!B27 -> 0 | M44: =ROUND(D36,-2)-ROUND('PYYTD performance measures'!B27,-2) -> 0
B45: Cost: income ratio | C45: 0.55 | D45: 0.56
B47: Analysis of Barclays UK | C47: Year ended | D47: Year ended | H47: CIR Check
C48: 31.12.19 | D48: 31.12.18
B49: Analysis of total income | C49: £m | D49: £m | E49: % Change | H49: =ROUND(C45,2)-ROUND(H50,2) -> 0 | I49: =ROUND(D45,2)-ROUND(I50,2) -> 0
B50: Personal Banking | C50: 4009 | D50: 4006 | E50: - | H50: =(-ROUND(C14,0)+ROUND(C13,0))/ROUND(C7,0) -> 0.54902761 | I50: =(-ROUND(D14,0)+ROUND(D13,0))/ROUND(D7,0) -> 0.55817418 | L50: Consistency
B51: Barclaycard Consumer UK | C51: 1992 | D51: 2104 | E51: -5.3231939 | H51: =IFERROR(ROUND(IF(C42>0,100*(ROUND(C42,0)-ROUND(D42,0))/ROUND(D42,0),-100*(ROUND(C42,0)-ROUND(D42,0))/ROUND(D42,0)),0)-ROUND(E42,0),0) -> 0 | J51: Casting down check | L51: =C42-'CYYTD performance measures excl'!B17 -> 0 | M51: =D42-'PYYTD performance measures'!B17 -> 0 | P51: =ROUND(H50,3) -> 0.549 | Q51: =ROUND(C45,3) -> 0.55
B52: Business Banking | C52: 1352 | D52: 1273 | E52: 6.205813 | H52: =IFERROR(ROUND(IF(C43>0,100*(ROUND(C43,0)-ROUND(D43,0))/ROUND(D43,0),-100*(ROUND(C43,0)-ROUND(D43,0))/ROUND(D43,0)),0)-ROUND(E43,0),0) -> 0 | J52: =J6 -> #REF! | K52: =K6 -> #REF! | L52: =C43-'CYYTD performance measures excl'!B22 -> 0 | M52: =ROUND(D43,0)-ROUND('PYYTD performance measures'!B22,0) -> 0
B53: Total income | C53: 7353 | D53: 7383 | E53: -
J54: =ROUND(C16,0)-ROUND(C13,0)-ROUND(C42,0) -> 0 | K54: =ROUND(D16,0)-ROUND(D13,0)-ROUND(D42,0) -> 0 | L54: CIR
B55: Analysis of credit impairment charges | L55: =ROUND(C45,2)-ROUND('CYYTD performance measures excl'!B12,2) -> 0 | M55: =ROUND(D45,2)-ROUND('PYYTD performance measures'!B12,2) -> 0
B56: Personal Banking | C56: -195 | D56: -173 | E56: -12.716763 | L56: ='CYYTD performance measures excl'!B12 -> 0.55 | M56: ='PYYTD performance measures'!B12 -> 0.56
B57: Barclaycard Consumer UK | C57: -472 | D57: -590 | E57: 20
B58: Business Banking | C58: -45 | D58: -63 | E58: 28.571429 | H58: % Check | J58: Casting down check
B59: Total credit impairment charges | C59: -712 | D59: -826 | E59: 13.801453 | H59: =IFERROR(ROUND(IF(C50>0,100*(ROUND(C50,0)-ROUND(D50,0))/ROUND(D50,0),-100*(ROUND(C50,0)-ROUND(D50,0))/ROUND(D50,0)),0)-ROUND(E50,0),0) -> 0 | J59: =ROUND(C50,0)+ROUND(C51,0)+ROUND(C52,0)-ROUND(C53,0) -> 0 | K59: =ROUND(D50,0)+ROUND(D51,0)+ROUND(D52,0)-ROUND(D53,0) -> 0
H60: =IFERROR(ROUND(IF(C51>0,100*(ROUND(C51,0)-ROUND(D51,0))/ROUND(D51,0),-100*(ROUND(C51,0)-ROUND(D51,0))/ROUND(D51,0)),0)-ROUND(E51,0),0) -> 0
B61: Analysis of loans and advances to customers at amortised cost | C61: £bn | D61: £bn | H61: =IFERROR(ROUND(IF(C52>0,100*(ROUND(C52,0)-ROUND(D52,0))/ROUND(D52,0),-100*(ROUND(C52,0)-ROUND(D52,0))/ROUND(D52,0)),0)-ROUND(E52,0),0) -> 0 | J61: Consistency with BUK
B62: Personal Banking | C62: 151900 | D62: 146000 | H62: =IFERROR(ROUND(IF(C53>0,100*(ROUND(C53,0)-ROUND(D53,0))/ROUND(D53,0),-100*(ROUND(C53,0)-ROUND(D53,0))/ROUND(D53,0)),0)-ROUND(E53,0),0) -> 0 | J62: =ROUND(C53,0)-ROUND(C7,0) -> 0 | K62: =ROUND(D53,0)-ROUND(D7,0) -> 0
B63: Barclaycard Consumer UK | C63: 14700 | D63: 15300
B64: Business Banking | C64: 27100 | D64: 26300 | J64: Casting down check
B65: Total loans and advances to customers at amortised cost | C65: 193700 | D65: 187600 | H65: =IFERROR(ROUND(IF(C56>0,100*(ROUND(C56,0)-ROUND(D56,0))/ROUND(D56,0),-100*(ROUND(C56,0)-ROUND(D56,0))/ROUND(D56,0)),0)-ROUND(E56,0),0) -> 0 | J65: =ROUND(C56,0)+ROUND(C57,0)+ROUND(C58,0)-ROUND(C59,0) -> 0 | K65: =ROUND(D56,0)+ROUND(D57,0)+ROUND(D58,0)-ROUND(D59,0) -> 0
H66: =IFERROR(ROUND(IF(C57>0,100*(ROUND(C57,0)-ROUND(D57,0))/ROUND(D57,0),-100*(ROUND(C57,0)-ROUND(D57,0))/ROUND(D57,0)),0)-ROUND(E57,0),0) -> 0
B67: Analysis of customer deposits at amortised cost | H67: =IFERROR(ROUND(IF(C58>0,100*(ROUND(C58,0)-ROUND(D58,0))/ROUND(D58,0),-100*(ROUND(C58,0)-ROUND(D58,0))/ROUND(D58,0)),0)-ROUND(E58,0),0) -> 0 | J67: Consistency with BUK
B68: Personal Banking | C68: 159200 | D68: 154000 | H68: =IFERROR(ROUND(IF(C59>0,100*(ROUND(C59,0)-ROUND(D59,0))/ROUND(D59,0),-100*(ROUND(C59,0)-ROUND(D59,0))/ROUND(D59,0)),0)-ROUND(E59,0),0) -> 0 | J68: =ROUND(C59,0)-ROUND(C8,0) -> 0 | K68: =ROUND(D59,0)-ROUND(D8,0) -> 0
B69: Barclaycard Consumer UK | C69: 0 | D69: 0
B70: Business Banking | C70: 46344.898 | D70: 43300
B71: Total customer deposits at amortised cost | C71: 205477.24 | D71: 197300 | J71: Casting down check
J72: =ROUND(C62,0)+ROUND(C63,0)+ROUND(C64,0)-ROUND(C65,0) -> 0 | K72: =ROUND(D62,0)+ROUND(D63,0)+ROUND(D64,0)-ROUND(D65,0) -> 0
J74: Consistency with BUK
J75: =ROUND(C65,0)-ROUND(C20,0) -> 0 | K75: =ROUND(D65,0)-ROUND(D20,0) -> 0
J77: Casting down check
J78: =ROUND(C68,-2)+ROUND(C69,-2)+ROUND(C70,-2)-ROUND(C71,-2) -> 0 | K78: =ROUND(D68,0)+ROUND(D69,0)+ROUND(D70,0)-ROUND(D71,0) -> 0
J80: Consistency with BUK
J81: =ROUND(C71,0)-ROUND(C22,0) -> 0 | K81: =ROUND(D71,0)-ROUND(D22,0) -> 0

Sheet Barclays International YTD
B2: Barclays International | C2: Year ended | D2: Year ended
C3: 31.12.19 | D3: 31.12.18
B4: Income statement information | C4: £m | D4: £m | E4: % Change | H4: % Check | J4: Casting down check | M4: CIB+CCP=BI | P4: Checking to Appendix
B5: Net interest income | C5: 3941 | D5: 3815 | E5: 3.3027523 | H5: =IFERROR(ROUND(IF(C5>0,100*(ROUND(C5,0)-ROUND(D5,0))/ROUND(D5,0),-100*(ROUND(C5,0)-ROUND(D5,0))/ROUND(D5,0)),0)-ROUND(E5,0),0) -> 0 | J5: =CQtr&" YTD" -> #REF! | K5: =PPPPQtr&" YTD" -> #REF! | P5: =CQtr&" YTD" -> #REF! | Q5: =PPPPQtr&" YTD" -> #REF!
B6: Net trading income | C6: 4199 | D6: 4450 | E6: -5.6404494 | H6: =IFERROR(ROUND(IF(C6>0,100*(ROUND(C6,0)-ROUND(D6,0))/ROUND(D6,0),-100*(ROUND(C6,0)-ROUND(D6,0))/ROUND(D6,0)),0)-ROUND(E6,0),0) -> 0
B7: Net fee, commission and other income | C7: 6535 | D7: 5761 | E7: 13.435168 | H7: =IFERROR(ROUND(IF(C7>0,100*(ROUND(C7,0)-ROUND(D7,0))/ROUND(D7,0),-100*(ROUND(C7,0)-ROUND(D7,0))/ROUND(D7,0)),0)-ROUND(E7,0),0) -> 0
B8: Total income | C8: 14675 | D8: 14026 | E8: 4.6271211 | H8: =IFERROR(ROUND(IF(C8>0,100*(ROUND(C8,0)-ROUND(D8,0))/ROUND(D8,0),-100*(ROUND(C8,0)-ROUND(D8,0))/ROUND(D8,0)),0)-ROUND(E8,0),0) -> 0 | J8: =ROUND(C5,0)+ROUND(C6,0)+ROUND(C7,0)-ROUND(C8,0) -> 0 | K8: =ROUND(D5,0)+ROUND(D6,0)+ROUND(D7,0)-ROUND(D8,0) -> 0 | M8: =ROUND(C62,0)+ROUND(C102,0)-ROUND(C8,0) -> 0 | N8: =ROUND(D62,0)+ROUND(D102,0)-ROUND(D8,0) -> 0 | P8: =C8-'CYYTD performance measures excl'!E10 -> 0 | Q8: =D8-'PYYTD performance measures'!E10 -> 0
B9: Credit impairment charges | C9: -1173 | D9: -658 | E9: -78.267477 | H9: =IFERROR(ROUND(IF(C9>0,100*(ROUND(C9,0)-ROUND(D9,0))/ROUND(D9,0),-100*(ROUND(C9,0)-ROUND(D9,0))/ROUND(D9,0)),0)-ROUND(E9,0),0) -> 0 | M9: =ROUND(C63,0)+ROUND(C103,0)-ROUND(C9,0) -> 0 | N9: =ROUND(D63,0)+ROUND(D103,0)-ROUND(D9,0) -> 0
B10: Net operating income | C10: 13502 | D10: 13368 | E10: 1.0023938 | H10: =IFERROR(ROUND(IF(C10>0,100*(ROUND(C10,0)-ROUND(D10,0))/ROUND(D10,0),-100*(ROUND(C10,0)-ROUND(D10,0))/ROUND(D10,0)),0)-ROUND(E10,0),0) -> 0 | J10: =ROUND(C8,0)+ROUND(C9,0)-ROUND(C10,0) -> 0 | K10: =ROUND(D8,0)+ROUND(D9,0)-ROUND(D10,0) -> 0 | M10: =ROUND(C64,0)+ROUND(C104,0)-ROUND(C10,0) -> 0 | N10: =ROUND(D64,0)+ROUND(D104,0)-ROUND(D10,0) -> 0
B11: Operating costs | C11: -9162.8284 | D11: -9324 | E11: 1.7267267 | H11: =IFERROR(ROUND(IF(C11>0,100*(ROUND(C11,0)-ROUND(D11,0))/ROUND(D11,0),-100*(ROUND(C11,0)-ROUND(D11,0))/ROUND(D11,0)),0)-ROUND(E11,0),0) -> 0 | M11: =ROUND(C65,0)+ROUND(C105,0)-ROUND(C15,0)+ROUND(C14,0)+ROUND(C12,0) -> 0 | N11: =ROUND(D65,0)+ROUND(D105,0)-ROUND(D15,0)+ROUND(D14,0)+D12 -> 0 | P11: =ROUND(C11,0)+ROUND(C12,0)-ROUND('CYYTD performance measures excl'!E8,0) -> 0 | Q11: =D11+D12-'PYYTD performance measures'!E8 -> 0
B12: UK bank levy | C12: -174.4 | D12: -210 | E12: 17.142857 | H12: =IFERROR(ROUND(IF(C12>0,100*(ROUND(C12,0)-ROUND(D12,0))/ROUND(D12,0),-100*(ROUND(C12,0)-ROUND(D12,0))/ROUND(D12,0)),0)-ROUND(E12,0),0) -> 0 | M12: =ROUND(C12,0)-ROUND(C66,0)-ROUND(C106,0) -> 0 | N12: =D12-D66-D106 -> 0
B13: Operating expenses | C13: -9337.2284 | D13: -9534 | E13: 2.0662891 | H13: =IFERROR(ROUND(IF(C13>0,100*(ROUND(C13,0)-ROUND(D13,0))/ROUND(D13,0),-100*(ROUND(C13,0)-ROUND(D13,0))/ROUND(D13,0)),0)-ROUND(E13,0),0) -> 0 | J13: =ROUND(C11,0)+ROUND(C12,0)-ROUND(C13,0) -> 0 | K13: =ROUND(D11,0)+ROUND(D12,0)-ROUND(D13,0) -> 0 | M13: =ROUND(C13,0)-ROUND(C67,0)-ROUND(C107,0) -> 0 | N13: =D13-D67-D107 -> 0 | P13: =ROUND(C13,0)-ROUND('CYYTD performance measures excl'!E8,0) -> 0 | Q13: =D13-'PYYTD performance measures'!E8 -> 0
B14: Litigation and conduct | C14: -115.77155 | D14: -127 | E14: 8.6614173 | H14: =IFERROR(ROUND(IF(C14>0,100*(ROUND(C14,0)-ROUND(D14,0))/ROUND(D14,0),-100*(ROUND(C14,0)-ROUND(D14,0))/ROUND(D14,0)),0)-ROUND(E14,0),0) -> 0 | M14: =ROUND(C68,0)+ROUND(C108,0)-ROUND(C14,0) -> 0 | N14: =ROUND(D68,0)+ROUND(D108,0)-ROUND(D14,0) -> 0
B15: Total operating expenses | C15: -9453 | D15: -9661 | E15: 2.1529862 | H15: =IFERROR(ROUND(IF(C15>0,100*(ROUND(C15,0)-ROUND(D15,0))/ROUND(D15,0),-100*(ROUND(C15,0)-ROUND(D15,0))/ROUND(D15,0)),0)-ROUND(E15,0),0) -> 0 | J15: =+ROUND(C11,0)+ROUND(C14,0)+ROUND(C12,0)-ROUND(C15,0) -> 0 | K15: =+ROUND(D11,0)+ROUND(D14,0)+ROUND(D12,0)-ROUND(D15,0) -> 0 | M15: =ROUND(C69,0)+ROUND(C109,0)-ROUND(C15,0) -> 0 | N15: =ROUND(D69,0)+ROUND(D109,0)-ROUND(D15,0) -> 0 | P15: =C15-'CYYTD performance measures excl'!E6 -> 0 | Q15: =D15-'PYYTD performance measures'!E6 -> 0
B16: Other net income | C16: 69 | D16: 68 | E16: 1.4705882 | H16: =IFERROR(ROUND(IF(C16>0,100*(ROUND(C16,0)-ROUND(D16,0))/ROUND(D16,0),-100*(ROUND(C16,0)-ROUND(D16,0))/ROUND(D16,0)),0)-ROUND(E16,0),0) -> 0 | M16: =ROUND(C70,0)+ROUND(C110,0)-ROUND(C16,0) -> 0 | N16: =ROUND(D70,0)+ROUND(D110,0)-ROUND(D16,0) -> 0
B17: Profit before tax | C17: 4118 | D17: 3775 | E17: 9.0860927 | H17: =IFERROR(ROUND(IF(C17>0,100*(ROUND(C17,0)-ROUND(D17,0))/ROUND(D17,0),-100*(ROUND(C17,0)-ROUND(D17,0))/ROUND(D17,0)),0)-ROUND(E17,0),0) -> 0 | J17: =ROUND(C10,0)+ROUND(C11,0)+ROUND(C14,0)+ROUND(C16,0)+ROUND(C12,0)-ROUND(C17,0) -> 0 | K17: =ROUND(D10,0)+ROUND(D11,0)+ROUND(D14,0)+ROUND(D16,0)+ROUND(D12,0)-ROUND(D17,0) -> 0 | M17: =ROUND(C71,0)+ROUND(C111,0)-ROUND(C17,0) -> 0 | N17: =ROUND(D71,0)+ROUND(D111,0)-ROUND(D17,0) -> 0 | P17: =C17-'CYYTD performance measures excl'!E15 -> 0 | Q17: =D17-'PYYTD performance measures'!E15 -> 0
B18: Attributable profit1 | C18: 2816 | D18: 2599 | E18: 8.3493651 | H18: =IFERROR(ROUND(IF(C18>0,100*(ROUND(C18,0)-ROUND(D18,0))/ROUND(D18,0),-100*(ROUND(C18,0)-ROUND(D18,0))/ROUND(D18,0)),0)-ROUND(E18,0),0) -> 0 | M18: =ROUND(C72,0)+ROUND(C112,0)-ROUND(C18,0) -> 0 | N18: =ROUND(D72,0)+ROUND(D112,0)-ROUND(D18,0) -> 0 | P18: =C18-'CYYTD performance measures excl'!E20 -> 0 | Q18: =D18-'PYYTD performance measures'!E20 -> 0
B20: Balance sheet information | C20: £bn | D20: £bn
B21: Loans and advances at amortised cost | C21: 132813.91 | D21: 127214.92 | M21: =ROUND(C75,-2)+ROUND(C115,-2)-ROUND(C21,-2) -> 0 | N21: =ROUND(D75,-2)+ROUND(D115,-2)-(ROUND(D21,-2)) -> 0 | O21: =ROUND(E75,-2)+ROUND(E115,-2)-ROUND(E21,-2) -> 0 | R21: Consistency with quarterlies check | S21: =CQtr -> #REF! | T21: Q418 | U21: Q218 | W21: =CQtr -> #REF! | X21: Q418 | Y21: Q218
B22: Trading portfolio assets | C22: 113300 | D22: 104033 | R22: Loans and advances at amortised cost | S22: =ROUND(C21,-2)-ROUND(W22,-2) -> -34200 | T22: =ROUND(D21,-2)-ROUND(X22,-2) -> -3700 | W22: ='Barclays International Qrtly'!C21 -> 167042.61 | X22: ='Barclays International Qrtly'!H21 -> 130931.97 | Y22: ='Barclays International Qrtly'!J21 -> 127214.92
B23: Derivative financial instrument assets | C23: 228864 | D23: 222099 | M23: Assets CIB + CCP = BI | R23: Trading portfolio assets | S23: =ROUND(C22,-2)-ROUND(W23,-2) -> 11700 | T23: =ROUND(D22,-2)-ROUND(X23,-2) -> -13200 | W23: ='Barclays International Qrtly'!C22 -> 101595 | X23: ='Barclays International Qrtly'!H22 -> 117236 | Y23: ='Barclays International Qrtly'!J22 -> 104033
B24: Financial assets at fair value through the income statement | C24: 128383.29 | D24: 144719.45 | M24: =ROUND(C27,-2)-ROUND(C81,-2)-ROUND(C116,-2) -> 0 | N24: =ROUND(D27,-2)-ROUND(D81,-2)-ROUND(D116,-2) -> 0 | O24: =ROUND(E27,-2)-ROUND(E81,-2)-ROUND(E116,-2) -> 0 | R24: Derivative financial instrument assets | S24: =ROUND(C23,-2)-ROUND(W24,-2) -> -112600 | T24: =ROUND(D23,-2)-ROUND(X24,-2) -> 4800 | W24: ='Barclays International Qrtly'!C23 -> 341542 | X24: ='Barclays International Qrtly'!H23 -> 217298 | Y24: ='Barclays International Qrtly'!J23 -> 222099
B25: Cash collateral and settlement balances | C25: 79379.067 | D25: 74300 | R25: Financial assets at fair value through the income statement | S25: =ROUND(C24,-2)-ROUND(W25,-2) -> -60000 | T25: =ROUND(D24,-2)-ROUND(X25,-2) -> -8800 | W25: ='Barclays International Qrtly'!C24 -> 188407.75 | X25: ='Barclays International Qrtly'!H24 -> 153482.6 | Y25: ='Barclays International Qrtly'!J24 -> 144719.45
B26: Other assets | C26: 178600 | D26: 189800 | H26: Casting down check | M26: Assets casting check | R26: Cash collateral and settlement balances | S26: =ROUND(C25,-2)-ROUND(W26,-2) -> -73800 | T26: =ROUND(D25,-2)-ROUND(X26,-2) -> -23500 | W26: ='Barclays International Qrtly'!C25 -> 153222.05 | X26: ='Barclays International Qrtly'!H25 -> 97800 | Y26: ='Barclays International Qrtly'!J25 -> 74300
B27: Total assets | C27: 861400 | D27: 862100 | H27: =ROUND(C27,-2)-ROUND(SUM(C21),-2) -ROUND(C22,-2)-ROUND(C23,-2)-ROUND(C24,-2)-ROUND(C25,-2)-ROUND(C26,-2) -> 0 | I27: =ROUND(D27,-2)-ROUND(SUM(D21),-2) -ROUND(D22,-2)-ROUND(D23,-2)-ROUND(D24,-2)-ROUND(D25,-2)-ROUND(D26,-2) -> 0 | J27: =ROUND(E27,-2)-ROUND(SUM(E21),-2) -ROUND(E22,-2)-ROUND(E23,-2)-ROUND(E24,-2)-ROUND(E25,-2)-ROUND(E26,-2) -> 0 | M27: =ROUND(C27,-2)-ROUND(C26,-2)-ROUND(C25,-2)-ROUND(C24,-2)-ROUND(C23,-2)-ROUND(C22,-2)-ROUND(C21,-2) -> 0 | N27: =ROUND(D27,-2)-ROUND(D26,-2)-ROUND(D25,-2)-ROUND(D24,-2)-ROUND(D23,-2)-ROUND(D22,-2)-ROUND(D21,-2) -> 0 | O27: =ROUND(E27,-2)-ROUND(E26,-2)-ROUND(E25,-2)-ROUND(E24,-2)-ROUND(E23,-2)-ROUND(E22,-2)-ROUND(E21,-2) -> 0 | R27: Other assets | S27: =ROUND(C26,-2)-ROUND(W27,-2) -> -22900 | T27: =ROUND(D26,-2)-ROUND(X27,-2) -> -12500 | W27: ='Barclays International Qrtly'!C26 -> 201500 | X27: ='Barclays International Qrtly'!H26 -> 202300 | Y27: ='Barclays International Qrtly'!J26 -> 189800
B28: Deposits at amortised cost | C28: 210000 | D28: 197219.43 | M28: =ROUND(C81,-2)+ROUND(C116,-2)-ROUND(C27,-2) -> 0 | N28: =ROUND(D81,-2)+ROUND(D116,-2)-ROUND(D27,-2) -> 0 | O28: =ROUND(E81,-2)+ROUND(E116,-2)-ROUND(E27,-2) -> 0 | R28: Total assets | S28: =ROUND(C27,-2)-ROUND(W28,-2) -> -291800 | T28: =ROUND(D27,-2)-ROUND(X28,-2) -> -56900 | W28: ='Barclays International Qrtly'!C27 -> 1153201 | X28: ='Barclays International Qrtly'!H27 -> 918950 | Y28: ='Barclays International Qrtly'!J27 -> 862128
B29: Derivative financial instrument liabilities | C29: 228897 | D29: 219577 | J29: LDR check | M29: =ROUND(C82,-2)+ROUND(C117,-2)-ROUND(C28,-2) -> 0 | N29: =ROUND(D82,-2)+ROUND(D117,-2)-ROUND(D28,-2) -> 0 | O29: =ROUND(E82,-2)+ROUND(E117,-2)-ROUND(E28,-2) -> 0 | R29: Deposits at amortised cost | S29: =ROUND(C28,-2)-ROUND(W29,-2) -> -53300 | T29: =ROUND(D28,-2)-ROUND(X29,-2) -> -18300 | W29: ='Barclays International Qrtly'!C28 -> 263251.72 | X29: ='Barclays International Qrtly'!H28 -> 215505.13 | Y29: ='Barclays International Qrtly'!J28 -> 197219.43
B30: Loan: deposit ratio | C30: 0.63 | D30: 0.65 | J30: =C30-ROUND((C21/C28),2) -> 0 | K30: =D30-ROUND((D21/D28),2) -> 0 | R30: Derivative financial instrument liabilities | S30: =ROUND(C29,-2)-ROUND(W30,-2) -> -109900 | T30: =ROUND(D29,-2)-ROUND(X30,-2) -> 6100 | W30: ='Barclays International Qrtly'!C29 -> 338776 | X30: ='Barclays International Qrtly'!H29 -> 213489 | Y30: ='Barclays International Qrtly'!J29 -> 219577
B31: Risk weighted assets | C31: 209243.3 | D31: 210741 | M31: =ROUND(C84,-2)+ROUND(C118,-2)-ROUND(C31,-2) -> 0 | N31: =ROUND(D84,-2)+ROUND(D118,-2)-ROUND(D31,-2) -> 0 | O31: =ROUND(E84,-2)+ROUND(E118,-2)-ROUND(E31,-2) -> 0 | R31: Loan: deposit ratio | S31: =ROUND(C30,-2)-ROUND(W31,-2) -> 0 | T31: =ROUND(D30,-2)-ROUND(X31,-2) -> 0 | W31: ='Barclays International Qrtly'!C30 -> 0.63 | X31: ='Barclays International Qrtly'!H30 -> 0.61 | Y31: ='Barclays International Qrtly'!J30 -> 0.65
B32: Period end allocated tangible equity | C32: 29622.522 | D32: 29900 | R32: Risk weighted assets | S32: =ROUND(C31,-2)-ROUND(W32,-2) -> -28700 | T32: =ROUND(D31,-2)-ROUND(X32,-2) -> -5400 | W32: ='Barclays International Qrtly'!C31 -> 237908 | X32: ='Barclays International Qrtly'!H31 -> 216070.94 | Y32: ='Barclays International Qrtly'!J31 -> 210741
R33: Period end allocated tangible equity | S33: =ROUND(C32,-2)-ROUND(W33,-2) -> -4600 | T33: =ROUND(D32,-2)-ROUND(X33,-2) -> -700 | W33: ='Barclays International Qrtly'!C32 -> 34241.552 | X33: ='Barclays International Qrtly'!H32 -> 30620.903 | Y33: ='Barclays International Qrtly'!J32 -> 29887.857
B34: Performance measures | H34: CIR Check
B35: Return on average allocated tangible equity | C35: 0.09 | D35: 0.084 | H35: =ROUND(-ROUND(C15,0)/ROUND(C8,0),2)-ROUND(C37,2) -> 0 | I35: =ROUND(-ROUND(D15,0)/ROUND(D8,0),2)-ROUND(D37,2) -> 0
B36: Average allocated tangible equity (£bn) | C36: 31168.529 | D36: 31000 | H36: =ROUND((-ROUND(C15,0)/ROUND(C8,0)),2) -> 0.64 | I36: =ROUND((-ROUND(D15,0)/ROUND(D8,0)),2) -> 0.69
B37: Cost: income ratio | C37: 0.64 | D37: 0.69 | P37: =C36-'CYYTD performance measures excl'!E27 -> 0 | Q37: =ROUND(D36,-2)-ROUND('PYYTD performance measures'!E27,-2) -> 0
B38: Loan loss rate (bps) | C38: 86.049635 | D38: 50 | M38: =ROUND(C88,-2)+ROUND(C130,-2)-ROUND(C36,-2) -> 0 | N38: =ROUND(D88,-2)+ROUND(D130,-2)-ROUND(D36,-2) -> 0
B39: Net interest margin | C39: 0.0407 | D39: 0.0411
H40: CIR Check
B41: Performance measures excluding litigation and conduct2 | C41: £m | D41: £m | H41: =ROUND(C45,2)-ROUND(H42,2) -> 0 | I41: =ROUND(D45,2)-ROUND(I42,2) -> 0
B42: Profit before tax | C42: 4233.7716 | D42: 3902 | E42: 8.5084572 | H42: =ROUND(((-ROUND(C15,0)+ROUND(C14,0))/ROUND(C8,0)),2) -> 0.64 | I42: =ROUND(((-ROUND(D15,0)+ROUND(D14,0))/ROUND(D8,0)),2) -> 0.68
B43: Attributable profit | C43: 2906.0373 | D43: 2705 | E43: 7.4306839 | H43: =IFERROR(ROUND(IF(C42>0,100*(ROUND(C42,0)-ROUND(D42,0))/ROUND(D42,0),-100*(ROUND(C42,0)-ROUND(D42,0))/ROUND(D42,0)),0)-ROUND(E42,0),0) -> 0 | P43: =ROUND(C42,0)-ROUND('CYYTD performance measures excl'!E17,0) -> 0 | Q43: =ROUND(D42,0)-ROUND('PYYTD performance measures'!E17,0) -> 0
B44: Return on average allocated tangible equity | C44: 0.093 | D44: 0.087 | H44: =IFERROR(ROUND(IF(C43>0,100*(ROUND(C43,0)-ROUND(D43,0))/ROUND(D43,0),-100*(ROUND(C43,0)-ROUND(D43,0))/ROUND(D43,0)),0)-ROUND(E43,0),0) -> 0 | J44: =(ROUND(C17,0)-ROUND(C14,0))-ROUND(C42,0) -> 0 | K44: =(ROUND(D17,0)-ROUND(D14,0))-ROUND(D42,0) -> 0 | M44: =ROUND(C135,0)+ROUND(C92,0)-ROUND(C42,0) -> 0 | N44: =ROUND(D135,0)+ROUND(D92,0)-ROUND(D42,0) -> 0 | P44: =C43-'CYYTD performance measures excl'!E22 -> 0 | Q44: =ROUND(D43,0)-ROUND('PYYTD performance measures'!E22,0) -> 0
B45: Cost: income ratio | C45: 0.64 | D45: 0.68 | M45: =ROUND(C136,0)+ROUND(C93,0)-ROUND(C43,0) -> 0 | N45: =ROUND(D136,0)+ROUND(D93,0)-ROUND(D43,0) -> 0 | P45: =C44-'CYYTD performance measures excl'!E29 -> 0 | Q45: =D44-'PYYTD performance measures'!E29 -> 0
H46: ROTE Check | P46: =ROUND(C45,0)-ROUND('CYYTD performance measures excl'!E12,0) -> 0 | Q46: =ROUND(D45,0)-ROUND('PYYTD performance measures'!D12,0) -> 0
B47: Analysis of Barclays International | H47: =ROUND(C35,3)-ROUND((C18/C36),3) -> 0 | I47: =ROUND(D35,3)-ROUND((D18/D36),3) -> 0
B48: Corporate and Investment Bank | C48: Year ended | D48: Year ended | G48: Ex L&C | H48: =ROUND(C44,3)-ROUND((C43/C36),3) -> 0 | I48: =ROUND(D44,3)-ROUND((D43/D36),3) -> 0
C49: 31.12.19 | D49: 31.12.18
B50: Income statement information | C50: £m | D50: £m | E50: % Change
B51: FICC | C51: 3364 | D51: 2863 | E51: 17 | H51: % Check | J51: Casting down check
B52: Equities | C52: 1887 | D52: 2037 | E52: -7.3146784 | H52: =IFERROR(ROUND(IF(C51>0,100*(ROUND(C51,0)-ROUND(D51,0))/ROUND(D51,0),-100*(ROUND(C51,0)-ROUND(D51,0))/ROUND(D51,0)),0)-ROUND(E51,0),0) -> 0
B53: Markets | C53: 5251 | D53: 4900 | E53: 7.2244898 | H53: =IFERROR(ROUND(IF(C52>0,100*(ROUND(C52,0)-ROUND(D52,0))/ROUND(D52,0),-100*(ROUND(C52,0)-ROUND(D52,0))/ROUND(D52,0)),0)-ROUND(E52,0),0) -> 0 | J53: =ROUND(C51,0)+ROUND(C52,0)-ROUND(C53,0) -> 0 | K53: =ROUND(D51,0)+ROUND(D52,0)-ROUND(D53,0) -> 0
B54: Advisory | C54: 776 | D54: 708 | E54: 10 | H54: =IFERROR(ROUND(IF(C56>0,100*(ROUND(C56,0)-ROUND(D56,0))/ROUND(D56,0),-100*(ROUND(C56,0)-ROUND(D56,0))/ROUND(D56,0)),0)-ROUND(E56,0),0) -> 0
B55: Equity capital markets | C55: 329 | D55: 300 | E55: 9.6666667 | H55: =IFERROR(ROUND(IF(C54>0,100*(ROUND(C54,0)-ROUND(D54,0))/ROUND(D54,0),-100*(ROUND(C54,0)-ROUND(D54,0))/ROUND(D54,0)),0)-ROUND(E54,0),0) -> 0
B56: Debt capital markets | C56: 1430 | D56: 1523 | E56: -6.0407091 | H56: =IFERROR(ROUND(IF(C53>0,100*(ROUND(C53,0)-ROUND(D53,0))/ROUND(D53,0),-100*(ROUND(C53,0)-ROUND(D53,0))/ROUND(D53,0)),0)-ROUND(E53,0),0) -> 0
B57: Banking fees | C57: 2535 | D57: 2531 | E57: - | H57: =IFERROR(ROUND(IF(C53>0,100*(ROUND(C53,0)-ROUND(D53,0))/ROUND(D53,0),-100*(ROUND(C53,0)-ROUND(D53,0))/ROUND(D53,0)),0)-ROUND(E53,0),0) -> 0 | J57: =ROUND(C54,0)+ROUND(C55,0)-ROUND(C57,0)+ROUND(C56,0) -> 0 | K57: =ROUND(D54,0)+ROUND(D55,0)-ROUND(D57,0)+ROUND(D56,0) -> 0
B58: Corporate lending | C58: 765 | D58: 878 | E58: -12.756264 | H58: =IFERROR(ROUND(IF(C57>0,100*(ROUND(C57,0)-ROUND(D57,0))/ROUND(D57,0),-100*(ROUND(C57,0)-ROUND(D57,0))/ROUND(D57,0)),0)-ROUND(E57,0),0) -> 0
B59: Transaction banking | C59: 1680 | D59: 1627 | E59: 3.2575292 | H59: =IFERROR(ROUND(IF(C58>0,100*(ROUND(C58,0)-ROUND(D58,0))/ROUND(D58,0),-100*(ROUND(C58,0)-ROUND(D58,0))/ROUND(D58,0)),0)-ROUND(E58,0),0) -> 0
B60: Corporate | C60: 2445 | D60: 2505 | E60: -2.3552894 | H60: =IFERROR(ROUND(IF(C59>0,100*(ROUND(C59,0)-ROUND(D59,0))/ROUND(D59,0),-100*(ROUND(C59,0)-ROUND(D59,0))/ROUND(D59,0)),0)-ROUND(E59,0),0) -> 0
B61: Other1 | C61: 0 | D61: -171 | H61: =IFERROR(ROUND(IF(C60>0,100*(ROUND(C60,0)-ROUND(D60,0))/ROUND(D60,0),-100*(ROUND(C60,0)-ROUND(D60,0))/ROUND(D60,0)),0)-ROUND(E60,0),0) -> 0 | J61: =ROUND(C58,0)+ROUND(C59,0)-ROUND(C60,0) -> 0 | K61: =ROUND(D58,0)+ROUND(D59,0)-ROUND(D60,0) -> 0
B62: Total income | C62: 10231 | D62: 9765 | E62: 4.7721454 | H62: =IFERROR(ROUND(IF(C61>0,100*(ROUND(C61,0)-ROUND(D61,0))/ROUND(D61,0),-100*(ROUND(C61,0)-ROUND(D61,0))/ROUND(D61,0)),0)-ROUND(E61,0),0) -> 0
B63: Credit impairment (charges)/releases | C63: -157 | D63: 150 | H63: =IFERROR(ROUND(IF(C62>0,100*(ROUND(C62,0)-ROUND(D62,0))/ROUND(D62,0),-100*(ROUND(C62,0)-ROUND(D62,0))/ROUND(D62,0)),0)-ROUND(E62,0),0) -> 0 | J63: =ROUND(C53,0)+ROUND(C60,0)+ROUND(C61,0)+ROUND(C57,0)-ROUND(C62,0) -> 0 | K63: =ROUND(D53,0)+ROUND(D60,0)+ROUND(D61,0)+ROUND(D57,0)-ROUND(D62,0) -> 0
B64: Net operating income | C64: 10074 | D64: 9915 | E64: 1.6036309 | H64: =IFERROR(ROUND(IF(C63>0,100*(ROUND(C63,0)-ROUND(D63,0))/ROUND(D63,0),-100*(ROUND(C63,0)-ROUND(D63,0))/ROUND(D63,0)),0)-ROUND(E63,0),0) -> 0
B65: Operating costs | C65: -6882 | D65: -7093 | E65: 2.9747639 | H65: =IFERROR(ROUND(IF(C64>0,100*(ROUND(C64,0)-ROUND(D64,0))/ROUND(D64,0),-100*(ROUND(C64,0)-ROUND(D64,0))/ROUND(D64,0)),0)-ROUND(E64,0),0) -> 0 | J65: =ROUND(C62,0)+ROUND(C63,0)-ROUND(C64,0) -> 0 | K65: =ROUND(D62,0)+ROUND(D63,0)-ROUND(D64,0) -> 0
B66: UK bank levy | C66: -156 | D66: -188 | E66: 17.021277 | H66: =IFERROR(ROUND(IF(C65>0,100*(ROUND(C65,0)-ROUND(D65,0))/ROUND(D65,0),-100*(ROUND(C65,0)-ROUND(D65,0))/ROUND(D65,0)),0)-ROUND(E65,0),0) -> 0
B67: Operating expenses | C67: -7038 | D67: -7281 | E67: 3.3374536 | H67: =IFERROR(ROUND(IF(C66>0,100*(ROUND(C66,0)-ROUND(D66,0))/ROUND(D66,0),-100*(ROUND(C66,0)-ROUND(D66,0))/ROUND(D66,0)),0)-ROUND(E66,0),0) -> 0 | J67: =ROUND(C65,0)+ROUND(C66,0)-ROUND(C67,0) -> 0 | K67: =ROUND(D65,0)+ROUND(D66,0)-ROUND(D67,0) -> 0
B68: Litigation and conduct | C68: -109.36277 | D68: -68 | E68: -60.294118 | H68: =IFERROR(ROUND(IF(C65>0,100*(ROUND(C65,0)-ROUND(D65,0))/ROUND(D65,0),-100*(ROUND(C65,0)-ROUND(D65,0))/ROUND(D65,0)),0)-ROUND(E65,0),0) -> 0
B69: Total operating expenses | C69: -7147 | D69: -7349 | E69: 2.7486733 | H69: =IFERROR(ROUND(IF(C68>0,100*(ROUND(C68,0)-ROUND(D68,0))/ROUND(D68,0),-100*(ROUND(C68,0)-ROUND(D68,0))/ROUND(D68,0)),0)-ROUND(E68,0),0) -> 0
B70: Other net income | C70: 28 | D70: 27 | E70: 3.7037037 | H70: =IFERROR(ROUND(IF(C69>0,100*(ROUND(C69,0)-ROUND(D69,0))/ROUND(D69,0),-100*(ROUND(C69,0)-ROUND(D69,0))/ROUND(D69,0)),0)-ROUND(E69,0),0) -> 0 | J70: =ROUND(C65,0)+ROUND(C68,0)-ROUND(C69,0)+C66 -> 0 | K70: =ROUND(D65,0)+ROUND(D68,0)-ROUND(D69,0)+D66 -> 0
B71: Profit before tax | C71: 2955 | D71: 2593 | E71: 13.960663 | H71: =IFERROR(ROUND(IF(C70>0,100*(ROUND(C70,0)-ROUND(D70,0))/ROUND(D70,0),-100*(ROUND(C70,0)-ROUND(D70,0))/ROUND(D70,0)),0)-ROUND(E70,0),0) -> 0 | P71: Consistency
B72: Attributable profit2 | C72: 1980 | D72: 1781 | E72: 11.173498 | H72: =IFERROR(ROUND(IF(C71>0,100*(ROUND(C71,0)-ROUND(D71,0))/ROUND(D71,0),-100*(ROUND(C71,0)-ROUND(D71,0))/ROUND(D71,0)),0)-ROUND(E71,0),0) -> 0 | J72: =ROUND(C62,0)+ROUND(C63,0)+ROUND(C69,0)+ROUND(C70,0)-ROUND(C71,0) -> 0 | K72: =ROUND(D62,0)+ROUND(D63,0)+ROUND(D69,0)+ROUND(D70,0)-ROUND(D71,0) -> 0 | P72: =C71-'CYYTD performance measures excl'!C15 -> 0 | Q72: =D71-'PYYTD performance measures'!C15 -> 0
H73: =IFERROR(ROUND(IF(C72>0,100*(ROUND(C72,0)-ROUND(D72,0))/ROUND(D72,0),-100*(ROUND(C72,0)-ROUND(D72,0))/ROUND(D72,0)),0)-ROUND(E72,0),0) -> 0 | O73: AP | P73: =C72-'CYYTD performance measures excl'!C20 -> 0 | Q73: =D72-'PYYTD performance measures'!C20 -> 0
B74: Balance sheet information | C74: £bn | D74: £bn | I74: AP
B75: Loans and advances at amortised cost | C75: 92042.316 | D75: 86400
B76: Trading portfolio assets | C76: 113300 | D76: 104000 | W76: BI quarterly
B77: Derivative financial instrument assets | C77: 228826 | D77: 222100 | R77: Consistency with quarterlies check | S77: =CQtr -> #REF! | T77: Q418 | U77: Q318 | W77: =CQtr -> #REF! | X77: Q418 | Y77: Q318
B78: Financial assets at fair value through the income statement | C78: 127676.91 | D78: 144200 | R78: Loans and advances at amortised cost | S78: =ROUND(C75,-2)-ROUND(W78,-2) -> -36200 | T78: =ROUND(D75,-2)-ROUND(X78,-2) -> -4200 | W78: ='Barclays International Qrtly'!C77 -> 128173.98 | X78: ='Barclays International Qrtly'!H77 -> 90629.573 | Y78: ='Barclays International Qrtly'!J77 -> 86369.046
B79: Cash collateral and settlement balances | C79: 78508.939 | D79: 73400 | R79: Trading portfolio assets | S79: =ROUND(C76,-2)-ROUND(W79,-2) -> 11800 | T79: =ROUND(D76,-2)-ROUND(X79,-2) -> -13200 | W79: ='Barclays International Qrtly'!C78 -> 101487 | X79: ='Barclays International Qrtly'!H78 -> 117200 | Y79: ='Barclays International Qrtly'!J78 -> 104000
B80: Other assets | C80: 155300 | D80: 160400 | R80: Derivative financial instrument assets | S80: =ROUND(C77,-2)-ROUND(W80,-2) -> -112600 | T80: =ROUND(D77,-2)-ROUND(X80,-2) -> 4800 | W80: ='Barclays International Qrtly'!C79 -> 341439 | X80: ='Barclays International Qrtly'!H79 -> 217300 | Y80: ='Barclays International Qrtly'!J79 -> 222100
B81: Total assets | C81: 795600 | D81: 790500 | R81: Financial assets at fair value through the income statement | S81: =ROUND(C78,-2)-ROUND(W81,-2) -> -60100 | T81: =ROUND(D78,-2)-ROUND(X81,-2) -> -8700 | W81: ='Barclays International Qrtly'!C80 -> 187772.96 | X81: ='Barclays International Qrtly'!H80 -> 152900 | Y81: ='Barclays International Qrtly'!J80 -> 144200
B82: Deposits at amortised cost | C82: 146200 | D82: 136300 | R82: Cash collateral and settlement balances | S82: =ROUND(C79,-2)-ROUND(W82,-2) -> -73700 | T82: =ROUND(D79,-2)-ROUND(X82,-2) -> -23500 | W82: ='Barclays International Qrtly'!C81 -> 152246.81 | X82: ='Barclays International Qrtly'!H81 -> 96900 | Y82: ='Barclays International Qrtly'!J81 -> 73400
B83: Derivative financial instrument liabilities | C83: 228867 | D83: 219600 | J83: =ROUND(C81,-2)-ROUND(C80,-2)-ROUND(C79,-2)-ROUND(C78,-2)-ROUND(C77,-2)-ROUND(C76,-2)-ROUND(C75,-2) -> 0 | K83: =ROUND(D81,-2)-ROUND(D80,-2)-ROUND(D79,-2)-ROUND(D78,-2)-ROUND(D77,-2)-ROUND(D76,-2)-ROUND(D75,-2) -> 0 | L83: =ROUND(E81,-2)-ROUND(E80,-2)-ROUND(E79,-2)-ROUND(E78,-2)-ROUND(E77,-2)-ROUND(E76,-2)-ROUND(E75,-2) -> 0 | R83: Other assets | S83: =ROUND(C80,-2)-ROUND(W83,-2) -> -16100 | T83: =ROUND(D80,-2)-ROUND(X83,-2) -> -2800 | W83: ='Barclays International Qrtly'!C82 -> 171400 | X83: ='Barclays International Qrtly'!H82 -> 163200 | Y83: ='Barclays International Qrtly'!J82 -> 160400
B84: Risk weighted assets | C84: 171452.99 | D84: 170900 | R84: Total assets | S84: =ROUND(C81,-2)-ROUND(W84,-2) -> -286900 | T84: =ROUND(D81,-2)-ROUND(X84,-2) -> -47600 | W84: ='Barclays International Qrtly'!C83 -> 1082486 | X84: ='Barclays International Qrtly'!H83 -> 838100 | Y84: ='Barclays International Qrtly'!J83 -> 790500
R85: Deposits at amortised cost | S85: =ROUND(C82,-2)-ROUND(W85,-2) -> -52200 | T85: =ROUND(D82,-2)-ROUND(X85,-2) -> -15100 | W85: ='Barclays International Qrtly'!C84 -> 198413.72 | X85: ='Barclays International Qrtly'!H84 -> 151408.63 | Y85: ='Barclays International Qrtly'!J84 -> 136278.73
B86: Performance measures | R86: Derivative financial instrument liabilities | S86: =ROUND(C83,-2)-ROUND(W86,-2) -> -109800 | T86: =ROUND(D83,-2)-ROUND(X86,-2) -> 6100 | W86: ='Barclays International Qrtly'!C85 -> 338703 | X86: ='Barclays International Qrtly'!H85 -> 213500 | Y86: ='Barclays International Qrtly'!J85 -> 219600
B87: Return on average allocated tangible equity | C87: 0.076 | D87: 0.069 | R87: Risk weighted assets | S87: =ROUND(C84,-2)-ROUND(W87,-2) -> -30200 | T87: =ROUND(D84,-2)-ROUND(X87,-2) -> -5700 | W87: ='Barclays International Qrtly'!C86 -> 201747 | X87: ='Barclays International Qrtly'!H86 -> 176589.56 | Y87: ='Barclays International Qrtly'!J86 -> 170902
B88: Average allocated tangible equity (£bn) | C88: 25886.815 | D88: 26000
B89: Cost: income ratio | C89: 0.7 | D89: 0.75
B91: Performance measures excluding litigation and conduct3 | C91: £m | D91: £m | H91: CIR Check | K91: ROTE check
B92: Profit before tax | C92: 3064.3628 | D92: 2661 | E92: 15.144682 | H92: =ROUND(H93,2)-ROUND(C89,2) -> 0 | I92: =ROUND(I93,2)-ROUND(D89,2) -> 0 | K92: =ROUND(C87,3)-ROUND((ROUND(C72,0)/ROUND(C88,-2)),3) -> 0 | L92: =ROUND(D87,3)-ROUND((ROUND(D72,0)/ROUND(D88,-2)),3) -> 0
B93: Attributable profit | C93: 2063.5163 | D93: 1843 | E93: 11.991319 | H93: =-1*(ROUND(C69,0))/ROUND(C62,0) -> 0.69856319 | I93: =-1*(ROUND(D69,0))/D62 -> 0.75258577 | J93: ex L&C | K93: =ROUND(C94,3)-ROUND((ROUND(C93,0)/ROUND(C88,-2)),3) -> 0 | L93: =ROUND(D94,3)-ROUND((ROUND(D93,0)/ROUND(D88,-2)),3) -> 0
B94: Return on average allocated tangible equity | C94: 0.08 | D94: 0.071
B95: Cost: income ratio | C95: 0.69 | D95: 0.75 | H95: =IFERROR(ROUND(IF(C92>0,100*(ROUND(C92,0)-ROUND(D92,0))/ROUND(D92,0),-100*(ROUND(C92,0)-ROUND(D92,0))/ROUND(D92,0)),0)-ROUND(E92,0),0) -> 0 | K95: =ROUND(C92,0)-SUM('BI performance measures excl'!B44:F44) -> -357.22717 | L95: =ROUND(D92,-1)-ROUND(SUM('BI performance measures excl'!G44:K44),-1) -> 340 | P95: =ROUND(C92,0)-ROUND('CYYTD performance measures excl'!C17,0) -> 0 | Q95: =ROUND(D92,0)-ROUND('PYYTD performance measures'!C17,0) -> 0
H96: =IFERROR(ROUND(IF(C93>0,100*(ROUND(C93,0)-ROUND(D93,0))/ROUND(D93,0),-100*(ROUND(C93,0)-ROUND(D93,0))/ROUND(D93,0)),0)-ROUND(E93,0),0) -> 0 | P96: =C93-'CYYTD performance measures excl'!C22 -> 0 | Q96: =ROUND(D93,0)-ROUND('PYYTD performance measures'!C22,0) -> 0
B97: Consumer, Cards and Payments | C97: Year ended | D97: Year ended | P97: =C94-'CYYTD performance measures excl'!C29 -> 0 | Q97: =D94-'PYYTD performance measures'!C29 -> 0
C98: 31.12.19 | D98: 31.12.18 | H98: CIR Check ex L&C | P98: =ROUND(C95,0)-ROUND('CYYTD performance measures excl'!C12,0) -> 0 | Q98: =ROUND(D95,0)-ROUND('PYYTD performance measures'!C12,0) -> 0
B99: Income statement information | C99: £m | D99: £m | E99: % Change | H99: =ROUND(C95,2)-ROUND(H100,2) -> 0 | I99: =ROUND(D95,2)-ROUND(I100,2) -> 0
B100: Net interest income | C100: 2822 | D100: 2731 | E100: 3.3321128 | H100: =-1*(ROUND(C69,0)-ROUND(C68,0))/ROUND(C62,0) -> 0.6879093 | I100: =-1*(ROUND(D69,0)-ROUND(D68,0))/ROUND(D62,0) -> 0.74562212
B101: Net fee, commission, trading and other income | C101: 1622 | D101: 1530 | E101: 6.0130719
B102: Total income | C102: 4444 | D102: 4261 | E102: 4.2947665 | H102: % Check | J102: Casting down check
B103: Credit impairment charges | C103: -1016 | D103: -808 | E103: -25.742574 | H103: =IFERROR(ROUND(IF(C100>0,100*(ROUND(C100,0)-ROUND(D100,0))/ROUND(D100,0),-100*(ROUND(C100,0)-ROUND(D100,0))/ROUND(D100,0)),0)-ROUND(E100,0),0) -> 0 | J103: =ROUND(C100,0)+ROUND(C101,0)-ROUND(C102,0) -> 0 | K103: =ROUND(D100,0)+ROUND(D101,0)-ROUND(D102,0) -> 0
...

Sheet Head Office YTD
B2: Head Office | C2: Year ended | D2: Year ended
C3: 31.12.19 | D3: 31.12.18
B4: Income statement information | C4: £m | D4: £m | E4: % Change | H4: % Check | J4: Casting down check | L4: Checking to Appendix
B5: Net interest income | C5: -422 | D5: -781 | E5: 45.966709 | H5: =IFERROR(ROUND(IF(C5>0,100*(ROUND(C5,0)-ROUND(D5,0))/ROUND(D5,0),-100*(ROUND(C5,0)-ROUND(D5,0))/ROUND(D5,0)),0)-ROUND(E5,0),0) -> 0 | J5: =CQtr&" YTD" -> #REF! | K5: =PPPPQtr&" YTD" -> #REF! | L5: =CQtr&" YTD" -> #REF! | M5: =PPPPQtr&" YTD" -> #REF!
B6: Net fee, commission and other income | C6: 26 | D6: 508 | E6: -94.88189 | H6: =IFERROR(ROUND(IF(C6>0,100*(ROUND(C6,0)-ROUND(D6,0))/ROUND(D6,0),-100*(ROUND(C6,0)-ROUND(D6,0))/ROUND(D6,0)),0)-ROUND(E6,0),0) -> 0
B7: Total income | C7: -396 | D7: -273 | E7: -45.054945 | H7: =IFERROR(ROUND(IF(C7>0,100*(ROUND(C7,0)-ROUND(D7,0))/ROUND(D7,0),-100*(ROUND(C7,0)-ROUND(D7,0))/ROUND(D7,0)),0)-ROUND(E7,0),0) -> 0 | J7: =ROUND(C5,0)+ROUND(C6,0)-ROUND(C7,0) -> 0 | K7: =ROUND(D5,0)+ROUND(D6,0)-ROUND(D7,0) -> 0 | L7: =C7-'CYYTD performance measures excl'!F10 -> 0 | M7: =D7-'PYYTD performance measures'!F10 -> 0
B8: Credit impairment (charges)/releases | C8: -27 | D8: 16 | H8: =IFERROR(ROUND(IF(C8>0,100*(ROUND(C8,0)-ROUND(D8,0))/ROUND(D8,0),-100*(ROUND(C8,0)-ROUND(D8,0))/ROUND(D8,0)),0)-ROUND(E8,0),0) -> 0
B9: Net operating income | C9: -423 | D9: -257 | E9: -64.59144 | H9: =IFERROR(ROUND(IF(C9>0,100*(ROUND(C9,0)-ROUND(D9,0))/ROUND(D9,0),-100*(ROUND(C9,0)-ROUND(D9,0))/ROUND(D9,0)),0)-ROUND(E9,0),0) -> 0 | J9: =ROUND(C7,0)+ROUND(C8,0)-ROUND(C9,0) -> 0 | K9: =ROUND(D7,0)+ROUND(D8,0)-ROUND(D9,0) -> 0
B10: Operating costs | C10: -200 | D10: -228 | E10: 12.280702 | H10: =IFERROR(ROUND(IF(C10>0,100*(ROUND(C10,0)-ROUND(D10,0))/ROUND(D10,0),-100*(ROUND(C10,0)-ROUND(D10,0))/ROUND(D10,0)),0)-ROUND(E10,0),0) -> 0 | L10: =ROUND(C15,0)-ROUND(C14,0)-ROUND('CYYTD performance measures excl'!F8,0) -> 0 | M10: =D10+D11+D13-'PYYTD performance measures'!F8 -> 0
B11: UK bank levy | C11: -11 | D11: -13 | E11: 15.384615 | H11: =IFERROR(ROUND(IF(C11>0,100*(ROUND(C11,0)-ROUND(D11,0))/ROUND(D11,0),-100*(ROUND(C11,0)-ROUND(D11,0))/ROUND(D11,0)),0)-ROUND(E11,0),0) -> 0
B12: Operating expenses | C12: -211 | D12: -241 | E12: 12.448133 | H12: =IFERROR(ROUND(IF(C12>0,100*(ROUND(C12,0)-ROUND(D12,0))/ROUND(D12,0),-100*(ROUND(C12,0)-ROUND(D12,0))/ROUND(D12,0)),0)-ROUND(E12,0),0) -> 0 | J12: =ROUND(C10,0)+ROUND(C11,0)-ROUND(C12,0) -> 0 | K12: =ROUND(D10,0)+ROUND(D11,0)-ROUND(D12,0) -> 0
B13: GMP charge | C13: 0 | D13: -140 | H13: =IFERROR(ROUND(IF(C13>0,100*(ROUND(C13,0)-ROUND(D13,0))/ROUND(D13,0),-100*(ROUND(C13,0)-ROUND(D13,0))/ROUND(D13,0)),0)-ROUND(E13,0),0) -> 0
B14: Litigation and conduct | C14: -151.39434 | D14: -1597 | E14: 90.544771 | H14: =IFERROR(ROUND(IF(C14>0,100*(ROUND(C14,0)-ROUND(D14,0))/ROUND(D14,0),-100*(ROUND(C14,0)-ROUND(D14,0))/ROUND(D14,0)),0)-ROUND(E14,0),0) -> 0
B15: Total operating expenses | C15: -362 | D15: -1978 | E15: 81.698686 | H15: =IFERROR(ROUND(IF(C15>0,100*(ROUND(C15,0)-ROUND(D15,0))/ROUND(D15,0),-100*(ROUND(C15,0)-ROUND(D15,0))/ROUND(D15,0)),0)-ROUND(E15,0),0) -> 0 | J15: =ROUND(C10,0)+ROUND(C14,0)+ROUND(C11,0)+ROUND(C13,0)-ROUND(C15,0) -> 0 | K15: =ROUND(D10,0)+ROUND(D14,0)+ROUND(D11,0)+ROUND(D13,0)-ROUND(D15,0) -> 0 | L15: =C15-'CYYTD performance measures excl'!F6 -> 0 | M15: =D15-'PYYTD performance measures'!F6 -> 0
B16: Other net income/(expenses) | C16: 2 | D16: -2 | H16: =IFERROR(ROUND(IF(C16>0,100*(ROUND(C16,0)-ROUND(D16,0))/ROUND(D16,0),-100*(ROUND(C16,0)-ROUND(D16,0))/ROUND(D16,0)),0)-ROUND(E16,0),0) -> 0
B17: Loss before tax | C17: -783 | D17: -2237 | E17: 64.997765 | H17: =IFERROR(ROUND(IF(C17>0,100*(ROUND(C17,0)-ROUND(D17,0))/ROUND(D17,0),-100*(ROUND(C17,0)-ROUND(D17,0))/ROUND(D17,0)),0)-ROUND(E17,0),0) -> 0 | J17: =ROUND(C9,0)+ROUND(C15,0)+ROUND(C16,0)-ROUND(C17,0) -> 0 | K17: =ROUND(D9,0)+ROUND(D15,0)+ROUND(D16,0)-ROUND(D17,0) -> 0 | L17: =ROUND(C17,0)-ROUND('CYYTD performance measures excl'!F15,0) -> 0 | M17: =D17-'PYYTD performance measures'!F15 -> 0
B18: Attributable loss1 | C18: -636 | D18: -2200 | E18: 71.090909 | H18: =IFERROR(ROUND(IF(C18>0,100*(ROUND(C18,0)-ROUND(D18,0))/ROUND(D18,0),-100*(ROUND(C18,0)-ROUND(D18,0))/ROUND(D18,0)),0)-ROUND(E18,0),0) -> 0 | L18: =ROUND(C18,0)-ROUND('CYYTD performance measures excl'!F20,0) -> 0 | M18: =D18-'PYYTD performance measures'!F20 -> 0
B20: Balance sheet information | C20: £bn | D20: £bn
B21: Total assets | C21: 21040 | D21: 21500
B22: Risk weighted assets | C22: 10986.984 | D22: 26000 | H22: =ROUND(C21,-2)-ROUND('Head Office Qrtly'!C21,-2) -> -2600 | I22: =ROUND(D21,-2)-ROUND('Head Office Qrtly'!H21,-2) -> 100
B23: Period end allocated tangible equity | C23: 5562.7824 | D23: 4900 | H23: =ROUND(C22,-2)-ROUND('Head Office Qrtly'!C22,-2) -> 1000 | I23: =ROUND(D22,-2)-ROUND('Head Office Qrtly'!H22,-2) -> -1000
H24: =ROUND(C23,-2)-ROUND('Head Office Qrtly'!C23,-2) -> 1200 | I24: =ROUND(D23,-2)-ROUND('Head Office Qrtly'!H23,-2) -> 400
B25: Performance measures
B26: Average allocated tangible equity (£bn) | C26: 5056.3352 | D26: 3100
B28: Performance measures excluding litigation and conduct2 | C28: £m | D28: £m | L28: =C26-'CYYTD performance measures excl'!F27 -> 0 | M28: =ROUND(D26,-2)-ROUND('PYYTD performance measures'!F27,-2) -> 0
B29: Loss before tax | C29: -631.60566 | D29: -640 | E29: 1.25
B30: Attributable loss | C30: -524.84075 | D30: -642 | E30: 18.224299
H31: =IFERROR(ROUND(IF(C29>0,100*(ROUND(C29,0)-ROUND(D29,0))/ROUND(D29,0),-100*(ROUND(C29,0)-ROUND(D29,0))/ROUND(D29,0)),0)-ROUND(E29,0),0) -> 0 | J31: =ROUND(C14,0)-ROUND(C17,0)+ROUND(C29,0) -> 0 | K31: =ROUND(D14,0)-ROUND(D17,0)+ROUND(D29,0) -> 0 | L31: =C29-'CYYTD performance measures excl'!F17 -> 0 | M31: =ROUND(D29,-2)-ROUND('PYYTD performance measures'!F17,-2) -> 0
H32: =IFERROR(ROUND(IF(C30>0,100*(ROUND(C30,0)-ROUND(D30,0))/ROUND(D30,0),-100*(ROUND(C30,0)-ROUND(D30,0))/ROUND(D30,0)),0)-ROUND(E30,0),0) -> 0 | L32: =C30-'CYYTD performance measures excl'!F22 -> 0 | M32: =D30-'PYYTD performance measures'!F22 -> 0

Sheet Group Qrtly
B1: Barclays Group
C2: Q120 | E2: Q419 | F2: Q319 | G2: Q219 | H2: Q119 | J2: Q418 | K2: Q318 | L2: Q218
B3: Income statement information | C3: £m | E3: £m | F3: £m | G3: £m | H3: £m | J3: £m | K3: £m | L3: £m
B4: Net interest income | C4: 2331 | E4: 2344 | F4: 2445 | G4: 2360 | H4: 2258 | J4: 2296 | K4: 2388 | L4: 2190
B5: Net fee, commission and other income | C5: 3952 | E5: 2957 | F5: 3096 | G5: 3178 | H5: 2994 | J5: 2777 | K5: 2741 | L5: 3386
B6: Total income | C6: 6283 | E6: 5301 | F6: 5541 | G6: 5538 | H6: 5252 | J6: 5073 | K6: 5129 | L6: 5576
B7: Credit impairment charges | C7: -2115 | E7: -523 | F7: -461 | G7: -480 | H7: -448 | J7: -643 | K7: -254 | L7: -283
B8: Net operating income | C8: 4168 | E8: 4778 | F8: 5080 | G8: 5058 | H8: 4804 | J8: 4430 | K8: 4875 | L8: 5293
B9: Operating costs | C9: -3253 | E9: -3308 | F9: -3293 | G9: -3501 | H9: -3257 | J9: -3624 | K9: -3329 | L9: -3310
B10: UK bank levy | C10: 0 | E10: -226.4 | F10: 0 | G10: 0 | H10: 0 | J10: -269 | K10: 0 | L10: 0
B11: Operating expenses | C11: -3252.6591 | E11: -3533.7577 | F11: -3293 | G11: -3501 | H11: -3257 | J11: -3893 | K11: -3329.1489 | L11: -3310
B12: Guaranteed Minimum Pensions (GMP) charge | C12: 0 | E12: 0 | F12: 0 | G12: 0 | H12: 0 | J12: -140 | K12: 0 | L12: 0
B13: Litigation and conduct | C13: -10.340854 | E13: -167.24226 | F13: -1568 | G13: -52.709985 | H13: -60.842181 | J13: -60 | K13: -104.85113 | L13: -81
B14: Total operating expenses | C14: -3263 | E14: -3701 | F14: -4861 | G14: -3554 | H14: -3318 | J14: -4093 | K14: -3434 | L14: -3391
B15: Other net income/(expenses) | C15: 8 | E15: 20 | F15: 27 | G15: 27 | H15: -3 | J15: 37 | K15: 20 | L15: -7
... B21: Attributable profit/(loss) | C21: 605 | E21: 681 | F21: -292 | G21: 1034 | H21: 1038 | J21: -14 | K21: 1050 | L21: 1279
B23: Performance measures
B24: Return on average tangible shareholders' equity | C24: 0.051 | E24: 0.059 | F24: -0.024 | G24: 0.09 | H24: 0.092 | J24: -0.001 | K24: 0.094 | L24: 0.118
B25: Average tangible shareholders' equity (£bn) | C25: 46994.626 | E25: 46426.648 | F25: 48351.201 | G25: 46207.655 | H25: 45246.744 | J25: 44300 | K25: 44645.617 | L25: 43500
B26: Cost: income ratio | C26: 0.52 | E26: 0.7 | F26: 0.88 | G26: 0.64 | H26: 0.63 | J26: 0.81 | K26: 0.67 | L26: 0.61
B27: Loan loss rate (bps) | C27: 222.58505 | E27: 59.902287 | F27: 51.895366 | G27: 55.93486 | H27: 54 | J27: 77 | K27: 30 | L27: 35
B28: Basic earnings/(loss) per share | C28: 3.5015357 | E28: 3.9476247 | F28: -1.6984588 | G28: 6.0194272 | H28: 6.0663075 | J28: -0.081404377 | K28: 6.1448975 | L28: 7.5
B30: Performance measures excluding litigation and conduct | C30: £m | E30: £m | F30: £m | G30: £m | H30: £m | J30: £m | K30: £m | L30: £m
B31: Profit before tax | C31: 923.34085 | E31: 1264.2423 | F31: 1814 | G31: 1583.71 | H31: 1544 | J31: 434 | K31: 1565.8511 | L31: 1976
B32: Attributable profit | C32: 604.40094 | E32: 803.25437 | F32: 1232.8386 | G32: 1074.4374 | H32: 1084 | J32: 48 | K32: 1135 | L32: 1338
B33: Return on average tangible shareholders' equity | C33: 0.051 | E33: 0.069 | F33: 0.102 | G33: 0.093 | H33: 0.096 | J33: 0.004 | K33: 0.102 | L33: 0.123
B34: Cost: income ratio | C34: 0.52 | E34: 0.67 | F34: 0.59 | G34: 0.63 | H34: 0.62 | J34: 0.79 | K34: 0.65 | L34: 0.59
B35: Basic earnings per share | C35: 3.4980685 | E35: 4.6700247 | F35: 7.1709778 | G35: 6.2548337 | H35: 6.33 | J35: 0.3 | K35: 6.6358918 | L35: 7.84
B37: Balance sheet and capital management | C37: £bn | E37: £bn | F37: £bn | G37: £bn | H37: £bn | J37: £bn | K37: £bn | L37: £bn
B38: Total assets | C38: 1444297 | E38: 1140174.1 | F38: 1290352 | G38: 1232823 | H38: 1193543 | J38: 1133283 | K38: 1170776 | L38: 1149600
B39: Tangible net asset value per share | C39: 284.38013 | E39: 262.31927 | F39: 273.7296 | G39: 275 | H39: 266 | J39: 262 | K39: 260 | L39: 259
B40: Common equity tier 1 ratio | C40: 0.131 | E40: 0.138 | F40: 0.134 | G40: 0.134 | H40: 0.13 | J40: 0.132 | K40: 0.132 | L40: 0.13
B41: Common equity tier 1 capital | C41: 42484 | E41: 40813.416 | F41: 41875.68 | G41: 42888 | H41: 41400 | J41: 41100 | K41: 41700 | L41: 41400
B42: Risk weighted assets | C42: 325631 | E42: 295131.09 | F42: 313261 | G42: 319107 | H42: 319670.58 | J42: 311925 | K42: 316167 | L42: 319300
B43: Average UK leverage ratio | C43: 0.045 | E43: 0.045 | F43: 0.046 | G43: 0.047 | H43: 0.046 | J43: 0.045 | K43: 0.046 | L43: 0.046
B44: Average UK leverage exposure | C44: 1176200 | E44: 1142800 | F44: 1171200 | G44: 1134600 | H44: 1105500 | J44: 1110000 | K44: 1119000 | L44: 1081800
B45: UK leverage ratio | C45: 0.045 | E45: 0.051 | F45: 0.048 | G45: 0.051 | H45: 0.049 | J45: 0.051 | K45: 0.049 | L45: 0.049
B46: UK leverage exposure | C46: 1178700 | E46: 1007700 | F46: 1099800 | G46: 1079400 | H46: 1065000 | J46: 998600 | K46: 1063500 | L46: 1030100
B48: Funding and liquidity
B49: Group liquidity pool (£bn) | C49: 237000 | E49: 211000 | F49: 226000 | G49: 238000 | H49: 232000 | J49: 227000 | K49: 213000 | L49: 214000
B50: Liquidity coverage ratio | C50: 1.55 | E50: 1.6 | F50: 1.51 | G50: 1.56 | H50: 1.6 | J50: 1.69 | K50: 1.61 | L50: 1.54
B51: Loan: deposit ratio | C51: 0.79 | E51: 0.82 | F51: 0.82 | G51: 0.82 | H51: 0.8 | J51: 0.83 | K51: 0.83 | L51: 0.83

Sheet Barclays UK Qrtly
B2: Barclays UK
C3: Q120 | E3: Q419 | F3: Q319 | G3: Q219 | H3: Q119 | J3: Q418 | K3: Q318 | L3: Q218
B4: Income statement information | C4: £m | E4: £m | F4: £m | G4: £m | H4: £m | J4: £m | K4: £m | L4: £m
B5: Net interest income | C5: 1412 | E5: 1478 | F5: 1503 | G5: 1438 | H5: 1469 | J5: 1513 | K5: 1529 | L5: 1493
B6: Net fee, commission and other income | C6: 292 | E6: 481 | F6: 343 | G6: 333 | H6: 308 | J6: 350 | K6: 367 | L6: 343
B7: Total income | C7: 1704 | E7: 1959 | F7: 1846 | G7: 1771 | H7: 1777 | J7: 1863 | K7: 1896 | L7: 1836
B8: Credit impairment charges | C8: -481 | E8: -190 | F8: -101 | G8: -230 | H8: -191 | J8: -296 | K8: -115 | L8: -214
B9: Net operating income | C9: 1223 | E9: 1769 | F9: 1745 | G9: 1541 | H9: 1586 | J9: 1567 | K9: 1781 | L9: 1622
B10: Operating costs | C10: -1023 | E10: -1023 | F10: -952 | G10: -1022 | H10: -999 | J10: -1114 | K10: -988 | L10: -968
B11: UK bank levy | C11: 0 | E11: -41 | F11: 0 | G11: 0 | H11: 0 | J11: -46.3 | K11: 0 | L11: 0
B12: Operating expenses | C12: -1023 | E12: -1064 | F12: -952 | G12: -1022 | H12: -999 | J12: -1160.3 | K12: -988 | L12: -968
B13: Litigation and conduct | C13: -4.7742343 | E13: -57.87055 | F13: -1480 | G13: -40.871671 | H13: -3.0397 | J13: -15.360694 | K13: -53.790523 | L13: -3.2250375
B14: Total operating expenses | C14: -1028 | E14: -1122 | F14: -2432 | G14: -1063 | H14: -1002 | J14: -1175 | K14: -1042 | L14: -971
B15: Other net (expenses)/income | C15: 0 | E15: - | F15: - | G15: -1 | H15: 1 | J15: -2 | K15: 1 | L15: 5
B16: Profit/(loss) before tax | C16: 195 | E16: 647 | F16: -687 | G16: 477 | H16: 585 | J16: 390 | K16: 740 | L16: 656
B17: Attributable profit/(loss) | C17: 175 | E17: 438 | F17: -907 | G17: 328 | H17: 422 | J17: 241 | K17: 510 | L17: 473
B19: Balance sheet information | C19: £bn | E19: £bn | F19: £bn | G19: £bn | H19: £bn | J19: £bn | K19: £bn | L19: £bn
B20: Loans and advances to customers at amortised cost | C20: 195700 | E20: 193700 | F20: 193200 | G20: 189100 | H20: 187500 | J20: 187600 | K20: 186700 | L20: 185300
B21: Total assets | C21: 267542 | E21: 257776 | F21: 257908 | G21: 258953 | H21: 253086 | J21: 249669 | K21: 251976 | L21: 245948
B22: Customer deposits at amortised cost | C22: 207489.79 | E22: 205477.24 | F22: 203262.55 | G22: 200921.82 | H22: 197284.41 | J22: 197279.46 | K22: 195751.7 | L22: 194305.78
B23: Loan: deposit ratio | C23: 0.96 | E23: 0.96 | F23: 0.97 | G23: 0.97 | H23: 0.96 | J23: 0.96 | K23: 0.96 | L23: 0.96
B24: Risk weighted assets | C24: 77678 | E24: 74900.809 | F24: 76792 | G24: 76150 | H24: 76558.949 | J24: 75181 | K24: 74773 | L24: 74998
B25: Period end allocated tangible equity | C25: 10645.223 | E25: 10253.792 | F25: 10382.93 | G25: 10288.714 | H25: 10466.112 | J25: 10201.511 | K25: 10063.32 | L25: 10158.49
B27: Performance measures
B28: Return on average allocated tangible equity | C28: 0.067 | E28: 0.17 | F28: -0.349 | G28: 0.127 | H28: 0.163 | J28: 0.096 | K28: 0.201 | L28: 0.188
B29: Average allocated tangible equity (£bn) | C29: 10525.027 | E29: 10280.541 | F29: 10387.153 | G29: 10305.551 | H29: 10359.544 | J29: 10094.615 | K29: 10129.036 | L29: 10086.74
B30: Cost: income ratio | C30: 0.6 | E30: 0.57 | F30: 1.32 | G30: 0.6 | H30: 0.56 | J30: 0.63 | K30: 0.55 | L30: 0.53
B31: Loan loss rate (bps) | C31: 96.138473 | E31: 37.66142 | F31: 19.973791 | G31: 46.787011 | H31: 40.249102 | J31: 61 | K31: 24 | L31: 45
B32: Net interest margin | C32: 0.0291 | E32: 0.0303 | F32: 0.031 | G32: 0.0305 | H32: 0.0318 | J32: 0.032 | K32: 0.0322 | L32: 0.0322
B34: Performance measures excluding litigation and conduct | C34: £m | E34: £m | F34: £m | G34: £m | H34: £m | J34: £m | K34: £m | L34: £m
B35: Profit before tax | C35: 199.77423 | E35: 704.87055 | F35: 793 | G35: 517.87167 | H35: 588.0397 | J35: 405.36069 | K35: 793.79052 | L35: 659.22504
B36: Attributable profit | C36: 178.48519 | E36: 481.29206 | F36: 550 | G36: 357.61308 | H36: 423.7397 | J36: 253 | K36: 558 | L36: 474
B37: Return on average allocated tangible equity | C37: 0.068 | E37: 0.187 | F37: 0.212 | G37: 0.139 | H37: 0.164 | J37: 0.101 | K37: 0.22 | L37: 0.188
B38: Cost: income ratio | C38: 0.6 | E38: 0.54 | F38: 0.52 | G38: 0.58 | H38: 0.56 | J38: 0.62 | K38: 0.52 | L38: 0.53
B40: Analysis of Barclays UK | C40: Q120 | E40: Q419 | F40: Q319 | G40: Q219 | H40: Q119 | J40: Q418 | K40: Q318 | L40: Q218
B41: Analysis of total income | C41: £m | E41: £m | F41: £m | G41: £m | H41: £m | J41: £m | K41: £m | L41: £m
B42: Personal Banking | C42: 968 | E42: 1064 | F42: 1035 | G42: 946 | H42: 964 | J42: 998 | K42: 1021 | L42: 1015
B43: Barclaycard Consumer UK | C43: 436 | E43: 533 | F43: 472 | G43: 497 | H43: 490 | J43: 522 | K43: 551 | L43: 504
B44: Business Banking | C44: 300 | E44: 362 | F44: 339 | G44: 328 | H44: 323 | J44: 343 | K44: 324 | L44: 317
B45: Total income | C45: 1704 | E45: 1959 | F45: 1846 | G45: 1771 | H45: 1777 | J45: 1863 | K45: 1896 | L45: 1836
B47: Analysis of credit impairment (charges)/releases
B48: Personal Banking | C48: -134 | E48: -71 | F48: -36 | G48: -36 | H48: -52 | J48: -44 | K48: -8 | L48: -49
B49: Barclaycard Consumer UK | C49: -301 | E49: -108 | F49: -49 | G49: -175 | H49: -140 | J49: -250 | K49: -88 | L49: -139
B50: Business Banking | C50: -46 | E50: -11 | F50: -16 | G50: -19 | H50: 1 | J50: -2 | K50: -19 | L50: -26
B51: Total credit impairment charges | C51: -481 | E51: -190 | F51: -101 | G51: -230 | H51: -191 | J51: -296 | K51: -115 | L51: -214
B53: Analysis of loans and advances to customers at amortised cost | C53: £bn | E53: £bn | F53: £bn | G53: £bn | H53: £bn | J53: £bn | K53: £bn | L53: £bn
B54: Personal Banking | C54: 153400 | E54: 151900 | F54: 150100 | G54: 147300 | H54: 145900 | J54: 146000 | K54: 145400 | L54: 143600
B55: Barclaycard Consumer UK | C55: 13600 | E55: 14700 | F55: 14900 | G55: 15100 | H55: 15000 | J55: 15300 | K55: 15300 | L55: 15200
B56: Business Banking | C56: 28700 | E56: 27100 | F56: 28200 | G56: 26700 | H56: 26600 | J56: 26300 | K56: 26000 | L56: 26500
B57: Total loans and advances to customers at amortised cost | C57: 195700 | E57: 193700 | F57: 193200 | G57: 189100 | H57: 187500 | J57: 187600 | K57: 186700 | L57: 185300
B59: Analysis of customer deposits at amortised cost
B60: Personal Banking | C60: 161373.91 | E60: 159197.25 | F60: 157900 | G60: 156280.03 | H60: 154068.33 | J60: 154002.99 | K60: 153419.24 | L60: 152860.97
B61: Barclaycard Consumer UK | C61: 0 | E61: 0 | F61: 0 | G61: 0 | H61: - | J61: 0 | K61: 0 | L61: 0
B62: Business Banking | C62: 46079.939 | E62: 46344.898 | F62: 45443.399 | G62: 44602.103 | H62: 43177.068 | J62: 43337.528 | K62: 42389.85 | L62: 41400.335
B63: Total customer deposits at amortised cost | C63: 207489.79 | E63: 205477.24 | F63: 203262.55 | G63: 200921.82 | H63: 197284.41 | J63: 197279.46 | K63: 195751.7 | L63: 194305.78

Sheet Barclays International Qrtly
B2: Barclays International
C3: Q120 | E3: Q419 | F3: Q319 | G3: Q219 | H3: Q119 | J3: Q418 | K3: Q318 | L3: Q218
B4: Income statement information | C4: £m | E4: £m | F4: £m | G4: £m | H4: £m | J4: £m | K4: £m | L4: £m
B5: Net interest income | C5: 998 | E5: 965 | F5: 1059 | G5: 1017 | H5: 900 | J5: 984 | K5: 965 | L5: 853
B6: Net trading income | C6: 2360 | E6: 929 | F6: 1110 | G6: 1016 | H6: 1144 | J6: 837 | K6: 1103 | L6: 1094
B7: Net fee, commission and other income | C7: 1286 | E7: 1558 | F7: 1581 | G7: 1870 | H7: 1526 | J7: 1400 | K7: 1222 | L7: 1760
B8: Total income | C8: 4644 | E8: 3452 | F8: 3750 | G8: 3903 | H8: 3570 | J8: 3221 | K8: 3290 | L8: 3707
B9: Credit impairment charges | C9: -1609 | E9: -329 | F9: -352 | G9: -247 | H9: -245 | J9: -354 | K9: -143 | L9: -68
B10: Net operating income | C10: 3035 | E10: 3123 | F10: 3398 | G10: 3656 | H10: 3325 | J10: 2867 | K10: 3147 | L10: 3639
B11: Operating costs | C11: -2219 | E11: -2240 | F11: -2282 | G11: -2435 | H11: -2206 | J11: -2441 | K11: -2277 | L11: -2306
B12: UK bank levy | C12: 0 | E12: -174.4 | F12: 0 | G12: 0 | H12: 0 | J12: -210.3 | K12: 0 | L12: 0
B13: Operating expenses | C13: -2219 | E13: -2414.4 | F13: -2282 | G13: -2435 | H13: -2206 | J13: -2651.3 | K13: -2277 | L13: -2306
B14: Litigation and conduct | C14: 0 | E14: -86.480076 | F14: 0 | G14: -11.394014 | H14: -19.153094 | J14: -32.75178 | K14: -32.107 | L14: -46.558188
B15: Total operating expenses | C15: -2219 | E15: -2500 | F15: -2282 | G15: -2446 | H15: -2225 | J15: -2684 | K15: -2309 | L15: -2353
B16: Other net income | C16: 6 | E16: 17 | F16: 21 | G16: 13 | H16: 18 | J16: 32 | K16: 12 | L16: 11
... B18: Attributable profit/(loss) | C18: 529 | E18: 397 | F18: 799 | G18: 832 | H18: 788 | J18: -21 | K18: 687 | L18: 926
B20: Balance sheet information | C20: £bn | E20: £bn | F20: £bn | G20: £bn | H20: £bn | J20: £bn | K20: £bn | L20: £bn
B21: Loans and advances at amortised cost | C21: 167042.61 | E21: 132813.91 | F21: 138077.86 | G21: 134842.82 | H21: 130931.97 | J21: 127214.92 | K21: 132392.75 | L21: 125490.85
B22: Trading portfolio assets | C22: 101595 | E22: 113332.14 | F22: 119384 | G22: 120020 | H22: 117236 | J22: 104033 | K22: 124592 | L22: 116534
B23: Derivative financial instrument assets | C23: 341542 | E23: 228864 | F23: 286021 | G23: 243796 | H23: 217298 | J23: 222099 | K23: 214797 | L23: 228150
B24: Financial assets at fair value through the income statement | C24: 188407.75 | E24: 128383.29 | F24: 157971.07 | G24: 154747.2 | H24: 153482.6 | J24: 144719.45 | K24: 147818.08 | L24: 141202.41
B25: Cash collateral and settlement balances | C25: 153222.05 | E25: 79379.067 | F25: 112457.71 | G25: 101259.8 | H25: 97800 | J25: 74300 | K25: 94300 | L25: 91500
B26: Other assets | C26: 201500 | E26: 178600 | F26: 195600 | G26: 196800 | H26: 202300 | J26: 189800 | K26: 186300 | L26: 183600
B27: Total assets | C27: 1153201 | E27: 861358.14 | F27: 1009574 | G27: 951413 | H27: 918950 | J27: 862128 | K27: 900194 | L27: 886536
B28: Deposits at amortised cost | C28: 263251.72 | E28: 209951.38 | F28: 217610.23 | G28: 212040.66 | H28: 215505.13 | J28: 197219.43 | K28: 200338.46 | L28: 191022.44
B29: Derivative financial instrument liabilities | C29: 338776 | E29: 228897 | F29: 283267 | G29: 242977 | H29: 213489 | J29: 219577 | K29: 213695 | L29: 224909
B30: Loan: deposit ratio | C30: 0.63 | E30: 0.63 | F30: 0.63 | G30: 0.64 | H30: 0.61 | J30: 0.65 | K30: 0.66 | L30: 0.66
B31: Risk weighted assets | C31: 237908 | E31: 209243.3 | F31: 223051 | G31: 214772 | H31: 216070.94 | J31: 210741 | K31: 214595 | L31: 218015
B32: Period end allocated tangible equity | C32: 34241.552 | E32: 29622.522 | F32: 31409.821 | G32: 30214.464 | H32: 30620.903 | J32: 29887.857 | K32: 30229.836 | L32: 30507.802
B34: Performance measures
B35: Return on average allocated tangible equity | C35: 0.065 | E35: 0.051 | F35: 0.099 | G35: 0.107 | H35: 0.104 | J35: -0.003 | K35: 0.088 | L35: 0.118
B36: Average allocated tangible equity (£bn) | C36: 32332.084 | E36: 30900.698 | F36: 32151.102 | G36: 31115.198 | H36: 30452.119 | J36: 31289.781 | K36: 31129.213 | L36: 31403.451
B37: Cost: income ratio | C37: 0.48 | E37: 0.72 | F37: 0.61 | G37: 0.63 | H37: 0.62 | J37: 0.83 | K37: 0.7 | L37: 0.63
B38: Loan loss rate (bps) | C38: 376.93221 | E38: 95.627064 | F38: 98.716135 | G38: 72.03538 | H38: 73 | J38: 107 | K38: 41 | L38: 22
B39: Net interest margin | C39: 0.0393 | E39: 0.0429 | F39: 0.041 | G39: 0.0391 | H39: 0.0399 | J39: 0.0398 | K39: 0.0387 | L39: 0.0403
B41: Performance measures excluding litigation and conduct | C41: £m | E41: £m | F41: £m | G41: £m | H41: £m | J41: £m | K41: £m | L41: £m
B42: Profit before tax | C42: 821.98531 | E42: 726.48008 | F42: 1137 | G42: 1234.394 | H42: 1137.1531 | J42: 247.75178 | K42: 882.107 | L42: 1343.5582
B43: Attributable profit | C43: 528.99106 | E43: 460.87986 | F43: 800.78627 | G43: 839.51807 | H43: 803.85309 | J43: 13 | K43: 713 | L43: 960
B44: Return on average allocated tangible equity | C44: 0.065 | E44: 0.06 | F44: 0.1 | G44: 0.108 | H44: 0.106 | J44: 0.002 | K44: 0.092 | L44: 0.122
B45: Cost: income ratio | C45: 0.48 | E45: 0.7 | F45: 0.61 | G45: 0.62 | H45: 0.62 | J45: 0.82 | K45: 0.69 | L45: 0.62
B49: Analysis of Barclays International
B51: Corporate and Investment Bank | C51: Q120 | E51: Q419 | F51: Q319 | G51: Q219 | H51: Q119 | J51: Q418 | K51: Q318 | L51: Q218
B52: Income statement information | C52: £m | E52: £m | F52: £m | G52: £m | H52: £m | J52: £m | K52: £m | L52: £m
B53: FICC | C53: 1858 | E53: 726 | F53: 816 | G53: 920 | H53: 902 | J53: 570 | K53: 688 | L53: 736
B54: Equities | C54: 564 | E54: 409 | F54: 494 | G54: 517 | H54: 467 | J54: 375 | K54: 471 | L54: 601
B55: Markets | C55: 2422 | E55: 1135 | F55: 1310 | G55: 1437 | H55: 1369 | J55: 945 | K55: 1159 | L55: 1337
B56: Advisory | C56: 155 | E56: 202 | F56: 221 | G56: 221 | H56: 132 | J56: 242 | K56: 151 | L56: 168
B57: Equity capital markets | C57: 62 | E57: 56 | F57: 86 | G57: 104 | H57: 83 | J57: 53 | K57: 55 | L57: 90
B58: Debt capital markets | C58: 418 | E58: 322 | F58: 381 | G58: 373 | H58: 354 | J58: 330 | K58: 313 | L58: 446
B59: Banking fees | C59: 635 | E59: 580 | F59: 688 | G59: 698 | H59: 569 | J59: 625 | K59: 519 | L59: 704
B60: Corporate lending | C60: 111 | E60: 202 | F60: 195 | G60: 216 | H60: 152 | J60: 243 | K60: 197 | L60: 198
B61: Transaction banking | C61: 449 | E61: 397 | F61: 424 | G61: 444 | H61: 415 | J61: 412 | K61: 416 | L61: 385
B62: Corporate | C62: 560 | E62: 599 | F62: 619 | G62: 660 | H62: 567 | J62: 655 | K62: 613 | L62: 583
B63: Other | C63: 0 | E63: 0 | F63: 0 | G63: 0 | H63: 0 | J63: -74 | K63: -56 | L63: -44
B64: Total income | C64: 3617 | E64: 2314 | F64: 2617 | G64: 2795 | H64: 2505 | J64: 2151 | K64: 2235 | L64: 2580
... B69: Operating expenses | C69: -1689.6249 | E69: -1847.0386 | F69: -1712 | G69: -1860.1093 | H69: -1619.3383 | J69: -2023 | K69: -1711.7208 | L69: -1772.6741
B70: Litigation and conduct | C70: 0 | E70: -78.961358 | F70: -4 | G70: -6.8906693 | H70: -18.66172 | J70: -23.239048 | K70: -32.279216 | L70: -
B71: Total operating expenses | C71: -1690 | E71: -1926 | F71: -1716 | G71: -1867 | H71: -1638 | J71: -2046 | K71: -1744 | L71: -1773
B72: Other net income | C72: 0 | E72: 1 | F72: 12 | G72: 3 | H72: 12 | J72: 15 | K72: 4 | L72: 5
B73: Profit before tax | C73: 1203 | E73: 359 | F73: 882 | G73: 887 | H73: 827 | J73: 85 | K73: 498 | L73: 835
B74: Attributable profit/(loss) | C74: 820 | E74: 193 | F74: 609 | G74: 596 | H74: 582 | J74: -84 | K74: 431 | L74: 600
B76: Balance sheet information | C76: £bn | E76: £bn | F76: £bn | G76: £bn | H76: £bn | J76: £bn | K76: £bn | L76: £bn
B77: Loans and advances at amortised cost | C77: 128173.98 | E77: 92042.316 | F77: 95826.177 | G77: 92132.642 | H77: 90629.573 | J77: 86369.046 | K77: 93252.294 | L77: 87800
B78: Trading portfolio assets | C78: 101487 | E78: 113256.14 | F78: 119305 | G78: 119948 | H78: 117200 | J78: 104000 | K78: 124500 | L78: 116500
B79: Derivative financial instruments assets | C79: 341439 | E79: 228826 | F79: 285967 | G79: 243742 | H79: 217300 | J79: 222100 | K79: 214800 | L79: 228100
B80: Financial assets at fair value through the income statement | C80: 187772.96 | E80: 127676.91 | F80: 157278.82 | G80: 154071.38 | H80: 152900 | J80: 144200 | K80: 147300 | L80: 140700
B81: Cash collateral and settlement balances | C81: 152246.81 | E81: 78508.939 | F81: 111587.63 | G81: 100359.14 | H81: 96900 | J81: 73400 | K81: 93300 | L81: 90600
B82: Other assets | C82: 171400 | E82: 155300 | F82: 171512.37 | G82: 168100 | H82: 163200 | J82: 160400 | K82: 153800 | L82: 151600
B83: Total assets | C83: 1082486 | E83: 795607.14 | F83: 941477 | G83: 878294 | H83: 838100 | J83: 790500 | K83: 827000 | L83: 815300
B84: Deposits at amortised cost | C84: 198413.72 | E84: 146227.04 | F84: 152107.61 | G84: 145382.95 | H84: 151408.63 | J84: 136278.73 | K84: 137647.34 | L84: 130300
B85: Derivative financial instrument liabilities | C85: 338703 | E85: 228867 | F85: 283232 | G85: 242946 | H85: 213500 | J85: 219600 | K85: 213700 | L85: 224900
B86: Risk weighted assets | C86: 201747 | E86: 171452.99 | F86: 184900 | G86: 175907 | H86: 176589.56 | J86: 170902 | K86: 175924 | L86: 180438
B88: Performance measures
B89: Return on average allocated tangible equity | C89: 0.121 | E89: 0.03 | F89: 0.091 | G89: 0.092 | H89: 0.093 | J89: -0.013 | K89: 0.066 | L89: 0.091
B90: Average allocated tangible equity (£bn) | C90: 27184.287 | E90: 25827.794 | F90: 26900 | G90: 25823.57 | H90: 25087.923 | J90: 25986.736 | K90: 25871.782 | L90: 26430.187
B91: Cost: income ratio | C91: 0.47 | E91: 0.83 | F91: 0.66 | G91: 0.67 | H91: 0.65 | J91: 0.95 | K91: 0.78 | L91: 0.69
B93: Performance measures excluding litigation and conduct | C93: £m | E93: £m | F93: £m | G93: £m | H93: £m | J93: £m | K93: £m | L93: £m
B94: Profit before tax | C94: 1203.3751 | E94: 437.96136 | F94: 886 | G94: 893.89067 | H94: 845.66172 | J94: 108.23905 | K94: 530.27922 | L94: 835.32588
B95: Attributable profit/(loss) | C95: 820.29459 | E95: 251.41124 | F95: 613.65 | G95: 601.0933 | H95: 598 | J95: -57 | K95: 456 | L95: 600
B96: Return on average allocated tangible equity | C96: 0.121 | E96: 0.039 | F96: 0.092 | G96: 0.093 | H96: 0.095 | J96: -0.009 | K96: 0.07 | L96: 0.091
B97: Cost: income ratio | C97: 0.47 | E97: 0.8 | F97: 0.65 | G97: 0.67 | H97: 0.65 | J97: 0.94 | K97: 0.77 | L97: 0.69
B99: Analysis of Barclays International
B101: Consumer, Cards and Payments | C101: Q120 | E101: Q419 | F101: Q319 | G101: Q219 | H101: Q119 | J101: Q418 | K101: Q318 | L101: Q218
B102: Income statement information | C102: £m | E102: £m | F102: £m | G102: £m | H102: £m | J102: £m | K102: £m | L102: £m
B103: Net interest income | C103: 663 | E103: 717 | F103: 720 | G103: 720 | H103: 665 | J103: 664 | K103: 691 | L103: 699
B104: Net fee, commission, trading and other income | C104: 364 | E104: 421 | F104: 413 | G104: 388 | H104: 400 | J104: 406 | K104: 364 | L104: 428
B105: Total income | C105: 1027 | E105: 1138 | F105: 1133 | G105: 1108 | H105: 1065 | J105: 1070 | K105: 1055 | L105: 1127
B106: Credit impairment charges | C106: -885 | E106: -299 | F106: -321 | G106: -203 | H106: -193 | J106: -319 | K106: -146 | L106: -91
B107: Net operating income | C107: 142 | E107: 839 | F107: 812 | G107: 905 | H107: 872 | J107: 751 | K107: 909 | L107: 1036
B108: Operating costs | C108: -529 | E108: -549 | F108: -570 | G108: -575 | H108: -586.50863 | J108: -606 | K108: -565.17222 | L108: -532.7677
B109: UK bank levy | C109: 0 | E109: -18.4 | F109: 0 | G109: 0 | H109: 0 | J109: -22 | K109: 0 | L109: 0
B110: Operating expenses | C110: -529 | E110: -567.4 | F110: -570 | G110: -575 | H110: -586.50863 | J110: -628 | K110: -565.17222 | L110: -532.7677
B111: Litigation and conduct | C111: 0 | E111: -6.5187184 | F111: 4.1046522 | G111: -3.5033445 | H111: 0 | J111: -9.5127318 | K111: 0 | L111: -47.232305
B112: Total operating expenses | C112: -529 | E112: -574 | F112: -566 | G112: -579 | H112: -587 | J112: -638 | K112: -565 | L112: -580
B113: Other net income | C113: 6 | E113: 16 | F113: 9 | G113: 10 | H113: 6 | J113: 17 | K113: 8 | L113: 6
B114: (Loss)/profit before tax | C114: -381 | E114: 281 | F114: 255 | G114: 336 | H114: 291 | J114: 130 | K114: 352 | L114: 462
B115: Attributable (loss)/profit | C115: -291 | E115: 204 | F115: 190 | G115: 236 | H115: 206 | J115: 63 | K115: 256 | L115: 326
B117: Balance sheet information | C117: £bn | E117: £bn | F117: £bn | G117: £bn | H117: £bn | J117: £bn | K117: £bn | L117: £bn
B118: Loans and advances at amortised cost | C118: 38768.634 | E118: 40771.597 | F118: 42251.681 | G118: 42710.176 | H118: 40302.399 | J118: 40845.872 | K118: 39140.451 | L118: 37663.575
B119: Total assets | C119: 70715 | E119: 65751 | F119: 68097 | G119: 73119 | H119: 80900 | J119: 71600 | K119: 73200 | L119: 71200
...

Sheet Head Office Qrtly
B2: Head Office
C3: Q120 | E3: Q419 | F3: Q319 | G3: Q219 | H3: Q119 | J3: Q418 | K3: Q318 | L3: Q218
B4: Income statement information | C4: £m | E4: £m | F4: £m | G4: £m | H4: £m | J4: £m | K4: £m | L4: £m
B5: Net interest income | C5: -79 | E5: -99 | F5: -117 | G5: -95 | H5: -111 | J5: -201 | K5: -106 | L5: -156
B6: Net fee, commission and other income | C6: 14 | E6: -11 | F6: 62 | G6: -41 | H6: 16 | J6: 190 | K6: 49 | L6: 189
B7: Total income | C7: -65 | E7: -110 | F7: -55 | G7: -136 | H7: -95 | J7: -11 | K7: -57 | L7: 33
B8: Credit impairment (charges)/releases | C8: -25 | E8: -4 | F8: -8 | G8: -3 | H8: -12 | J8: 7 | K8: 4 | L8: -1
B9: Net operating (expenses)/income | C9: -90 | E9: -114 | F9: -63 | G9: -139 | H9: -107 | J9: -4 | K9: -53 | L9: 32
B10: Operating costs | C10: -11 | E10: -45 | F10: -59 | G10: -44 | H10: -52 | J10: -68.582863 | K10: -64 | L10: -36
B11: UK bank levy | C11: 0 | E11: -11 | F11: 0 | G11: 0 | H11: 0 | J11: -13.4 | K11: 0 | L11: 0
B12: Operating expenses | C12: -11 | E12: -56 | F12: -59 | G12: -44 | H12: -52 | J12: -81.982863 | K12: -64 | L12: -36
B13: GMP charge | C13: 0 | E13: 0 | F13: 0 | G13: 0 | H13: 0 | J13: -140 | K13: 0 | L13: 0
B14: Litigation and conduct | C14: -4.5813061 | E14: -22.891631 | F14: -88 | G14: -1.4443004 | H14: -38.649388 | J14: -12.017137 | K14: -18.953604 | L14: -31
B15: Total operating expenses | C15: -16 | E15: -79 | F15: -147 | G15: -45 | H15: -91 | J15: -234 | K15: -83 | L15: -67
B16: Other net income/(expenses) | C16: 2 | E16: 3 | F16: 6 | G16: 15 | H16: -22 | J16: 7 | K16: 7 | L16: -23
... B18: Attributable loss | C18: -99 | E18: -154 | F18: -184 | G18: -126 | H18: -172 | J18: -234 | K18: -147 | L18: -120
B20: Balance sheet information | C20: £bn | E20: £bn | F20: £bn | G20: £bn | H20: £bn | J20: £bn | K20: £bn | L20: £bn
B21: Total assets | C21: 23554 | E21: 21040 | F21: 22870 | G21: 22357 | H21: 21407 | J21: 21486 | K21: 18606 | L21: 17200
B22: Risk weighted assets | C22: 10045 | E22: 10986.984 | F22: 13418 | G22: 28085 | H22: 27040.696 | J22: 26003 | K22: 26799 | L22: 26300
B23: Period end allocated tangible equity | C23: 4402.4454 | E23: 5562.7824 | F23: 5476.6655 | G23: 6956.1699 | H23: 4533.7656 | J23: 4861.4646 | K23: 4155.8455 | L23: 3600
B25: Performance measures
B26: Average allocated tangible equity (£bn) | C26: 4237.5154 | E26: 5190.4097 | F26: 5812.9454 | G26: 4786.9068 | H26: 4335.0813 | J26: 2906.1443 | K26: 3387.3684 | L26: 2000
B28: Performance measures excluding litigation and conduct | C28: £m | E28: £m | F28: £m | G28: £m | H28: £m | J28: £m | K28: £m | L28: £m
B29: Loss before tax | C29: -99.418694 | E29: -167.10837 | F29: -116 | G29: -167.5557 | H29: -181.35061 | J29: -218.98286 | K29: -110.0464 | L29: -27
B30: Attributable loss | C30: -103.07531 | E30: -138.91754 | F30: -118 | G30: -123.69369 | H30: -143.85061 | J30: -218 | K30: -136 | L30: -96

Sheet Segmental Reporting Note
A2: Analysis of results by business
B3: Barclays_x000D_ UK | C3: Barclays_x000D_ International | D3: Head_x000D_ Office | E3: Barclays_x000D_ Group | G3: Cast to business pages | N3: Cast down
A4: Half year ended 30.06.19 | B4: £m | C4: £m | D4: £m | E4: £m | G4: BUK | H4: BI | I4: HO | J4: Group | L4: Cast to Group | N4: BUK | O4: BI | P4: HO | Q4: Group | R4: casting checks please
A5: Total income | B5: 3548 | C5: 7473 | D5: -231 | E5: 10790 | G5: =(B5-'Barclays UK YTD'!C7) -> -3805 | H5: =(C5-'Barclays International YTD'!C8) -> -7202 | I5: =(D5-'Head Office YTD'!C7) -> 165 | J5: =E5-'Group PH'!C4 -> 4507 | L5: =(ROUND(E5,0)-ROUND(D5,0)-ROUND(C5,0)-ROUND(B5,0)) -> 0
A6: Credit impairment charges and other provisions | B6: -421 | C6: -492 | D6: -15 | E6: -928 | G6: =(B6-'Barclays UK YTD'!C8) -> 291 | H6: =(C6-'Barclays International YTD'!C9) -> 681 | I6: =(D6-'Head Office YTD'!C8) -> 12 | J6: =E6-'Group PH'!C5 -> 1187 | L6: =(ROUND(E6,0)-ROUND(D6,0)-ROUND(C6,0)-ROUND(B6,0)) -> 0
A7: Net operating income/(expenses) | B7: 3127 | C7: 6981 | D7: -246 | E7: 9862 | G7: =(B7-'Barclays UK YTD'!C9) -> -3514 | H7: =(C7-'Barclays International YTD'!C10) -> -6521 | I7: =(ROUND(D7,0)-ROUND('Head Office YTD'!C9,0)) -> 177 | J7: =E7-'Group PH'!C6 -> 5694 | L7: =(ROUND(E7,0)-ROUND(D7,0)-ROUND(C7,0)-ROUND(B7,0)) -> 0
A8: Total operating expenses | B8: -2065 | C8: -4671 | D8: -136 | E8: -6872 | G8: =(B8-'Barclays UK YTD'!C14) -> 3554 | H8: =(C8-'Barclays International YTD'!C15) -> 4782 | I8: =(D8-'Head Office YTD'!C15) -> 226 | J8: =(E8-'Group PH'!C9) -> -3609 | L8: =(ROUND(E8,0)-ROUND(D8,0)-ROUND(C8,0)-ROUND(B8,0)) -> 0
A9: Other net income/(expenses)1 | B9: - | C9: 31 | D9: -7 | E9: 24 | G9: =(B9-'Barclays UK YTD'!C15) -> #VALUE! | H9: =(C9-'Barclays International YTD'!C16) -> -38 | I9: =(D9-'Head Office YTD'!C16) -> -9 | J9: =(E9-'Group PH'!C10) -> 16 | L9: =(ROUND(E9,0)-ROUND(D9,0)-ROUND(C9,0)-ROUND(B9,0)) -> #VALUE!
A10: Profit/(loss) before tax | B10: 1062 | C10: 2341 | D10: -389 | E10: 3014 | G10: =(B10-'Barclays UK YTD'!C16) -> 40 | H10: =(C10-'Barclays International YTD'!C17) -> -1777 | I10: =(ROUND(D10,0)-ROUND('Head Office YTD'!C17,0)) -> 394 | J10: =(ROUND(E10,0)-ROUND('Group PH'!C11,0)) -> 2101 | L10: =(ROUND(E10,0)-ROUND(D10,0)-ROUND(C10,0)-ROUND(B10,0)) -> 0
G11: Assets
B12: £bn | C12: £bn | D12: £bn | E12: £bn | G12: Cast to YTD
A13: Total assets | B13: 258953 | C13: 951413 | D13: 22357 | E13: 1232823 | G13: =ROUND(B13,-2)-ROUND('Barclays UK YTD'!C21,-2) -> 1200 | H13: =ROUND('Barclays International YTD'!C27,-2)-ROUND(C13,-2) -> -90000 | I13: =ROUND('Head Office YTD'!C21,-2)-ROUND(D13,-2) -> -1400 | J13: =ROUND('Group Qrtly'!C38,-2)-ROUND(E13,-2) -> 211500 | L13: =ROUND(B13,-2)+ROUND(C13,-2)+ROUND(D13,-2)-ROUND(E13,-2) -> 0
G14: Cast to Quarterly
G15: =ROUND('Barclays UK Qrtly'!C21,-2)-ROUND(B13,-2) -> 8500 | H15: =ROUND('Barclays International Qrtly'!C27,-2)-ROUND(C13,-2) -> 201800 | I15: =ROUND('Head Office Qrtly'!C21,-2)-ROUND(D13,-2) -> 1200 | J15: =ROUND('Group Qrtly'!C38,-2)-ROUND(E13,-2) -> 211500
K16: `
B17: Barclays_x000D_ UK | C17: Barclays_x000D_ International | D17: Head_x000D_ Office | E17: Barclays_x000D_ Group
A18: Half year ended 30.06.18 | B18: £m | C18: £m | D18: £m | E18: £m | G18: BUK | H18: BI | I18: HO | J18: Group | L18: Cast to Group
A19: Total income | B19: 3624 | C19: 7515 | D19: -205 | E19: 10934 | G19: =(ROUND(B19,0)-ROUND('Barclays UK YTD'!D7,0)) -> -3759 | H19: =(ROUND(C19,0)-ROUND('Barclays International YTD'!D8,0)) -> -6511 | I19: =(ROUND(D19,0)-ROUND('Head Office YTD'!D7,0)) -> 68 | J19: =(ROUND(E19,0)-ROUND('Group PH'!D4,0)) -> 5682 | L19: =(ROUND(E19,0)-ROUND(D19,0)-ROUND(C19,0)-ROUND(B19,0)) -> 0
A20: Credit impairment (charges)/releases and other provisions | B20: -415 | C20: -161 | D20: 5 | E20: -571 | G20: =(ROUND(B20,0)-ROUND('Barclays UK YTD'!D8,0)) -> 411 | H20: =(C20-'Barclays International YTD'!D9) -> 497 | I20: =(ROUND(D20,0)-ROUND('Head Office YTD'!D8,0)) -> -11 | J20: =(ROUND(E20,0)-ROUND('Group PH'!D5,0)) -> -123 | L20: =(ROUND(E20,0)-ROUND(D20,0)-ROUND(C20,0)-ROUND(B20,0)) -> 0
A21: Net operating income/(expenses) | B21: 3209 | C21: 7354 | D21: -200 | E21: 10363 | G21: =(ROUND(B21,0)-ROUND('Barclays UK YTD'!D9,0)) -> -3348 | H21: =(C21-'Barclays International YTD'!D10) -> -6014 | I21: =(ROUND(D21,0)-ROUND('Head Office YTD'!D9,0)) -> 57 | J21: =(ROUND(E21,0)-ROUND('Group PH'!D6,0)) -> 5559 | L21: =(ROUND(E21,0)-ROUND(D21,0)-ROUND(C21,0)-ROUND(B21,0)) -> 0
A22: Total operating expenses | B22: -2387 | C22: -4668 | D22: -1661 | E22: -8716 | G22: =(ROUND(B22,0)-ROUND('Barclays UK YTD'!D14,0)) -> 2217 | H22: =(C22-'Barclays International YTD'!D15) -> 4993 | I22: =(ROUND(D22,0)-ROUND('Head Office YTD'!D15,0)) -> 317 | J22: =(E22-'Group PH'!D9) -> -5398 | L22: =(ROUND(E22,0)-ROUND(D22,0)-ROUND(C22,0)-ROUND(B22,0)) -> 0
A23: Other net income/(expenses)1 | B23: 4 | C23: 24 | D23: -16 | E23: 12 | G23: =(B23-'Barclays UK YTD'!D15) -> 1 | H23: =(C23-'Barclays International YTD'!D16) -> -44 | I23: =(ROUND(D23,0)-ROUND('Head Office YTD'!D16,0)) -> -14 | J23: =(E23-'Group PH'!D10) -> 15 | L23: =(ROUND(E23,0)-ROUND(D23,0)-ROUND(C23,0)-ROUND(B23,0)) -> 0
A24: Profit/(loss) before tax | B24: 826 | C24: 2710 | D24: -1877 | E24: 1659 | G24: =(ROUND(B24,0)-ROUND('Barclays UK YTD'!D16,0)) -> -1130 | H24: =(ROUND(C24,0)-ROUND('Barclays International YTD'!D17,0)) -> -1065 | I24: =(ROUND(D24,0)-ROUND('Head Office YTD'!D17,0)) -> 360 | J24: =(ROUND(E24,0)-ROUND('Group PH'!D11,0)) -> 176 | L24: =(ROUND(E24,0)-ROUND(D24,0)-ROUND(C24,0)-ROUND(B24,0)) -> 0
G25: Assets
A26: As at 31.12.18 | B26: £bn | C26: £bn | D26: £bn | E26: £bn | G26: Cast to YTD
A27: Total assets | B27: 249700 | C27: 862100 | D27: 21500 | E27: 1133300 | G27: =ROUND(('Barclays UK YTD'!D21),-2)-ROUND(B27,-2) -> 0 | H27: =ROUND('Barclays International YTD'!D27,-2)-ROUND(C27,-2) -> 0 | I27: =ROUND('Head Office YTD'!D21,-2)-ROUND(D27,-2) -> 0 | J27: =ROUND('Group Qrtly'!F38,-2)-ROUND(E27,-2) -> 157100 | L27: =SUM(B27:D27)-E27 -> 0
G28: Cast to Quarterly
G29: =ROUND('Barclays UK Qrtly'!F21,-2)-ROUND(B27,-2) -> 8200 | H29: =ROUND('Barclays International Qrtly'!F27,-2)-ROUND(C27,-2) -> 147500 | I29: =ROUND('Head Office Qrtly'!F21,-2)-ROUND(D27,-2) -> 1400 | J29: =ROUND('Group Qrtly'!F38,-2)-ROUND(E27,-2) -> 157100

Sheet Margins and balances
B2: Margins and balances
C3: Three months ended 31.03.20 | F3: Three months ended 31.03.19
C4: Net interest income | D4: Average customer assets | E4: Net interest margin | F4: Net interest income | G4: Average customer assets | H4: Net interest margin
C5: £m | D5: £m | E5: % | F5: £m | G5: £m | H5: %
B6: Barclays UK | C6: 1412 | D6: 195204 | E6: 2.91 | F6: 1469 | G6: 187570 | H6: 3.18
B7: Barclays International | C7: 980 | D7: 100171 | E7: 3.93 | F7: 967 | G7: 98313 | H7: 3.99
B8: Total Barclays UK and Barclays International | C8: 2392 | D8: 295375 | E8: 3.26 | F8: 2436 | G8: 285883 | H8: 3.46
B9: Other | C9: -61 | F9: -178
B10: Total Barclays Group | C10: 2331 | F10: 2258
B13: Quarterly analysis for Barclays UK and Barclays International
F14: Net interest income | G14: Average customer assets | H14: Net interest margin
B15: Three months ended 31.12.19 | F15: £m | G15: £m | H15: %
B16: Barclays UK | F16: 1478 | G16: 193610 | H16: 3.03
B17: Barclays International | F17: 1036 | G17: 95819 | H17: 4.29
B18: Total Barclays UK and Barclays International | F18: 2514 | G18: 289429 | H18: 3.45
B20: Three months ended 30.09.19
B21: Barclays UK | F21: 1503 | G21: 192262 | H21: 3.1
B22: Barclays International | F22: 1038 | G22: 100589 | H22: 4.1
B23: Total Barclays UK and Barclays International | F23: 2541 | G23: 292851 | H23: 3.44
B25: Three months ended 30.06.19
B26: Barclays UK | F26: 1438 | G26: 189172 | H26: 3.05
B27: Barclays International | F27: 980 | G27: 100645 | H27: 3.91
B28: Total Barclays UK and Barclays International | F28: 2418 | G28: 289817 | H28: 3.35

Sheet L&A by stage
B2: Loans and advances at amortised cost by stage
C3: Gross exposure | H3: Impairment allowance | L3: Net exposure
C4: Stage 1 | D4: Stage 2 | E4: Stage 3 | F4: Total | H4: Stage 1 | I4: Stage 2 | J4: Stage 3 | K4: Total
B5: As at 31.03.20 | C5: £m | D5: £m | E5: £m | F5: £m | H5: £m | I5: £m | J5: £m | K5: £m | L5: £m
B6: Barclays UK | C6: 143325 | D6: 23727 | E6: 2479 | F6: 169531 | H6: 237 | I6: 1455 | J6: 1031 | K6: 2723 | L6: 166808
B7: Barclays International | C7: 25006 | D7: 4903 | E7: 1834 | F7: 31743 | H7: 431 | I7: 1280 | J7: 1460 | K7: 3171 | L7: 28572
B8: Head Office | C8: 4836 | D8: 514 | E8: 845 | F8: 6195 | H8: 5 | I8: 52 | J8: 321 | K8: 378 | L8: 5817
B9: Total Barclays Group retail | C9: 173167 | D9: 29144 | E9: 5158 | F9: 207469 | H9: 673 | I9: 2787 | J9: 2812 | K9: 6272 | L9: 201197
B10: Barclays UK | C10: 28413 | D10: 2223 | E10: 1061 | F10: 31697 | H10: 21 | I10: 58 | J10: 118 | K10: 197 | L10: 31500
B11: Barclays International | C11: 127536 | D11: 10276 | E11: 2090 | F11: 139902 | H11: 152 | I11: 497 | J11: 784 | K11: 1433 | L11: 138469
B12: Head Office | C12: 2982 | D12: - | E12: 38 | F12: 3020 | H12: - | I12: - | J12: 37 | K12: 37 | L12: 2983
B13: Total Barclays Group wholesale | C13: 158931 | D13: 12499 | E13: 3189 | F13: 174619 | H13: 173 | I13: 555 | J13: 939 | K13: 1667 | L13: 172952
B14: Total loans and advances at amortised cost | C14: 332098 | D14: 41643 | E14: 8347 | F14: 382088 | H14: 846 | I14: 3342 | J14: 3751 | K14: 7939 | L14: 374149
B15: Off-balance sheet loan commitments and financial guarantee contracts | C15: 311218 | D15: 19335 | E15: 1056 | F15: 331609 | H15: 104 | I15: 234 | J15: 47 | K15: 385 | L15: 331224
B16: Total | C16: 643316 | D16: 60978 | E16: 9403 | F16: 713697 | H16: 950 | I16: 3576 | J16: 3798 | K16: 8324 | L16: 705373
C18: As at 31.03.20 | H18: Three months ended 31.03.20
C19: Coverage ratio | H19: Loan impairment charge and loan loss rate
C20: Stage 1 | D20: Stage 2 | E20: Stage 3 | F20: Total | H20: Loan impairment charge | J20: Loan loss rate
C21: % | D21: % | E21: % | F21: % | H21: £m | J21: bps
B22: Barclays UK | C22: 0.2 | D22: 6.1 | E22: 41.6 | F22: 1.6 | I22: 419 | K22: 99
B23: Barclays International | C23: 1.7 | D23: 26.1 | E23: 79.6 | F23: 10 | I23: 892 | K23: 1130
B24: Head Office | C24: 0.1 | D24: 10.1 | E24: 38 | F24: 6.1 | I24: 25 | K24: 162
B25: Total Barclays Group retail | C25: 0.4 | D25: 9.6 | E25: 54.5 | F25: 3 | I25: 1336 | K25: 259
B26: Barclays UK | C26: 0.1 | D26: 2.6 | E26: 11.1 | F26: 0.6 | I26: 44 | K26: 56
B27: Barclays International | C27: 0.1 | D27: 4.8 | E27: 37.5 | F27: 1 | I27: 574 | K27: 165
B28: Head Office | C28: - | D28: - | E28: 97.4 | F28: 1.2 | I28: - | K28: -
B29: Total Barclays Group wholesale | C29: 0.1 | D29: 4.4 | E29: 29.4 | F29: 1 | I29: 618 | K29: 142
B30: Total loans and advances at amortised cost | C30: 0.3 | D30: 8 | E30: 44.9 | F30: 2.1 | I30: 1954 | K30: 206
B31: Off-balance sheet loan commitments and financial guarantee contracts | C31: - | D31: 1.2 | E31: 4.5 | F31: 0.1 | I31: 58
B32: Other financial assets subject to impairment | I32: 103
B33: Total | C33: 0.1 | D33: 5.9 | E33: 40.4 | F33: 1.2 | I33: 2115
C36: Gross exposure | H36: Impairment allowance | L36: Net exposure
C37: Stage 1 | D37: Stage 2 | E37: Stage 3 | F37: Total | H37: Stage 1 | I37: Stage 2 | J37: Stage 3 | K37: Total
B38: As at 31.12.19 | C38: £m | D38: £m | E38: £m | F38: £m | H38: £m | I38: £m | J38: £m | K38: £m | L38: £m
B39: Barclays UK | C39: 143097 | D39: 23198 | E39: 2446 | F39: 168741 | H39: 198 | I39: 1277 | J39: 974 | K39: 2449 | L39: 166292
B40: Barclays International | C40: 27886 | D40: 4026 | E40: 1875 | F40: 33787 | H40: 352 | I40: 774 | J40: 1359 | K40: 2485 | L40: 31302
B41: Head Office | C41: 4803 | D41: 500 | E41: 826 | F41: 6129 | H41: 5 | I41: 36 | J41: 305 | K41: 346 | L41: 5783
B42: Total Barclays Group retail | C42: 175786 | D42: 27724 | E42: 5147 | F42: 208657 | H42: 555 | I42: 2087 | J42: 2638 | K42: 5280 | L42: 203377
B43: Barclays UK | C43: 27891 | D43: 2397 | E43: 1124 | F43: 31412 | H43: 16 | I43: 38 | J43: 108 | K43: 162 | L43: 31250
B44: Barclays International | C44: 92615 | D44: 8113 | E44: 1615 | F44: 102343 | H44: 136 | I44: 248 | J44: 447 | K44: 831 | L44: 101512
B45: Head Office | C45: 2974 | D45: - | E45: 37 | F45: 3011 | H45: - | I45: - | J45: 35 | K45: 35 | L45: 2976
B46: Total Barclays Group wholesale | C46: 123480 | D46: 10510 | E46: 2776 | F46: 136766 | H46: 152 | I46: 286 | J46: 590 | K46: 1028 | L46: 135738
B47: Total loans and advances at amortised cost | C47: 299266 | D47: 38234 | E47: 7923 | F47: 345423 | H47: 707 | I47: 2373 | J47: 3228 | K47: 6308 | L47: 339115
B48: Off-balance sheet loan commitments and financial guarantee contracts | C48: 321140 | D48: 19185 | E48: 935 | F48: 341260 | H48: 97 | I48: 170 | J48: 55 | K48: 322 | L48: 340938
B49: Total | C49: 620406 | D49: 57419 | E49: 8858 | F49: 686683 | H49: 804 | I49: 2543 | J49: 3283 | K49: 6630 | L49: 680053
C51: As at 31.12.19 | H51: Year ended 31.12.19
C52: Coverage ratio | H52: Loan impairment charge and loan loss rate
C53: Stage 1 | D53: Stage 2 | E53: Stage 3 | F53: Total | H53: Loan impairment charge | J53: Loan loss rate
C54: % | D54: % | E54: % | F54: % | H54: £m | K54: bps
B55: Barclays UK | C55: 0.1 | D55: 5.5 | E55: 39.8 | F55: 1.5 | I55: 661 | K55: 39
B56: Barclays International | C56: 1.3 | D56: 19.2 | E56: 72.5 | F56: 7.4 | I56: 999 | K56: 296
B57: Head Office | C57: 0.1 | D57: 7.2 | E57: 36.9 | F57: 5.6 | I57: 27 | K57: 44
B58: Total Barclays Group retail | C58: 0.3 | D58: 7.5 | E58: 51.3 | F58: 2.5 | I58: 1687 | K58: 81
B59: Barclays UK | C59: 0.1 | D59: 1.6 | E59: 9.6 | F59: 0.5 | I59: 33 | K59: 11
B60: Barclays International | C60: 0.1 | D60: 3.1 | E60: 27.7 | F60: 0.8 | I60: 113 | K60: 11
B61: Head Office | C61: - | D61: - | E61: 94.6 | F61: 1.2 | I61: - | K61: -
B62: Total Barclays Group wholesale | C62: 0.1 | D62: 2.7 | E62: 21.3 | F62: 0.8 | I62: 146 | K62: 11
B63: Total loans and advances at amortised cost | C63: 0.2 | D63: 6.2 | E63: 40.7 | F63: 1.8 | I63: 1833 | K63: 53
B64: Off-balance sheet loan commitments and financial guarantee contracts | C64: - | D64: 0.9 | E64: 5.9 | F64: 0.1 | I64: 71
B65: Other financial assets subject to impairment | I65: 8
B66: Total | C66: 0.1 | D66: 4.4 | E66: 37.1 | F66: 1 | I66: 1912

Sheet L&A by product
B2: Loans and advances at amortised cost by product
D3: Stage 2
B4: As at 31.03.20 | C4: Stage 1 | D4: Not past due | E4: <=30 days past due | F4: >30 days past due | G4: Total | H4: Stage 3 | I4: Total
B5: Gross exposure | C5: £m | D5: £m | E5: £m | F5: £m | G5: £m | H5: £m | I5: £m
B6: Home loans | C6: 137394 | D6: 14986 | E6: 1654 | F6: 732 | G6: 17372 | H6: 2155 | I6: 156921
B7: Credit cards, unsecured loans and other retail lending | C7: 41973 | D7: 10877 | E7: 489 | F7: 448 | G7: 11814 | H7: 3402 | I7: 57189
B8: Wholesale loans | C8: 152731 | D8: 11168 | E8: 588 | F8: 701 | G8: 12457 | H8: 2790 | I8: 167978
B9: Total | C9: 332098 | D9: 37031 | E9: 2731 | F9: 1881 | G9: 41643 | H9: 8347 | I9: 382088
B11: Impairment allowance
B12: Home loans | C12: 23 | D12: 50 | E12: 19 | F12: 13 | G12: 82 | H12: 358 | I12: 463
B13: Credit cards, unsecured loans and other retail lending | C13: 665 | D13: 2112 | E13: 253 | F13: 309 | G13: 2674 | H13: 2496 | I13: 5835
B14: Wholesale loans | C14: 158 | D14: 555 | E14: 15 | F14: 16 | G14: 586 | H14: 897 | I14: 1641
B15: Total | C15: 846 | D15: 2717 | E15: 287 | F15: 338 | G15: 3342 | H15: 3751 | I15: 7939
B17: Net exposure
B18: Home loans | C18: 137371 | D18: 14936 | E18: 1635 | F18: 719 | G18: 17290 | H18: 1797 | I18: 156458
B19: Credit cards, unsecured loans and other retail lending | C19: 41308 | D19: 8765 | E19: 236 | F19: 139 | G19: 9140 | H19: 906 | I19: 51354
B20: Wholesale loans | C20: 152573 | D20: 10613 | E20: 573 | F20: 685 | G20: 11871 | H20: 1893 | I20: 166337
B21: Total | C21: 331252 | D21: 34314 | E21: 2444 | F21: 1543 | G21: 38301 | H21: 4596 | I21: 374149
B23: Coverage ratio | C23: % | D23: % | E23: % | F23: % | G23: % | H23: % | I23: %
B24: Home loans | C24: - | D24: 0.3 | E24: 1.1 | F24: 1.8 | G24: 0.5 | H24: 16.6 | I24: 0.3
B25: Credit cards, unsecured loans and other retail lending | C25: 1.6 | D25: 19.4 | E25: 51.7 | F25: 69 | G25: 22.6 | H25: 73.4 | I25: 10.2
B26: Wholesale loans | C26: 0.1 | D26: 5 | E26: 2.6 | F26: 2.3 | G26: 4.7 | H26: 32.2 | I26: 1
B27: Total | C27: 0.3 | D27: 7.3 | E27: 10.5 | F27: 18 | G27: 8 | H27: 44.9 | I27: 2.1
B29: As at 31.12.19
B30: Gross exposure | C30: £m | D30: £m | E30: £m | F30: £m | G30: £m | H30: £m | I30: £m
B31: Home loans | C31: 135713 | D31: 14733 | E31: 1585 | F31: 725 | G31: 17043 | H31: 2155 | I31: 154911
B32: Credit cards, unsecured loans and other retail lending | C32: 46012 | D32: 9759 | E32: 496 | F32: 504 | G32: 10759 | H32: 3409 | I32: 60180
B33: Wholesale loans | C33: 117541 | D33: 9374 | E33: 374 | F33: 684 | G33: 10432 | H33: 2359 | I33: 130332
B34: Total | C34: 299266 | D34: 33866 | E34: 2455 | F34: 1913 | G34: 38234 | H34: 7923 | I34: 345423
B36: Impairment allowance
B37: Home loans | C37: 22 | D37: 37 | E37: 14 | F37: 13 | G37: 64 | H37: 346 | I37: 432
B38: Credit cards, unsecured loans and other retail lending | C38: 542 | D38: 1597 | E38: 159 | F38: 251 | G38: 2007 | H38: 2335 | I38: 4884
B39: Wholesale loans | C39: 143 | D39: 284 | E39: 9 | F39: 9 | G39: 302 | H39: 547 | I39: 992
B40: Total | C40: 707 | D40: 1918 | E40: 182 | F40: 273 | G40: 2373 | H40: 3228 | I40: 6308
B42: Net exposure
B43: Home loans | C43: 135691 | D43: 14696 | E43: 1571 | F43: 712 | G43: 16979 | H43: 1809 | I43: 154479
B44: Credit cards, unsecured loans and other retail lending | C44: 45470 | D44: 8162 | E44: 337 | F44: 253 | G44: 8752 | H44: 1074 | I44: 55296
B45: Wholesale loans | C45: 117398 | D45: 9090 | E45: 365 | F45: 675 | G45: 10130 | H45: 1812 | I45: 129340
B46: Total | C46: 298559 | D46: 31948 | E46: 2273 | F46: 1640 | G46: 35861 | H46: 4695 | I46: 339115
B48: Coverage ratio | C48: % | D48: % | E48: % | F48: % | G48: % | H48: % | I48: %
B49: Home loans | C49: - | D49: 0.3 | E49: 0.9 | F49: 1.8 | G49: 0.4 | H49: 16.1 | I49: 0.3
B50: Credit cards, unsecured loans and other retail lending | C50: 1.2 | D50: 16.4 | E50: 32.1 | F50: 49.8 | G50: 18.7 | H50: 68.5 | I50: 8.1
B51: Wholesale loans | C51: 0.1 | D51: 3 | E51: 2.4 | F51: 1.3 | G51: 2.9 | H51: 23.2 | I51: 0.8
B52: Total | C52: 0.2 | D52: 5.7 | E52: 7.4 | F52: 14.3 | G52: 6.2 | H52: 40.7 | I52: 1.8

Sheet MEVs and scenario weights
B2: Baseline average macroeconomic variables used in the calculation of ECL
E3: 2020 | F3: 2021 | G3: Expected Worst Point
B4: As at 31.03.20 | E4: % | F4: % | G4: %
B5: UK GDP | E5: -8 | F5: 6.3 | G5: -51.5
B6: UK unemployment | E6: 6.7 | F6: 4.5 | G6: 8
B7: UK HPI | E7: -3.5 | F7: 2.6 | G7: -6.5
B8: UK bank rate | E8: 0.1 | F8: 0.3 | G8: 0.1
B9: US GDP | E9: -6.4 | F9: 4.4 | G9: -45
B10: US unemployment | E10: 12.9 | F10: 7.5 | G10: 17
B11: US HPI | E11: - | F11: 0.7 | G11: -0.3
B12: US federal funds rate | E12: 0.25 | F12: 0.25 | G12: 0.25
B14: Scenario probability weighting
C15: Upside 2 | D15: Upside 1 | E15: Baseline | F15: Downside 1 | G15: Downside 2
B16: As at 31.03.20 | C16: % | D16: % | E16: % | F16: % | G16: %
B17: Scenario probability weighting | C17: 5 | D17: 20.8 | E17: 46.7 | F17: 21 | G17: 6.5
B19: As at 31.12.19
B20: Scenario probability weighting | C20: 10.1 | D20: 23.1 | E20: 40.8 | F20: 22.7 | G20: 3.3

Sheet Drivers of impairment change
B2: Drivers of loan impairment charge
B4: Three months ended 31.03.20 | D4: £m
B5: Impairment charge generated using scenarios before COVID-19 | D5: 370
B6: Single name wholesale loan charges | D6: 405
B7: Loan impairment charge prior to impact of COVID-19 scenario | D7: 775
B9: Impact of COVID-19 scenario and weights | D9: 1190
B10: Specific charge for the probability of a sustained period of low oil prices | D10: 300
B11: Incorporation of provision for UK economic uncertainty | D11: -150
B12: Total loan impairment charge | D12: 2115

Sheet Group liquidity pool
B2: Composition of the Group liquidity pool
D4: As at 31.03.20 | H4: As at 31.12.19
D5: Liquidity pool | E5: Liquidity pool of which CRR LCR eligible | H5: Liquidity pool
E6: Cash | F6: Level 1 | G6: Level 2A
D7: £bn | E7: £bn | F7: £bn | G7: £bn | H7: £bn
B8: Cash and deposits with central banks | D8: 157 | E8: 154 | F8: - | G8: - | H8: 153
B10: Government bonds
B11: AAA to AA- | D11: 43 | E11: - | F11: 38 | G11: 1 | H11: 31
B12: BBB+ to BBB- | D12: 14 | E12: - | F12: 7 | G12: 6 | H12: 2
B13: Other LCR ineligible government bonds | D13: 4 | E13: - | F13: 4 | G13: - | H13: 3
B14: Total government bonds | D14: 61 | E14: - | F14: 49 | G14: 7 | H14: 36
B16: Other
B17: Government guaranteed issuers, PSEs and GSEs | D17: 8 | E17: - | F17: 7 | G17: 1 | H17: 9
B18: International organisations and MDBs | D18: 6 | E18: - | F18: 6 | G18: - | H18: 7
B19: Covered bonds | D19: 5 | E19: - | F19: 5 | G19: 1 | H19: 6
B20: Total other | D20: 19 | E20: - | F20: 18 | G20: 2 | H20: 22
B22: Total as at 31 March 2020 | D22: 237 | E22: 154 | F22: 67 | G22: 9 | H22: 211
B23: Total as at 31 December 2019 | D23: 211 | E23: 150 | F23: 50 | G23: 3

Sheet Capital ratios and resources
B2: Capital ratios | C2: As at | D2: As at
C3: 31.03.20 | D3: 31.12.19
B4: CET1 | C4: 0.131 | D4: 0.138
B5: Tier 1 (T1) | C5: 0.166 | D5: 0.177
B6: Total regulatory capital | C6: 0.204 | D6: 0.216
B8: Capital resources | C8: £m | D8: £m
B9: Total equity excluding non-controlling interests per the balance sheet | C9: 68369 | D9: 64429
B10: Less: other equity instruments (recognised as AT1 capital) | C10: -10871 | D10: -10871
B11: Adjustment to retained earnings for foreseeable dividends | C11: -49 | D11: -1096
B13: Other regulatory adjustments and deductions
B14: Additional value adjustments (PVA) | C14: -1847 | D14: -1746
B15: Goodwill and intangible assets | C15: -8197 | D15: -8109
B16: Deferred tax assets that rely on future profitability excluding temporary differences | C16: -294 | D16: -479
B17: Fair value reserves related to gains or losses on cash flow hedges | C17: -1709 | D17: -1002
B18: Gains or losses on liabilities at fair value resulting from own credit | C18: -389 | D18: 260
B19: Defined benefit pension fund assets | C19: -3603 | D19: -1594
B20: Direct and indirect holdings by an institution of own CET1 instruments | C20: -50 | D20: -50
B21: Adjustment under IFRS 9 transitional arrangements | C21: 1215 | D21: 1126
B22: Other regulatory adjustments | C22: -57 | D22: -55
B23: CET1 capital | C23: 42518 | D23: 40813
B25: AT1 capital
B26: Capital instruments and related share premium accounts | C26: 10871 | D26: 10871
B27: Qualifying AT1 capital (including minority interests) issued by subsidiaries | C27: 753 | D27: 687
B28: Other regulatory adjustments and deductions | C28: -130 | D28: -130
B29: AT1 capital | C29: 11494 | D29: 11428
B31: T1 capital | C31: 54012 | D31: 52241
B33: T2 capital
B34: Capital instruments and related share premium accounts | C34: 8423 | D34: 7650
B35: Qualifying T2 capital (including minority interests) issued by subsidiaries | C35: 4013 | D35: 3984
B36: Credit risk adjustments (excess of impairment over expected losses) | C36: 196 | D36: 16
B37: Other regulatory adjustments and deductions | C37: -250 | D37: -250
B38: Total regulatory capital | C38: 66394 | D38: 63641
B40: Total RWAs | C40: 325631 | D40: 295131

Sheet Movement in CET1 capital
B2: Movement in CET1 capital | C2: Three months
C3: ended
C4: 31.03.20
C5: £m
B6: Opening CET1 capital | C6: 40813
B8: Profit for the period attributable to equity holders | C8: 826
B9: Own credit relating to derivative liabilities | C9: -169
B10: Dividends paid and foreseen | C10: 826
B11: Increase in retained regulatory capital generated from earnings | C11: 1483
B13: Net impact of share schemes | C13: -56
B14: Fair value through other comprehensive income reserve | C14: -777
B15: Currency translation reserve | C15: 997
B16: Other reserves | C16: -6
B17: Increase in other qualifying reserves | C17: 158
B19: Pension remeasurements within reserves | C19: 1990
B20: Defined benefit pension fund asset deduction | C20: -2009
... B30: Closing CET1 capital | C30: 42518

Sheet RWAs by risk type and business
B2: Risk weighted assets by risk type and business
C3: Credit risk | F3: Counterparty credit risk | K3: Market risk | N3: Operational risk | O3: Total RWAs
C4: Std | D4: IRB | F4: Std | G4: IRB | H4: Settlement risk | I4: CVA | K4: Std | L4: IMA
B5: As at 31.03.20 | C5: £m | D5: £m | F5: £m | G5: £m | H5: £m | I5: £m | K5: £m | L5: £m | N5: £m | O5: £m
B6: Barclays UK | C6: 5835 | D6: 59451 | F6: 311 | G6: - | H6: - | I6: 28 | K6: 202 | L6: - | N6: 11851 | O6: 77678
B7: Corporate and Investment Bank | C7: 30620 | D7: 71993 | F7: 15611 | G7: 19756 | H7: 1022 | I7: 3309 | K7: 14036 | L7: 24010 | N7: 21390 | O7: 201747
B8: Consumer, Cards and Payments | C8: 25205 | D8: 3085 | F8: 132 | G8: 31 | H8: - | I8: 21 | K8: - | L8: 151 | N8: 7536 | O8: 36161
B9: Barclays International | C9: 55825 | D9: 75078 | F9: 15743 | G9: 19787 | H9: 1022 | I9: 3330 | K9: 14036 | L9: 24161 | N9: 28926 | O9: 237908
B10: Head Office | C10: 3706 | D10: 6212 | F10: - | G10: - | H10: - | I10: - | K10: - | L10: - | N10: 127 | O10: 10045
B11: Barclays Group | C11: 65366 | D11: 140741 | F11: 16054 | G11: 19787 | H11: 1022 | I11: 3358 | K11: 14238 | L11: 24161 | N11: 40904 | O11: 325631
B13: As at 31.12.19
B14: Barclays UK | C14: 5189 | D14: 57455 | F14: 235 | G14: - | H14: - | I14: 23 | K14: 178 | L14: - | N14: 11821 | O14: 74901
B15: Corporate and Investment Bank | C15: 25749 | D15: 62177 | F15: 12051 | G15: 16875 | H15: 276 | I15: 2470 | K15: 12854 | L15: 17626 | N15: 21475 | O15: 171553
B16: Consumer, Cards and Payments | C16: 27209 | D16: 2706 | F16: 92 | G16: 37 | H16: - | I16: 11 | K16: - | L16: 103 | N16: 7532 | O16: 37690
B17: Barclays International | C17: 52958 | D17: 64883 | F17: 12143 | G17: 16912 | H17: 276 | I17: 2481 | K17: 12854 | L17: 17729 | N17: 29007 | O17: 209243
B18: Head Office | C18: 5104 | D18: 5754 | F18: - | G18: - | H18: - | I18: - | K18: - | L18: - | N18: 129 | O18: 10987
B19: Barclays Group | C19: 63251 | D19: 128092 | F19: 12378 | G19: 16912 | H19: 276 | I19: 2504 | K19: 13032 | L19: 17729 | N19: 40957 | O19: 295131

Sheet Movement in RWAs
B2: Movement analysis of RWAs
C3: Credit risk | D3: Counterparty credit risk | E3: Market risk | F3: Operational risk | G3: Total RWAs
C4: £m | D4: £m | E4: £m | F4: £m | G4: £m
B5: Opening RWAs (as at 31.12.19) | C5: 191343 | D5: 32070 | E5: 30761 | F5: 40957 | G5: 295131
B6: Book size | C6: 7205 | D6: 8300 | E6: 9977 | F6: -53 | G6: 25429
B7: Acquisitions and disposals | C7: -33 | D7: - | E7: - | F7: - | G7: -33
B8: Book quality | C8: 1511 | D8: -404 | E8: - | F8: - | G8: 1107
B9: Model updates | C9: 887 | D9: - | E9: - | F9: - | G9: 887
B10: Methodology and policy | C10: 1166 | D10: 255 | E10: -2339 | F10: - | G10: -918
B11: Foreign exchange movements | C11: 4028 | D11: - | E11: - | F11: - | G11: 4028
B12: Closing RWAs (as at 31.03.20) | C12: 206107 | D12: 40221 | E12: 38399 | F12: 40904 | G12: 325631

Sheet Leverage
B2: Leverage ratios | C2: As at | D2: As at
C3: 31.03.20 | D3: 31.12.19
C4: £m | D4: £m
B5: Average UK leverage ratio | C5: 0.045 | D5: 0.045
B6: Average T1 capital | C6: 53274 | D6: 51823
B7: Average UK leverage exposure | C7: 1176198 | D7: 1142819
B9: UK leverage ratio | C9: 0.045 | D9: 0.051
B11: CET1 capital | C11: 42518 | D11: 40812
B12: AT1 capital | C12: 10741 | D12: 10741
B13: T1 capital | C13: 53259 | D13: 51553
B15: UK leverage exposure | C15: 1178708 | D15: 1007721
B17: UK leverage exposure
B18: Accounting assets
B19: Derivative financial instruments | C19: 342120 | D19: 229236
B20: Derivative cash collateral | C20: 85321 | D20: 56589
B21: Securities financing transactions (SFTs) | C21: 185725 | D21: 111307
B22: Loans and advances and other assets | C22: 831130 | D22: 743097
B23: Total IFRS assets | C23: 1444296 | D23: 1140229
B25: Regulatory consolidation adjustments | C25: -4841 | D25: -1170
B27: Derivatives adjustments
B28: Derivatives netting | C28: -309585 | D28: -207756
B29: Adjustments to cash collateral | C29: -70758 | D29: -48464
B30: Net written credit protection | C30: 19994 | D30: 13784
B31: Potential future exposure (PFE) on derivatives | C31: 126503 | D31: 119118
B32: Total derivatives adjustments | C32: -233846 | D32: -123318
B34: SFTs adjustments | C34: 34271 | D34: 18339
B36: Regulatory deductions and other adjustments | C36: -14615 | D36: -11984
B38: Weighted off-balance sheet commitments | C38: 102499 | D38: 105289
B40: Qualifying central bank claims | C40: -149056 | D40: -119664
B42: UK leverage exposure | C42: 1178708 | D42: 1007721

Sheet MREL ratios and position
B2: MREL ratios and position
B4: Own funds and eligible liabilities ratios | C4: As at | D4: As at
C5: 31.03.20 | D5: 31.12.19
B6: CET1 capital | C6: 0.131 | D6: 0.138
B7: AT1 capital instruments and related share premium accounts | C7: 0.033 | D7: 0.036
B8: T2 capital instruments and related share premium accounts | C8: 0.026 | D8: 0.025
B9: Eligible liabilities | C9: 0.103 | D9: 0.112
B10: Total Barclays PLC (the Parent company) own funds and eligible liabilities | C10: 0.293 | D10: 0.312
B11: Qualifying AT1 capital (including minority interests) issued by subsidiaries | C11: 0.002 | D11: 0.002
B12: Qualifying T2 capital (including minority interests) issued by subsidiaries | C12: 0.012 | D12: 0.013
B13: Total own funds and eligible liabilities, including eligible Barclays Bank PLC instruments | C13: 0.307 | D13: 0.328
B15: Own funds and eligible liabilities | C15: £m | D15: £m
B16: CET1 capital | C16: 42518 | D16: 40813
B17: AT1 capital instruments and related share premium accounts | C17: 10741 | D17: 10741
B18: T2 capital instruments and related share premium accounts | C18: 8369 | D18: 7416
B19: Eligible liabilities | C19: 33674 | D19: 33025
B20: Total Barclays PLC (the Parent company) own funds and eligible liabilities | C20: 95302 | D20: 91995
B21: Qualifying AT1 capital (including minority interests) issued by subsidiaries | C21: 753 | D21: 687
B22: Qualifying T2 capital (including minority interests) issued by subsidiaries | C22: 4013 | D22: 3984
B23: Total own funds and eligible liabilities, including eligible Barclays Bank PLC instruments | C23: 100068 | D23: 96666
B25: Total RWAs | C25: 325631 | D25: 295131

Sheet Condensed consolidated IS
B2: Condensed consolidated income statement
D3: Three months ended | E3: Three months ended
D4: 31.03.20 | E4: 31.03.20
D5: £m | E5: £m
B6: Total income | D6: 6283 | E6: 5252
B7: Credit impairment charges and other provisions | D7: -2115 | E7: -448
B8: Net operating income | D8: 4168 | E8: 4804
B9: Operating expenses excluding litigation and conduct | D9: -3253 | E9: -3257
B10: Litigation and conduct | D10: -10 | E10: -61
B11: Operating expenses | D11: -3263 | E11: -3318
B12: Other net income/(expenses) | D12: 8 | E12: -3
B13: Profit before tax | D13: 913 | E13: 1483
B14: Tax charge | D14: -71 | E14: -248
B15: Profit after tax | D15: 842 | E15: 1235
B17: Attributable to:
B18: Equity holders of the parent | D18: 605 | E18: 1038
B19: Other equity instrument holders | D19: 221 | E19: 180
B20: Total equity holders of the parent | D20: 826 | E20: 1218
B21: Non-controlling interests | D21: 16 | E21: 17
B22: Profit after tax | D22: 842 | E22: 1235
B24: Earnings per share | D24: p | E24: p
B25: Basic earnings per ordinary share | D25: 3.5 | E25: 6.1

Sheet Condensed consolidated BS
B2: Condensed consolidated balance sheet
D3: As at | E3: As at
D4: 31.03.20 | E4: 31.12.19
B5: Assets | D5: £m | E5: £m
B6: Cash and balances at central banks | D6: 151805 | E6: 150258
B7: Cash collateral and settlement balances | D7: 157162 | E7: 83256
B8: Loans and advances at amortised cost | D8: 374149 | E8: 339115
B9: Reverse repurchase agreements and other similar secured lending | D9: 15384 | E9: 3379
B10: Trading portfolio assets | D10: 102000 | E10: 114195
B11: Financial assets at fair value through the income statement | D11: 193107 | E11: 133086
B12: Derivative financial instruments | D12: 342120 | E12: 229236
B13: Financial assets at fair value through other comprehensive income | D13: 83367 | E13: 65750
B14: Investments in associates and joint ventures | D14: 739 | E14: 721
B15: Goodwill and intangible assets | D15: 8209 | E15: 8119
B16: Current tax assets | D16: 510 | E16: 412
B17: Deferred tax assets | D17: 2713 | E17: 3290
... B19: Total assets | D19: 1444296 | E19: 1140229
B21: Liabilities
B22: Deposits at amortised cost | D22: 470698 | E22: 415787
B23: Cash collateral and settlement balances | D23: 127052 | E23: 67341
B24: Repurchase agreements and other similar secured borrowing | D24: 35958 | E24: 14517
B25: Debt securities in issue | D25: 87961 | E25: 76369
B26: Subordinated liabilities | D26: 19595 | E26: 18156
B27: Trading portfolio liabilities | D27: 54125 | E27: 36916
B28: Financial liabilities designated at fair value | D28: 227632 | E28: 204326
B29: Derivative financial instruments | D29: 338982 | E29: 229204
B30: Current tax liabilities | D30: 294 | E30: 313
B31: Deferred tax liabilities | D31: 516 | E31: 23
B32: Other liabilities | D32: 11883 | E32: 11617
B33: Total liabilities | D33: 1374696 | E33: 1074569
B35: Equity
B36: Called up share capital and share premium | D36: 4607 | E36: 4594
B37: Other reserves | D37: 6166 | E37: 4760
B38: Retained earnings | D38: 46725 | E38: 44204
B39: Shareholders' equity attributable to ordinary shareholders of the parent | D39: 57498 | E39: 53558
B40: Other equity instruments | D40: 10871 | E40: 10871
B41: Total equity excluding non-controlling interests | D41: 68369 | E41: 64429
B42: Non-controlling interests | D42: 1231 | E42: 1231
B43: Total equity | D43: 69600 | E43: 65660
B45: Total liabilities and equity | D45: 1444296 | E45: 1140229

Sheet Condensed consolidated SOCIE
B2: Condensed consolidated statement of changes in equity
C3: Called up share capital and share premium | D3: Other equity instruments | E3: Other reserves | F3: Retained earnings | G3: Total | H3: Non-controlling interests | I3: Total equity
B4: Three months ended 31.03.20 | C4: £m | D4: £m | E4: £m | F4: £m | G4: £m | H4: £m | I4: £m
B5: Balance as at 1 January 2020 | C5: 4594 | D5: 10871 | E5: 4760 | F5: 44204 | G5: 64429 | H5: 1231 | I5: 65660
B6: Profit after tax | C6: - | D6: 221 | E6: - | F6: 605 | G6: 826 | H6: 16 | I6: 842
B7: Retirement benefit remeasurements | C7: - | D7: - | E7: - | F7: 1990 | G7: 1990 | H7: - | I7: 1990
B8: Other | C8: - | D8: - | E8: 1407 | F8: -7 | G8: 1400 | H8: - | I8: 1400
B9: Total comprehensive income for the period | C9: - | D9: 221 | E9: 1407 | F9: 2588 | G9: 4216 | H9: 16 | I9: 4232
B10: Issue of shares under employee share schemes | C10: 13 | D10: - | E10: - | F10: 252 | G10: 265 | H10: - | I10: 265
B11: Other equity instruments coupons paid | C11: - | D11: -221 | E11: - | F11: - | G11: -221 | H11: - | I11: -221
B12: Vesting of shares under employee share schemes | C12: - | D12: - | E12: -1 | F12: -320 | G12: -321 | H12: - | I12: -321
B13: Dividends paid | C13: - | D13: - | E13: - | F13: - | G13: - | H13: -16 | I13: -16
B14: Other movements | C14: - | D14: - | E14: - | F14: 1 | G14: 1 | H14: - | I14: 1
B15: Balance as at 31 March 2020 | C15: 4607 | D15: 10871 | E15: 6166 | F15: 46725 | G15: 68369 | H15: 1231 | I15: 69600
H17: As at | I17: As at
H18: 31.03.20 | I18: 31.12.19
B19: Other reserves | H19: £m | I19: £m
B20: Currency translation reserve | H20: 4341 | I20: 3344
B21: Fair value through other comprehensive income reserve | H21: -964 | I21: -187
B22: Cash flow hedging reserve | H22: 1709 | I22: 1002
B23: Own credit reserve | H23: 107 | I23: -373
B24: Other reserves and treasury shares | H24: 973 | I24: 974
B25: Total | H25: 6166 | I25: 4760

Sheet Returns
A1: Returns
B2: Profit/(loss) attributable to ordinary equity holders of the parent | D2: Average tangible equity | F2: Return on average tangible equity
A3: Three months ended 31.03.20 | B3: £m | D3: £bn | F3: %
A4: Barclays UK | B4: 175 | D4: 10525.027 | F4: 6.7
A5: Corporate and Investment Bank | B5: 820 | D5: 27184.287 | F5: 12.1
A6: Consumer, Cards and Payments | B6: -291 | D6: 5147.7972 | F6: -22.6
A7: Barclays International | B7: 529 | D7: 32332.084 | F7: 6.5
A8: Head Office | B8: -99 | D8: 4237.5154 | F8: n/m
A9: Barclays Group | B9: 605 | D9: 46994.626 | F9: 5.1
A11: Three months ended 31.03.19
A12: Barclays UK | B12: 422 | D12: 10400 | F12: 16.3
A13: Corporate and Investment Bank | B13: 582 | D13: 25100 | F13: 9.3
A14: Consumer, Cards and Payments | B14: 206 | D14: 5400 | F14: 15.4
A15: Barclays International | B15: 788 | D15: 30500 | F15: 10.4
A16: Head Office | B16: -172 | D16: 4300 | F16: n/m
A17: Barclays Group | B17: 1038 | D17: 45200 | F17: 9.2

Sheet CYYTD performance measures excl
A1: Performance measures excluding litigation and conduct
I2: Please don't hide as this may be missed
B3: Year ended 31.12.19 | I3: Delete before distribution
B4: Barclays UK | C4: Corporate and Investment Bank | D4: Consumer, Cards and Payments | E4: Barclays International | F4: Head Office | G4: Barclays Group | O4: CIB+CPPB=BI | P4: Cast to Group | R4: Consistency to YTD | AF4: Consistency to YTD
A5: Cost: income ratio | B5: £m | C5: £m | D5: £m | E5: £m | F5: £m | G5: £m | R5: Barclays UK | S5: CIB | T5: CCP | U5: Barclays International | V5: Head Office | W5: Barclays Group | AF5: Barclays UK | AG5: Barclays International | AH5: Head Office | AI5: Barclays Group
A6: Total operating expenses | B6: -5619 | C6: -7147 | D6: -2306 | E6: -9453 | F6: -362 | G6: -15434 | O6: =ROUND(C6,0)+ROUND(D6,0)-ROUND(E6,0) -> 0 | P6: =G6-F6-E6-B6 -> 0 | R6: =+ROUND(B6,0)-ROUND('Barclays UK YTD'!C14,0) -> 0 | S6: =ROUND(C6,0)-ROUND('Barclays International YTD'!C69,0) -> 0 | T6: =ROUND(D6,0)-ROUND('Barclays International YTD'!C109,0) -> 0 | U6: =+ROUND(E6,0)-ROUND('Barclays International YTD'!C15,0) -> 0 | V6: =+ROUND(F6,0)-ROUND('Head Office YTD'!C15,0) -> 0 | W6: =+ROUND(G6,0)-ROUND('Group PH'!C9,0) -> -12171 | AF6: 4848 | AG6: 9855 | AH6: 469 | AI6: 15456
A7: Impact of litigation and conduct | B7: 1582.3055 | C7: 109.36277 | D7: 7.4087847 | E7: 115.77155 | F7: 151.39434 | G7: 1849.4714 | O7: =ROUND(C7,0)+ROUND(D7,0)-ROUND(E7,0) -> 0 | P7: =G7-F7-E7-B7 -> 0 | R7: =ROUND(B7,0)+ROUND('Barclays UK YTD'!C13,0) -> 0 | S7: =ROUND(C7,0)+ROUND('Barclays International YTD'!C68,) -> 0 | T7: =ROUND(D7,0)+ROUND('Barclays International YTD'!C108,0) -> 0 | U7: =ROUND(E7,0)+ROUND('Barclays International YTD'!C14,0) -> 0 | V7: =ROUND(F7,0)+ROUND('Head Office YTD'!C14,0) -> 0 | W7: =ROUND(G7,0)+ROUND('Group PH'!C8,0) -> 1839 | Y7: Casting | AF7: -59 | AG7: -265 | AH7: -151 | AI7: -365 | AK7: Casting
A8: Operating expenses | B8: -4036.6945 | C8: -7037.6372 | D8: -2298.5912 | E8: -9337.2284 | F8: -210.60566 | G8: -13584.529 | O8: =ROUND(C8,0)+ROUND(D8,0)-ROUND(E8,0) -> 0 | P8: =ROUND(G8,0)-ROUND(F8,0)-ROUND(E8,0)-ROUND(B8,0) -> 0 | R8: =+ROUND(B8,0)-ROUND('Barclays UK YTD'!C10,0)-ROUND('Barclays UK YTD'!C11,0) -> 0 | S8: =ROUND(C8,0)-ROUND('Barclays International YTD'!C65,0)-ROUND('Barclays International YTD'!C66,0) -> 0 | T8: =ROUND(D8,0)-ROUND('Barclays International YTD'!C105,0)-ROUND('Barclays International YTD'!C106,0) -> 0 | U8: =+ROUND(E8,0)-ROUND('Barclays International YTD'!C15,0)+ROUND('Barclays International YTD'!C14,0) -> 0 | V8: =+ROUND(F8,0)-ROUND('Head Office YTD'!C10,0)-ROUND('Head Office YTD'!C11,0) -> 0 | W8: =+ROUND(G8,0)-ROUND('Group PH'!C7,0)-ROUND('Group PH'!#REF!,0) -> #REF! | Y8: =+ROUND(B6,0)+ROUND(B7,0)-ROUND(B8,0) -> 0 | Z8: =+ROUND(C6,0)+ROUND(C7,0)-ROUND(C8,0) -> 0 | AA8: =+ROUND(D6,0)+ROUND(D7,0)-ROUND(D8,0) -> 0 | AB8: =+ROUND(E6,0)+ROUND(E7,0)-ROUND(E8,0) -> 0 | AC8: =+ROUND(F6,0)+ROUND(F7,0)-ROUND(F8,0) -> 0 | AD8: =+ROUND(G6,0)+ROUND(G7,0)-ROUND(G8,0) -> 0 | AF8: 4030 | AG8: 9321 | AH8: 277 | AI8: 13884 | AK8: =+ROUND(I6,0)+ROUND(I7,0)-ROUND(I8,0) -> 0 | AL8: =+ROUND(J6,0)+ROUND(J7,0)-ROUND(J8,0) -> 0 | AM8: =+ROUND(K6,0)+ROUND(K7,0)-ROUND(K8,0) -> 0 | AN8: =+ROUND(L6,0)+ROUND(L7,0)-ROUND(L8,0) -> 0
A10: Total income | B10: 7353 | C10: 10231 | D10: 4444 | E10: 14675 | F10: -396 | G10: 21632 | O10: =ROUND(C10,0)+ROUND(D10,0)-ROUND(E10,0) -> 0 | P10: =ROUND(G10,0)-ROUND(F10,0)-ROUND(E10,0)-ROUND(B10,0) -> 0 | R10: =+ROUND(B10,0)-ROUND('Barclays UK YTD'!C7,0) -> 0 | S10: =ROUND(C10,0)-ROUND('Barclays International YTD'!C62,0) -> 0 | T10: =ROUND(D10,0)-ROUND('Barclays International YTD'!C102,0) -> 0 | U10: =+ROUND(E10,0)-ROUND('Barclays International YTD'!C8,0) -> 0 | V10: =+ROUND(F10,0)-ROUND('Head Office YTD'!C7,0) -> 0 | W10: =+ROUND(G10,0)-ROUND('Group PH'!C4,0) -> 15349 | AF10: -7383 | AG10: -14382 | AH10: 159 | AI10: -21076
A12: Cost: income ratio excluding litigation and conduct | B12: 0.55 | C12: 0.69 | D12: 0.52 | E12: 0.64 | F12: n/m | G12: 0.63 | R12: =+ROUND(B12,2)-ROUND('Barclays UK YTD'!C45,2) -> 0 | S12: =ROUND(C12,2)-ROUND('Barclays International YTD'!C95,2) -> 0 | T12: =ROUND(D12,2)-ROUND('Barclays International YTD'!C138,2) -> 0 | U12: =+ROUND(E12,2)-ROUND('Barclays International YTD'!C45,2) -> 0 | W12: =+ROUND(G12,2)-ROUND('Group PH'!C29,2) -> 0.11 | AF12: -2506 | AG12: -3544 | AI12: -4748
A14: Profit before tax
A15: Profit/(loss) before tax | B15: 1022 | C15: 2955 | D15: 1163 | E15: 4118 | F15: -783 | G15: 4357 | O15: =ROUND(C15,0)+ROUND(D15,0)-ROUND(E15,0) -> 0 | P15: =ROUND(G15,0)-ROUND(F15,0)-ROUND(E15,0)-ROUND(B15,0) -> 0 | R15: =+ROUND(B15,0)-ROUND('Barclays UK YTD'!C16,0) -> 0 | S15: =ROUND(C15,0)-ROUND('Barclays International YTD'!C71,0) -> 0 | T15: =ROUND(D15,0)-ROUND('Barclays International YTD'!C111,0) -> 0 | U15: =+ROUND(E15,0)-ROUND('Barclays International YTD'!C17,0) -> 0 | V15: =+ROUND(F15,0)-ROUND('Head Office YTD'!C17,0) -> 0 | W15: =+ROUND(G15,0)-ROUND('Group PH'!C11,0) -> 3444 | AF15: -1747 | AG15: -3275 | AH15: 834 | AI15: -3541
A16: Impact of litigation and conduct | B16: 1582.3055 | C16: 109.36277 | D16: 7.4087847 | E16: 115.77155 | F16: 151.39434 | G16: 1849.4714 | O16: =ROUND(C16,0)+ROUND(D16,0)-ROUND(E16,0) -> 0 | P16: =G16-F16-E16-B16 -> 0 | R16: =ROUND(B16,0)+ROUND('Barclays UK YTD'!C13,0) -> 0 | S16: =ROUND(C16,0)+ROUND('Barclays International YTD'!C68,0) -> 0 | T16: =ROUND(D16,0)+ROUND('Barclays International YTD'!C108,0) -> 0 | U16: =ROUND(E16,0)+ROUND('Barclays International YTD'!C14,0) -> 0 | V16: =ROUND(F16,0)+ROUND('Head Office YTD'!C14,0) -> 0 | W16: =ROUND(G16,0)+ROUND('Group PH'!C8,0) -> 1839 | AF16: -59 | AG16: -265 | AH16: -151 | AI16: -365
A17: Profit/(loss) before tax excluding litigation and conduct | B17: 2604.3055 | C17: 3064.3628 | D17: 1170.4088 | E17: 4233.7716 | F17: -631.60566 | G17: 6206.4714 | O17: =ROUND(C17,0)+ROUND(D17,0)-ROUND(E17,0) -> 0 | P17: =G17-F17-E17-B17 -> 0 | R17: =+ROUND(B17,0)-ROUND('Barclays UK YTD'!C42,0) -> 0 | S17: =ROUND(C17,0)-ROUND('Barclays International YTD'!C92,0) -> 0 | T17: =ROUND(D17,0)-ROUND('Barclays International YTD'!C135,0) -> 0 | U17: =+ROUND(E17,0)-ROUND('Barclays International YTD'!C42,0) -> 0 | V17: =+ROUND(F17,0)-ROUND('Head Office YTD'!C29,0) -> 0 | W17: =+ROUND(G17,0)-ROUND('Group PH'!C26,0) -> 5283 | Y17: =+ROUND(B15,0)+ROUND(B16,0)-ROUND(B17,0) -> 0 | Z17: =+ROUND(C15,0)+ROUND(C16,0)-ROUND(C17,0) -> 0 | AA17: =+ROUND(D15,0)+ROUND(D16,0)-ROUND(D17,0) -> 0 | AB17: =+ROUND(E15,0)+ROUND(E16,0)-ROUND(E17,0) -> 0 | AC17: =+ROUND(F15,0)+ROUND(F16,0)-ROUND(F17,0) -> 0 | AD17: =+ROUND(G15,0)+ROUND(G16,0)-ROUND(G17,0) -> 0 | AF17: -1586 | AG17: -1107 | AH17: 683 | AI17: 772 | AK17: =+ROUND(I15,0)+ROUND(I16,0)-ROUND(I17,0) -> 0 | AL17: =+ROUND(J15,0)+ROUND(J16,0)-ROUND(J17,0) -> 0 | AM17: =+ROUND(K15,0)+ROUND(K16,0)-ROUND(K17,0) -> 0 | AN17: =+ROUND(L15,0)+ROUND(L16,0)-ROUND(L17,0) -> 0
A19: Profit attributable to ordinary equity holders of the parent
A20: Attributable profit/(loss) | B20: 281 | C20: 1980 | D20: 836 | E20: 2816 | F20: -636 | G20: 2461 | O20: =ROUND(C20,0)+ROUND(D20,0)-ROUND(E20,0) -> 0 | P20: =ROUND(G20,0)-ROUND(F20,0)-ROUND(E20,0)-ROUND(B20,0) -> 0 | R20: =+ROUND(B20,0)-ROUND('Barclays UK YTD'!C17,0) -> 0 | S20: =ROUND(C20,0)-ROUND('Barclays International YTD'!C72,0) -> 0 | T20: =ROUND(D20,0)-ROUND('Barclays International YTD'!C112,0) -> 0 | U20: =+ROUND(E20,0)-ROUND('Barclays International YTD'!C18,0) -> 0 | V20: =+ROUND(F20,0)-ROUND('Head Office YTD'!C18,0) -> 0 | W20: =+ROUND(G20,0)-ROUND('Group PH'!C16,0) -> 1856 | AF20: -853 | AG20: -847 | AH20: 868 | AI20: 1922
A21: Post-tax impact of litigation and conduct | B21: 1532 | C21: 84 | D21: 6 | E21: 90 | F21: 111 | G21: 1733 | O21: =ROUND(C21,0)+ROUND(D21,0)-ROUND(E21,0) -> 0 | P21: =G21-F21-E21-B21 -> 0
A22: Profit/(loss) attributable to ordinary equity holders of the parent excluding litigation and conduct | B22: 1813.076 | C22: 2063.5163 | D22: 841.52103 | E22: 2906.0373 | F22: -524.84075 | G22: 4194.2726 | O22: =ROUND(C22,0)+ROUND(D22,0)-ROUND(E22,0) -> 0 | P22: =ROUND(G22,0)-ROUND(F22,0)-ROUND(E22,0)-ROUND(B22,0) -> 0 | R22: =ROUND(B22,0)-ROUND('Barclays UK YTD'!C43,0) -> 0 | S22: =ROUND(C22,0)-ROUND('Barclays International YTD'!C93,0) -> 0 | T22: =ROUND(D22,0)-ROUND('Barclays International YTD'!C136,0) -> 0 | U22: =ROUND(E22,0)-ROUND('Barclays International YTD'!C43,0) -> 0 | V22: =ROUND(F22,0)-ROUND('Head Office YTD'!C30,0) -> 0 | W22: =ROUND(G22,0)-ROUND('Group PH'!C27,0) -> 3590
Y23: =+ROUND(B20,0)+ROUND(B21,0)-ROUND(B22,0) -> 0 | Z23: =+ROUND(C20,0)+ROUND(C21,0)-ROUND(C22,0) -> 0 | AA23: =+ROUND(D20,0)+ROUND(D21,0)-ROUND(D22,0) -> 0 | AB23: =+ROUND(E20,0)+ROUND(E21,0)-ROUND(E22,0) -> 0 | AC23: =+ROUND(F20,0)+ROUND(F21,0)-ROUND(F22,0) -> 0 | AD23: =+ROUND(G20,0)+ROUND(G21,0)-ROUND(G22,0) -> 0 | AK23: =+ROUND(#REF!,0)+ROUND(#REF!,0)-ROUND(I22,0) -> #REF! | AL23: =+ROUND(#REF!,0)+ROUND(#REF!,0)-ROUND(J22,0) -> #REF! | AM23: =+ROUND(#REF!,0)+ROUND(#REF!,0)-ROUND(K22,0) -> #REF! | AN23: =+ROUND(#REF!,0)+ROUND(#REF!,0)-ROUND(L22,0) -> #REF!
A24: Return on average tangible shareholders' equity | B24: £bn | C24: £bn | D24: £bn | E24: £bn | F24: £bn | G24: £bn | AF24: Consistency to Group YTD
A25: Average shareholders' equity | B25: 13900 | C25: 25900 | D25: 6300 | E25: 32200 | F25: 8500 | G25: 54600 | O25: =ROUND(C25,0)+ROUND(D25,0)-ROUND(E25,0) -> 0 | P25: =G25-F25-E25-B25 -> 0
A26: Average goodwill and intangibles | B26: -3600 | C26: 0 | D26: -1000 | E26: -1000 | F26: -3400 | G26: -8000 | O26: =ROUND(C26,0)+ROUND(D26,0)-ROUND(E26,0) -> 0 | P26: =G26-F26-E26-B26 -> 0 | R26: Consistency to Group YTD
A27: Average tangible shareholders' equity | B27: 10333.198 | C27: 25886.815 | D27: 5281.7143 | E27: 31168.529 | F27: 5056.3352 | G27: 46558.062 | O27: =ROUND(C27,0)+ROUND(D27,0)-ROUND(E27,0) -> 0 | P27: =G27-F27-E27-B27 -> 0 | R27: =+ROUND(B27,-2)-ROUND('Barclays UK YTD'!C36,-2) -> 0 | S27: =ROUND(C27,-2)-ROUND('Barclays International YTD'!C88,-2) -> 0 | T27: =ROUND(D27,-2)-ROUND('Barclays International YTD'!C130,-2) -> 0 | U27: =+ROUND(E27,-2)-ROUND('Barclays International YTD'!C36,-2) -> 0 | V27: =+ROUND(F27,-2)-ROUND('Head Office YTD'!C26,-2) -> 0 | W27: =+ROUND(G27,-2)-ROUND('Group PH'!C20,-2) -> -400 | AF27: -1 | AG27: -1 | AH27: -9300 | AI27: -1000
A29: Return on average tangible shareholders' equity excluding litigation and conduct | B29: 0.175 | C29: 0.08 | D29: 0.159 | E29: 0.093 | F29: n/m | G29: 0.09 | R29: =ROUND(B29,3)-ROUND('Barclays UK YTD'!C44,3) -> 0 | S29: =ROUND(C29,3)-ROUND('Barclays International YTD'!C94,3) -> 0 | T29: =ROUND(D29,3)-ROUND('Barclays International YTD'!C137,3) -> 0 | U29: =+ROUND(E29,3)-ROUND('Barclays International YTD'!C44,3) -> 0 | W29: =+ROUND(G29,3)-ROUND('Group PH'!C28,3) -> 0.039 | Y29: =+ROUND(B25,-2)+ROUND(B26,-2)-ROUND(B27,-2) -> 0 | Z29: =+ROUND(C25,-2)+ROUND(C26,-2)-ROUND(C27,-2) -> 0 | AA29: =+ROUND(D25,-2)+ROUND(D26,-2)-ROUND(D27,-2) -> 0 | AB29: =+ROUND(E25,-2)+ROUND(E26,-2)-ROUND(E27,-2) -> 0 | AC29: =+ROUND(F25,-2)+ROUND(F26,-2)-ROUND(F27,-2) -> 0 | AD29: =+ROUND(G25,-2)+ROUND(G26,-2)-ROUND(G27,-2) -> 0 | AF29: 0 | AG29: -1 | AI29: 0
N30: RoTE: | O30: CIB+CCP=BI
A31: Basic earnings per ordinary share
A32: Basic weighted average number of shares (m) | G32: 17200.217
A34: Basic earnings per ordinary share excluding litigation and conduct | G34: 24.384998 | N34: EPS | O34: =G34-G22/G32*100 -> 0 | W34: =+ROUND(G34,0)-ROUND('Group PH'!C30,0) -> 21 | AI34: 4

Sheet PYYTD performance measures
A1: Performance measures excluding litigation and conduct
B3: Year ended 31.12.18
B4: Barclays UK | C4: Corporate and Investment Bank | D4: Consumer, Cards and Payments | E4: Barclays International | F4: Head Office | G4: Barclays Group | K4: CIB+CPPB=BI | L4: Cast to Group | N4: Consistency to YTD | AB4: Consistency to YTD
A5: Cost: income ratio | B5: £m | C5: £m | D5: £m | E5: £m | F5: £m | G5: £m | N5: Barclays UK | O5: CIB | P5: CPPB | Q5: Barclays International | R5: Head Office | S5: Barclays Group | AB5: Barclays UK | AC5: Barclays International | AD5: Head Office | AE5: Barclays Group
A6: Total operating expenses | B6: -4604 | C6: -7349 | D6: -2312 | E6: -9661 | F6: -1978 | G6: -16243 | K6: =ROUND(C6,0)+ROUND(D6,0)-ROUND(E6,0) -> 0 | L6: =G6-F6-E6-B6 -> 0 | N6: =+ROUND(B6,0)-ROUND('Barclays UK YTD'!D14,0) -> 0 | O6: =ROUND(C6,0)-ROUND('Barclays International YTD'!D69,0) -> 0 | P6: =ROUND(D6,0)-ROUND('Barclays International YTD'!D109,0) -> 0 | Q6: =+ROUND(E6,0)-ROUND('Barclays International YTD'!D15,0) -> 0 | R6: =+ROUND(F6,0)-ROUND('Head Office YTD'!D15,0) -> 0 | S6: =+ROUND(G6,0)-ROUND('Group PH'!D9,0) -> -12925 | AB6: #REF! | AC6: #REF! | AD6: #REF! | AE6: #REF!
A7: Impact of litigation and conduct | B7: 483 | C7: 68 | D7: 59 | E7: 127 | F7: 1597 | G7: 2207 | K7: =ROUND(C7,0)+ROUND(D7,0)-ROUND(E7,0) -> 0 | L7: =G7-F7-E7-B7 -> 0 | N7: =B7+'Barclays UK YTD'!D13 -> 0 | O7: =ROUND(C7,0)+ROUND('Barclays International YTD'!D68,0) -> 0 | P7: =ROUND(D7,0)+ROUND('Barclays International YTD'!D108,0) -> 0 | Q7: =ROUND(E7,0)+ROUND('Barclays International YTD'!D14,0) -> 0 | R7: =+ROUND(F7,0)+ROUND('Head Office YTD'!D14,0) -> 0 | S7: =ROUND(G7,0)+ROUND('Group PH'!D8,0) -> 2146 | U7: Casting | AB7: #REF! | AC7: #REF! | AD7: #REF! | AE7: #REF! | AG7: Casting
A8: Operating expenses | B8: -4121 | C8: -7281 | D8: -2253 | E8: -9534 | F8: -381 | G8: -14036 | K8: =ROUND(C8,0)+ROUND(D8,0)-ROUND(E8,0) -> 0 | L8: =G8-F8-E8-B8 -> 0 | N8: =+ROUND(B8,0)-ROUND('Barclays UK YTD'!D10,0)-ROUND('Barclays UK YTD'!D11,0) -> 0 | O8: =ROUND(C8,0)-ROUND('Barclays International YTD'!D65,0)-ROUND('Barclays International YTD'!D66,0) -> 0 | P8: =ROUND(D8,0)-ROUND('Barclays International YTD'!D105,0)-ROUND('Barclays International YTD'!D106,0) -> 0 | Q8: =+ROUND(E8,0)-ROUND('Barclays International YTD'!D11,0)-ROUND('Barclays International YTD'!D12,0) -> 0 | R8: =+ROUND(F8,0)-ROUND('Head Office YTD'!D10,0)-ROUND('Head Office YTD'!D11,0)-ROUND('Head Office YTD'!D13,0) -> 0 | S8: =+ROUND(G8,0)-ROUND('Group PH'!D7,0)-ROUND('Group PH'!#REF!,0)-ROUND('Group PH'!#REF!,0) -> #REF! | U8: =+ROUND(B6,0)+ROUND(B7,0)-ROUND(B8,0) -> 0 | V8: =+ROUND(C6,0)+ROUND(C7,0)-ROUND(C8,0) -> 0 | W8: =+ROUND(D6,0)+ROUND(D7,0)-ROUND(D8,0) -> 0 | X8: =+ROUND(E6,0)+ROUND(E7,0)-ROUND(E8,0) -> 0 | Y8: =+ROUND(F6,0)+ROUND(F7,0)-ROUND(F8,0) -> 0 | Z8: =+ROUND(G6,0)+ROUND(G7,0)-ROUND(G8,0) -> 0 | AB8: #REF! | AC8: #REF! | AD8: #REF! | AE8: #REF! | AG8: =+ROUND(#REF!,0)+ROUND(#REF!,0)-ROUND(#REF!,0) -> #REF! | AH8: =+ROUND(#REF!,0)+ROUND(#REF!,0)-ROUND(#REF!,0) -> #REF! | AI8: =+ROUND(#REF!,0)+ROUND(#REF!,0)-ROUND(#REF!,0) -> #REF! | AJ8: =+ROUND(#REF!,0)+ROUND(#REF!,0)-ROUND(#REF!,0) -> #REF!
A10: Total income | B10: 7383 | C10: 9765 | D10: 4261 | E10: 14026 | F10: -273 | G10: 21136 | K10: =ROUND(C10,0)+ROUND(D10,0)-ROUND(E10,0) -> 0 | L10: =G10-F10-E10-B10 -> 0 | N10: =+ROUND(B10,0)-ROUND('Barclays UK YTD'!D7,0) -> 0 | O10: =ROUND(C10,0)-ROUND('Barclays International YTD'!D62,0) -> 0 | P10: =ROUND(D10,0)-ROUND('Barclays International YTD'!D102,0) -> 0 | Q10: =+ROUND(E10,0)-ROUND('Barclays International YTD'!D8,0) -> 0 | R10: =+ROUND(F10,0)-ROUND('Head Office YTD'!D7,0) -> 0 | S10: =+ROUND(G10,0)-ROUND('Group PH'!D4,0) -> 15884 | AB10: #REF! | AC10: #REF! | AD10: #REF! | AE10: #REF!
A12: Cost: income ratio excluding litigation and conduct | B12: 0.56 | C12: 0.75 | D12: 0.53 | E12: 0.68 | F12: n/m | G12: 0.66 | N12: =+ROUND(B12,2)-ROUND('Barclays UK YTD'!D45,2) -> 0 | O12: =ROUND(C12,2)-ROUND('Barclays International YTD'!D95,2) -> 0 | P12: =ROUND(D12,2)-ROUND('Barclays International YTD'!D138,2) -> 0 | Q12: =+ROUND(E12,2)-ROUND('Barclays International YTD'!D45,2) -> 0 | S12: =+ROUND(G12,2)-ROUND('Group PH'!D29,2) -> 0.04 | AB12: #REF! | AC12: #REF! | AE12: #REF!
A14: Profit before tax
A15: Profit/(loss) before tax | B15: 1956 | C15: 2593 | D15: 1182 | E15: 3775 | F15: -2237 | G15: 3494 | K15: =ROUND(C15,0)+ROUND(D15,0)-ROUND(E15,0) -> 0 | L15: =G15-F15-E15-B15 -> 0 | N15: =+ROUND(B15,0)-ROUND('Barclays UK YTD'!D16,0) -> 0 | O15: =ROUND(C15,0)-ROUND('Barclays International YTD'!D71,0) -> 0 | P15: =ROUND(D15,0)-ROUND('Barclays International YTD'!D111,0) -> 0 | Q15: =+ROUND(E15,0)-ROUND('Barclays International YTD'!D17,0) -> 0 | R15: =+ROUND(F15,0)-ROUND('Head Office YTD'!D17,0) -> 0 | S15: =+ROUND(G15,0)-ROUND('Group PH'!D11,0) -> 2011 | AB15: #REF! | AC15: #REF! | AD15: #REF! | AE15: #REF!
A16: Impact of litigation and conduct | B16: 483 | C16: 68 | D16: 59 | E16: 127 | F16: 1597 | G16: 2207 | K16: =ROUND(C16,0)+ROUND(D16,0)-ROUND(E16,0) -> 0 | L16: =G16-F16-E16-B16 -> 0 | N16: =+ROUND(B16,0)+ROUND('Barclays UK YTD'!D13,0) -> 0 | O16: =ROUND(C16,0)+ROUND('Barclays International YTD'!D68,0) -> 0 | P16: =ROUND(D16,0)+ROUND('Barclays International YTD'!D108,0) -> 0 | Q16: =+ROUND(E16,0)+ROUND('Barclays International YTD'!D14,0) -> 0 | R16: =+ROUND(F16,0)+ROUND('Head Office YTD'!D14,0) -> 0 | S16: =+ROUND(G16,0)+ROUND('Group PH'!D8,0) -> 2146 | AB16: #REF! | AC16: #REF! | AD16: #REF! | AE16: #REF!
A17: Profit/(loss) before tax excluding litigation and conduct | B17: 2439 | C17: 2661 | D17: 1241 | E17: 3902 | F17: -640 | G17: 5701 | K17: =ROUND(C17,0)+ROUND(D17,0)-ROUND(E17,0) -> 0 | L17: =G17-F17-E17-B17 -> 0 | N17: =+ROUND(B17,0)-ROUND('Barclays UK YTD'!D42,0) -> 0 | O17: =ROUND(C17,0)-ROUND('Barclays International YTD'!D92,0) -> 0 | P17: =ROUND(D17,0)-ROUND('Barclays International YTD'!D135,0) -> 0 | Q17: =+ROUND(E17,0)-ROUND('Barclays International YTD'!D42,0) -> 0 | R17: =+ROUND(F17,0)-ROUND('Head Office YTD'!D29,0) -> 0 | S17: =+ROUND(G17,0)-ROUND('Group PH'!D26,0) -> 4157 | U17: =+ROUND(B15,0)+ROUND(B16,0)-ROUND(B17,0) -> 0 | V17: =+ROUND(C15,0)+ROUND(C16,0)-ROUND(C17,0) -> 0 | W17: =+ROUND(D15,0)+ROUND(D16,0)-ROUND(D17,0) -> 0 | X17: =+ROUND(E15,0)+ROUND(E16,0)-ROUND(E17,0) -> 0 | Y17: =+ROUND(F15,0)+ROUND(F16,0)-ROUND(F17,0) -> 0 | Z17: =+ROUND(G15,0)+ROUND(G16,0)-ROUND(G17,0) -> 0 | AB17: #REF! | AC17: #REF! | AD17: #REF! | AE17: #REF! | AG17: =+ROUND(#REF!,0)+ROUND(#REF!,0)-ROUND(#REF!,0) -> #REF! | AH17: =+ROUND(#REF!,0)+ROUND(#REF!,0)-ROUND(#REF!,0) -> #REF! | AI17: =+ROUND(#REF!,0)+ROUND(#REF!,0)-ROUND(#REF!,0) -> #REF! | AJ17: =+ROUND(#REF!,0)+ROUND(#REF!,0)-ROUND(#REF!,0) -> #REF!
A19: Profit attributable to ordinary equity holders of the parent
A20: Attributable profit/(loss) | B20: 1198 | C20: 1781 | D20: 818 | E20: 2599 | F20: -2200 | G20: 1597 | K20: =ROUND(C20,0)+ROUND(D20,0)-ROUND(E20,0) -> 0 | L20: =G20-F20-E20-B20 -> 0 | N20: =+ROUND(B20,0)-ROUND('Barclays UK YTD'!D17,0) -> 0 | O20: =ROUND(C20,0)-ROUND('Barclays International YTD'!D72,0) -> 0 | P20: =ROUND(D20,0)-ROUND('Barclays International YTD'!D112,0) -> 0 | Q20: =+ROUND(E20,0)-ROUND('Barclays International YTD'!D18,0) -> 0 | R20: =+ROUND(F20,0)-ROUND('Head Office YTD'!D18,0) -> 0 | S20: =+ROUND(G20,0)-ROUND('Group PH'!D16,0) -> 559 | AB20: #REF! | AC20: #REF! | AD20: #REF! | AE20: #REF!
A21: Post-tax impact of litigation and conduct | B21: 472 | C21: 62 | D21: 44 | E21: 106 | F21: 1558 | G21: 2136 | K21: =ROUND(C21,0)+ROUND(D21,0)-ROUND(E21,0) -> 0 | L21: =G21-F21-E21-B21 -> 0
A22: Profit/(loss) attributable to ordinary equity holders of the parent excluding litigation and conduct | B22: 1670 | C22: 1843 | D22: 862 | E22: 2705 | F22: -642 | G22: 3733 | K22: =ROUND(C22,0)+ROUND(D22,0)-ROUND(E22,0) -> 0 | L22: =G22-F22-E22-B22 -> 0 | N22: =ROUND(B22,0)-ROUND('Barclays UK YTD'!D43,0) -> 0 | O22: =ROUND(C22,0)-ROUND('Barclays International YTD'!D93,0) -> 0 | P22: =ROUND(D22,0)-ROUND('Barclays International YTD'!D136,0) -> 0 | Q22: =ROUND(E22,0)-ROUND('Barclays International YTD'!D43,0) -> 0 | R22: =ROUND(F22,0)-ROUND('Head Office YTD'!D30,0) -> 0 | S22: =ROUND(G22,0)-(ROUND('Group PH'!D27,0)) -> 2649
U23: =+ROUND(B20,0)+ROUND(B21,0)-ROUND(B22,0) -> 0 | V23: =+ROUND(C20,0)+ROUND(C21,0)-ROUND(C22,0) -> 0 | W23: =+ROUND(D20,0)+ROUND(D21,0)-ROUND(D22,0) -> 0 | X23: =+ROUND(E20,0)+ROUND(E21,0)-ROUND(E22,0) -> 0 | Y23: =+ROUND(F20,0)+ROUND(F21,0)-ROUND(F22,0) -> 0 | Z23: =+ROUND(G20,0)+ROUND(G21,0)-ROUND(G22,0) -> 0 | AG23: =+ROUND(#REF!,0)+ROUND(#REF!,0)-ROUND(#REF!,0) -> #REF! | AH23: =+ROUND(#REF!,0)+ROUND(#REF!,0)-ROUND(#REF!,0) -> #REF! | AI23: =+ROUND(#REF!,0)+ROUND(#REF!,0)-ROUND(#REF!,0) -> #REF! | AJ23: =+ROUND(#REF!,0)+ROUND(#REF!,0)-ROUND(#REF!,0) -> #REF!
A24: Return on average tangible shareholders' equity | B24: £bn | C24: £bn | D24: £bn | E24: £bn | F24: £bn | G24: £bn | N24: Consistency to Group YTD | AB24: Consistency to Group YTD
A25: Average shareholders' equity | B25: 13600 | C25: 26200 | D25: 6100 | E25: 32300 | F25: 6169.5477 | G25: 52100
A26: Average goodwill and intangibles | B26: -3588 | C26: -201 | D26: -1100 | E26: -1300 | F26: -3070 | G26: -7997
A27: Average tangible shareholders' equity | B27: 10012.352 | C27: 25998.982 | D27: 5000 | E27: 31000 | F27: 3100 | G27: 44102.939 | N27: =+ROUND(B27,-2)-ROUND('Barclays UK YTD'!D36,-2) -> 0 | O27: =ROUND(C27,-2)-ROUND('Barclays International YTD'!D88,-2) -> 0 | P27: =ROUND(D27,-2)-ROUND('Barclays International YTD'!D130,-2) -> 0 | Q27: =+ROUND(E27,-2)-ROUND('Barclays International YTD'!D36,-2) -> 0 | R27: =+ROUND(F27,-2)-ROUND('Head Office YTD'!D26,-2) -> 0 | S27: =+ROUND(G27,-2)-ROUND('Group PH'!D20,-2) -> -1100 | U27: =ROUND(B27,-2)-ROUND(B25,-2)-ROUND(B26,-2) -> 0 | V27: =ROUND(C27,-2)-ROUND(C25,-2)-ROUND(C26,-2) -> 0 | W27: =ROUND(D27,-1)-ROUND(D25,-1)-ROUND(D26,-1) -> 0 | X27: =ROUND(E27,-1)-ROUND(E25,-1)-ROUND(E26,-1) -> 0 | Y27: =ROUND(F27,-1)-ROUND(F25,-1)-ROUND(F26,-1) -> 0 | Z27: =ROUND(G27,-2)-ROUND(G25,-2)-ROUND(G26,-2) -> 0 | AB27: #REF! | AC27: #REF! | AD27: #REF! | AE27: #REF!
A29: Return on average tangible shareholders' equity excluding litigation and conduct | B29: 0.167 | C29: 0.071 | D29: 0.173 | E29: 0.087 | F29: n/m | G29: 0.085 | N29: =ROUND(B29,3)-ROUND('Barclays UK YTD'!D44,3) -> 0 | O29: =ROUND(C29,3)-ROUND('Barclays International YTD'!D94,3) -> 0 | P29: =ROUND(D29,3)-ROUND('Barclays International YTD'!D137,3) -> 0 | Q29: =ROUND(E29,3)-ROUND('Barclays International YTD'!D44,3) -> 0 | S29: =ROUND(G29,3)-ROUND('Group PH'!D28,3) -> -0.011 | AB29: #REF! | AC29: #REF! | AE29: #REF!
A31: Basic earnings per ordinary share
A32: Basic weighted average number of shares (m) | G32: 17075
A34: Basic earnings per ordinary share excluding litigation and conduct | G34: 21.9 | J34: EPS | K34: =G34-G22/G32*100 -> 0.037628111 | S34: =+ROUND(G34,0)-ROUND('Group PH'!D30,0) -> 16 | AE34: #REF!

Sheet Group performance measures excl
A1: Performance measures excluding litigation and conduct
A3: Barclays Group
B4: Q120 | D4: Q419 | E4: Q319 | F4: Q219 | G4: Q119 | I4: Q418 | J4: Q318 | K4: Q218
A5: Cost: income ratio | B5: £m | D5: £m | E5: £m | F5: £m | G5: £m | I5: £m | J5: £m | K5: £m
A6: Total operating expenses | B6: -3263 | D6: -3701 | E6: -4861 | F6: -3554 | G6: -3318 | I6: -4093 | J6: -3434 | K6: -3391
A7: Impact of litigation and conduct | B7: 10.340854 | D7: 167.24226 | E7: 1568 | F7: 52.709985 | G7: 60.842181 | I7: 60.12961 | J7: 104.85113 | K7: 81.168594
A8: Operating expenses | B8: -3252.6591 | D8: -3533.7577 | E8: -3293 | F8: -3501 | G8: -3257.1578 | I8: -4032.8704 | J8: -3329.1489 | K8: -3309.8314
A10: Total income | B10: 6283 | D10: 5301 | E10: 5541 | F10: 5538 | G10: 5252 | I10: 5073 | J10: 5129 | K10: 5576
A12: Cost: income ratio excluding litigation and conduct | B12: 0.52 | D12: 0.67 | E12: 0.59 | F12: 0.63 | G12: 0.62 | I12: 0.79 | J12: 0.65 | K12: 0.59
A14: Profit before tax
A15: Profit before tax | B15: 913 | D15: 1097 | E15: 246 | F15: 1531 | G15: 1483 | I15: 374 | J15: 1461 | K15: 1895
A16: Impact of litigation and conduct | B16: 10.340854 | D16: 167.24226 | E16: 1568 | F16: 52.709985 | G16: 60.842181 | I16: 60.12961 | J16: 104.85113 | K16: 81.168594
A17: Profit before tax excluding litigation and conduct | B17: 923.34085 | D17: 1264.2423 | E17: 1814 | F17: 1583.71 | G17: 1543.8422 | I17: 434.12961 | J17: 1565.8511 | K17: 1976.1686
A19: Profit attributable to ordinary equity holders of the parent
A20: Attributable profit/(loss) | B20: 605 | D20: 681 | E20: -292 | F20: 1034 | G20: 1038 | I20: -14 | J20: 1050 | K20: 1279
A21: Post-tax impact of litigation and conduct | B21: -0.59906317 | D21: 122.25437 | E21: 1525 | F21: 40.43745 | G21: 46 | I21: 62 | J21: 85 | K21: 59
A22: Profit attributable to ordinary equity holders of the parent excluding litigation and conduct | B22: 604.40094 | D22: 803.25437 | E22: 1232.8386 | F22: 1074.4374 | G22: 1083.7422 | I22: 47.871069 | J22: 1134.9909 | K22: 1337.641
A24: Return on average tangible shareholders' equity | B24: £bn | D24: £bn | E24: £bn | F24: £bn | G24: £bn | I24: £bn | J24: £bn | K24: £bn
A25: Average shareholders' equity | B25: 55200 | D25: 54500 | E25: 56400 | F25: 54000 | G25: 53200 | I25: 52219.667 | J25: 52528.167 | K25: 51316.5
A26: Average goodwill and intangibles | B26: -8200 | D26: -8100 | E26: -8 | F26: -7.8 | G26: -8 | I26: -7.9 | J26: -7.9 | K26: -7.8
A27: Average tangible shareholders' equity | B27: 46994.626 | D27: 46426.648 | E27: 48351.201 | F27: 46207.655 | G27: 45246.744 | I27: 44290.54 | J27: 44645.617 | K27: 43470.462
A29: Return on average tangible shareholders' equity excluding litigation and conduct | B29: 0.051 | D29: 0.069 | E29: 0.102 | F29: 0.093 | G29: 0.096 | I29: 0.004 | J29: 0.102 | K29: 0.123
A31: Basic earnings per ordinary share
A32: Basic weighted average number of shares (m) | B32: 17278.133 | D32: 17200.217 | E32: 17192.057 | F32: 17177.714 | G32: 17110.903 | I32: 17075.249 | J32: 17073.68 | K32: 17066.757
A34: Basic earnings per ordinary share excluding litigation and conduct | B34: 3.4980685 | D34: 4.6700247 | E34: 7.1709778 | F34: 6.2548337 | G34: 6.3336352 | I34: 0.28620999 | J34: 6.6358918 | K34: 7.8435579

Sheet BUK performance measures excl
A1: Barclays UK
B2: Q120 | D2: Q419 | E2: Q319 | F2: Q219 | G2: Q119 | I2: Q418 | J2: Q318 | K2: Q218
A3: Cost: income ratio | B3: £m | D3: £m | E3: £m | F3: £m | G3: £m | I3: £m | J3: £m | K3: £m
A4: Total operating expenses | B4: -1028 | D4: -1122 | E4: -2432 | F4: -1063 | G4: -1002 | I4: -1175 | J4: -1042 | K4: -971
A5: Impact of litigation and conduct | B5: 4.7742343 | D5: 57.87055 | E5: 1480 | F5: 40.871671 | G5: 3.0397 | I5: 15.360694 | J5: 53.790523 | K5: 3
A6: Operating expenses | B6: -1023.2258 | D6: -1064.1294 | E6: -952 | F6: -1022 | G6: -998.9603 | I6: -1159.6393 | J6: -988 | K6: -968
A8: Total income | B8: 1704 | D8: 1959 | E8: 1846 | F8: 1771 | G8: 1777 | I8: 1863 | J8: 1896 | K8: 1836
A10: Cost: income ratio excluding litigation and conduct | B10: 0.6 | D10: 0.54 | E10: 0.52 | F10: 0.58 | G10: 0.56 | I10: 0.62 | J10: 0.52 | K10: 0.53
A12: Profit before tax
